Workbook
Name ForecastHorizon: '[1]Controls and README'!$C$8
Name ForecastRound: '[1]Controls and README'!$C$4
Name ForecastVersion: '[1]Controls and README'!$C$5
Name mpc_fcst_end: [1]VAR_controls!#REF!
Name mpc_fcst_start: [1]VAR_controls!#REF!
Name StartDate: '[1]Controls and README'!$C$3
Name STIFHorizon: '[1]Controls and README'!$C$7

Sheet FAME Persistence2
A1: 122 | B1: Estimation_data
A2: Data_FAME (2) | B2: $BH$10 | C2: A1:A157 | D2: CONV2QA(stif_pu_wgt.m) | E2: 46078.88 | F2: TRUE | G2: CONV2QA(stif_pu_wgt.m) | H2: 1990 | I2: 2028 | J2: 0 | K2: Quarterly | L2: FALSE | M2: TRUE | N2: FALSE
A3: Data_FAME (2) | B3: $BG$10 | C3: A1:A157 | D3: CONV2QA(STIF_GDS_XEATFNAB_wgt.m) | E3: 46078.88 | F3: TRUE | G3: CONV2QA(STIF_GDS_XEATFNAB_wgt.m) | H3: 1990 | I3: 2028 | J3: 0 | K3: Quarterly | L3: FALSE | M3: TRUE | N3: FALSE
A4: Data_FAME (2) | B4: $BF$10 | D4: Refresh | E4: 0
A5: Data_FAME (2) | B5: $D$10 | C5: A1:A157 | D5: N25_cpisa_FIN.q | E5: 46078.81 | F5: TRUE | G5: N25_cpisa_FIN.q | H5: 1990 | I5: 2028 | J5: 0 | K5: Quarterly | L5: FALSE | M5: TRUE | N5: FALSE
A6: Data_FAME (2) | B6: $A$10 | C6: A1:A157 | D6: FAMEDATE | E6: 46078.814 | F6: TRUE | G6: FAMEDATE | H6: 1990 | I6: 2028 | J6: 0 | K6: Quarterly | L6: FALSE | M6: TRUE | N6: FALSE
A7: Data_FAME (2) | B7: $B$10 | C7: A1:A161 | D7: conv2qa(X12(stifidx.m,MULT,1990m2,2025m12)) | E7: 46078.816 | F7: TRUE | G7: conv2qa(X12(stifidx.m,MULT,1990m2,2025m12)) | H7: 1990 | I7: 2029 | J7: 0 | K7: Quarterly | L7: FALSE | M7: TRUE | N7: FALSE
A8: Data_FAME (2) | B8: $C$10 | C8: A1:A157 | D8: conv2qa(X12(fprojm(stifidx_clothingadjusted.m,stifidx.m,"L"),MULT,1990m2,2025m12)) | E8: 46078.817 | F8: TRUE | G8: conv2qa(X12(fprojm(stifidx_clothingadjusted.m,stifidx.m,"L"),MULT,1990m2,2025m12)) | H8: 1990 | I8: 2028 | J8: 0 | K8: Quarterly | L8: FALSE | M8: TRUE | N8: FALSE
A9: Data_FAME (2) | B9: $H$10 | C9: A1:A157 | D9: conv2qa(X12(stif_gds_xeatfnab.m,MULT,1990m2,2025m12)) | E9: 46078.818 | F9: TRUE | G9: conv2qa(X12(stif_gds_xeatfnab.m,MULT,1990m2,2025m12)) | H9: 1990 | I9: 2028 | J9: 0 | K9: Quarterly | L9: FALSE | M9: TRUE | N9: FALSE
A10: Data_FAME (2) | B10: $J$10 | C10: A1:A157 | D10: conv2qa(X12(stif_fnab.m,MULT,1990m2,2025m12)) | E10: 46078.818 | F10: TRUE | G10: conv2qa(X12(stif_fnab.m,MULT,1990m2,2025m12)) | H10: 1990 | I10: 2028 | J10: 0 | K10: Quarterly | L10: FALSE | M10: TRUE | N10: FALSE
A11: Data_FAME (2) | B11: $O$10 | D11: Refresh | E11: 0 | F11: FALSE
A12: Data_FAME (2) | B12: $R$10 | C12: A1:A157 | D12: mod_gdpkp.q | E12: 0 | F12: TRUE | G12: mod_gdpkp.q | H12: 1990 | I12: 2028 | J12: 0 | K12: Quarterly | L12: FALSE | M12: TRUE | N12: FALSE
A13: Data_FAME (2) | B13: $S$10 | D13: Refresh | E13: 0 | F13: FALSE
A14: Data_FAME (2) | B14: $U$10 | C14: A1:A157 | D14: mod_capu.q | E14: 46078.819 | F14: TRUE | G14: mod_capu.q | H14: 1990 | I14: 2028 | J14: 0 | K14: Quarterly | L14: FALSE | M14: TRUE | N14: FALSE
A15: Data_FAME (2) | B15: $V$10 | D15: Refresh | E15: 0 | F15: FALSE
A16: Data_FAME (2) | B16: $X$10 | C16: A1:A157 | D16: mod_hrs.q | E16: 46078.819 | F16: TRUE | G16: mod_hrs.q | H16: 1990 | I16: 2028 | J16: 0 | K16: Quarterly | L16: FALSE | M16: TRUE | N16: FALSE
A17: Data_FAME (2) | B17: $Y$10 | D17: Refresh | E17: 0 | F17: FALSE
A18: Data_FAME (2) | B18: $AA$10 | C18: A1:A157 | D18: mod_unemp.q | E18: 46078.819 | F18: TRUE | G18: mod_unemp.q | H18: 1990 | I18: 2028 | J18: 0 | K18: Quarterly | L18: FALSE | M18: TRUE | N18: FALSE
A19: Data_FAME (2) | B19: $AB$10 | D19: Refresh | E19: 0 | F19: FALSE
A20: Data_FAME (2) | B20: $AD$10 | D20: #N/A | E20: 0 | F20: TRUE | H20: 1990 | I20: 2028 | J20: 0 | K20: Quarterly | L20: FALSE | M20: TRUE | N20: FALSE
A21: Data_FAME (2) | B21: $AE$10 | C21: A1:A157 | D21: conv2qa(OVERLAY(KAJ2_DP.M,KAJ2_HIST.M)) | E21: 0 | F21: TRUE | G21: conv2qa(OVERLAY(KAJ2_DP.M,KAJ2_HIST.M)) | H21: 1990 | I21: 2028 | J21: 0 | K21: Quarterly | L21: FALSE | M21: TRUE | N21: FALSE
A22: Data_FAME (2) | B22: $AF$10 | D22: Refresh | E22: 0 | F22: FALSE
A23: Data_FAME (2) | B23: $AH$10 | D23: #N/A | E23: 0 | F23: TRUE | H23: 1990 | I23: 2028 | J23: 0 | K23: Quarterly | L23: FALSE | M23: TRUE | N23: FALSE
A24: Data_FAME (2) | B24: $AI$10 | C24: A1:A157 | D24: CONV2QA(SERI.B) | E24: 0 | F24: TRUE | G24: CONV2QA(SERI.B) | H24: 1990 | I24: 2028 | J24: 0 | K24: Quarterly | L24: FALSE | M24: TRUE | N24: FALSE
A25: Data_FAME (2) | B25: $AJ$10 | D25: Refresh | E25: 0 | F25: FALSE
A26: Data_FAME (2) | B26: $AL$10 | D26: #N/A | E26: 0 | F26: TRUE | H26: 1990 | I26: 2028 | J26: 0 | K26: Quarterly | L26: FALSE | M26: TRUE | N26: FALSE
A27: Data_FAME (2) | B27: $AM$10 | D27: Refresh | E27: 0 | F27: FALSE
A28: Data_FAME (2) | B28: $AO$10 | C28: A1:A157 | D28: mod_rgawqe.q | E28: 46078.819 | F28: TRUE | G28: mod_rgawqe.q | H28: 1990 | I28: 2028 | J28: 0 | K28: Quarterly | L28: FALSE | M28: TRUE | N28: FALSE
A29: Data_FAME (2) | B29: $AP$10 | D29: Refresh | E29: 0 | F29: FALSE
A30: Data_FAME (2) | B30: $AR$10 | D30: #N/A | E30: 0 | F30: TRUE | H30: 1990 | I30: 2028 | J30: 0 | K30: Quarterly | L30: FALSE | M30: TRUE | N30: FALSE
A31: Data_FAME (2) | B31: $AS$10 | C31: A1:A157 | D31: mod_pmdef.q | E31: 0 | F31: TRUE | G31: mod_pmdef.q | H31: 1990 | I31: 2028 | J31: 0 | K31: Quarterly | L31: FALSE | M31: TRUE | N31: FALSE
A32: Data_FAME (2) | B32: $AT$10 | C32: A1:A157 | D32: N25_pmdef_FIN.q | E32: 0 | F32: TRUE | G32: N25_pmdef_FIN.q | H32: 1990 | I32: 2028 | J32: 0 | K32: Quarterly | L32: FALSE | M32: TRUE | N32: FALSE
A33: Data_FAME (2) | B33: $AU$10 | D33: Refresh | E33: 0 | F33: FALSE
A34: Data_FAME (2) | B34: $AW$10 | C34: A1:A157 | D34: mod_cpif.q | E34: 46078.819 | F34: TRUE | G34: mod_cpif.q | H34: 1990 | I34: 2028 | J34: 0 | K34: Quarterly | L34: FALSE | M34: TRUE | N34: FALSE
A35: Data_FAME (2) | B35: $AX$10 | D35: Refresh | E35: 0 | F35: FALSE
A36: Data_FAME (2) | B36: $AZ$10 | C36: A1:A157 | D36: PUB12MEDIAN.Q | E36: 46078.819 | F36: TRUE | G36: PUB12MEDIAN.Q | H36: 1990 | I36: 2028 | J36: 0 | K36: Quarterly | L36: FALSE | M36: TRUE | N36: FALSE
A37: Data_FAME (2) | B37: $BA$10 | C37: A1:A157 | D37: CONV2QA(cgrp.m) | E37: 0 | F37: TRUE | G37: CONV2QA(cgrp.m) | H37: 1990 | I37: 2028 | J37: 0 | K37: Quarterly | L37: FALSE | M37: TRUE | N37: FALSE
A38: Data_FAME (2) | B38: $BB$10 | C38: A1:A157 | D38: fprojm(PUB12MEDIAN.Q,CONV2QA(cgrp.m),""L"") | E38: 0 | F38: TRUE | G38: fprojm(PUB12MEDIAN.Q,CONV2QA(cgrp.m),""L"") | H38: 1990 | I38: 2028 | J38: 0 | K38: Quarterly | L38: FALSE | M38: TRUE | N38: FALSE
A39: Data_FAME (2) | B39: $BC$10 | D39: Refresh | E39: 0 | F39: FALSE
A40: Data_FAME (2) | B40: $F$10 | C40: A1:A157 | D40: conv2qa(X12(stif_srv.m,MULT,1990m2,2025m12)) | E40: 46078.819 | F40: TRUE | G40: conv2qa(X12(stif_srv.m,MULT,1990m2,2025m12)) | H40: 1990 | I40: 2028 | J40: 0 | K40: Quarterly | L40: FALSE | M40: TRUE | N40: FALSE
A41: Data_FAME (2) | B41: $M$10 | C41: A1:A157 | D41: conv2qa(X12(cpi_aggregation(stif_fnab.m, booze.m, fags.m,#,#,#,#,#,#,#,#,#,#,#,#,#,#,#,#,#),MULT,1990m2,2025m12)) | E41: 46078.854 | F41: TRUE | G41: conv2qa(X12(cpi_aggregation(stif_fnab.m, booze.m, fags.m,#,#,#,#,#,#,#,#,#,#,#,#,#,#,#,#,#),MULT,1990m2,2025m12)) | H41: 1990 | I41: 2028 | J41: 0 | K41: Quarterly | L41: FALSE | M41: TRUE | N41: FALSE
A42: Data_FAME (2) | B42: $L$10 | C42: A1:A157 | D42: conv2qa(cpi_aggregation(stif_fnab.m, booze.m, fags.m,#,#,#,#,#,#,#,#,#,#,#,#,#,#,#,#,#)) | E42: 46078.854 | F42: TRUE | G42: conv2qa(cpi_aggregation(stif_fnab.m, booze.m, fags.m,#,#,#,#,#,#,#,#,#,#,#,#,#,#,#,#,#)) | H42: 1990 | I42: 2028 | J42: 0 | K42: Quarterly | L42: FALSE | M42: TRUE | N42: FALSE
A43: Data_FAME (2) | B43: $P$10 | C43: A1:A157 | D43: conv2qa(X12(stif_pu.m,MULT,1990m2,2028m12)) | E43: 46078.861 | F43: TRUE | G43: conv2qa(X12(stif_pu.m,MULT,1990m2,2028m12)) | H43: 1990 | I43: 2028 | J43: 0 | K43: Quarterly | L43: FALSE | M43: TRUE | N43: FALSE
A44: Data_FAME (2) | B44: $BI$10 | C44: A1:A157 | D44: CONV2QA(stif_srv_wgt.m) | E44: 46078.88 | F44: TRUE | G44: CONV2QA(stif_srv_wgt.m) | H44: 1990 | I44: 2028 | J44: 0 | K44: Quarterly | L44: FALSE | M44: TRUE | N44: FALSE
A45: Data_FAME (2) | B45: $BK$10 | C45: A1:A157 | D45: CONV2QA(stif_fnab_wgt.m) | E45: 46078.88 | F45: TRUE | G45: CONV2QA(stif_fnab_wgt.m) | H45: 1990 | I45: 2028 | J45: 0 | K45: Quarterly | L45: FALSE | M45: TRUE | N45: FALSE
A46: Data_FAME (2) | B46: $BL$10 | C46: A1:A157 | D46: CONV2QA(booze_wgt.m) | E46: 46078.88 | F46: TRUE | G46: CONV2QA(booze_wgt.m) | H46: 1990 | I46: 2028 | J46: 0 | K46: Quarterly | L46: FALSE | M46: TRUE | N46: FALSE
A47: Data_FAME (2) | B47: $BM$10 | C47: A1:A157 | D47: CONV2QA(fags_wgt.m) | E47: 46078.88 | F47: TRUE | G47: CONV2QA(fags_wgt.m) | H47: 1990 | I47: 2028 | J47: 0 | K47: Quarterly | L47: FALSE | M47: TRUE | N47: FALSE
A48: Data_FAME (2) | B48: $Q$10 | D48: Refresh | E48: 0 | F48: FALSE
A49: Estimation_data | B49: $L$12 | C49: A1:A143 | D49: 8.6373834 | E49: 46136.648 | F49: TRUE | G49: BPROJA(conv2qa(cgrp.m),PUB12MEDIAN.Q,"E") | H49: 1990Q2 | I49: 2025Q4 | J49: 0 | K49: Quarterly | L49: FALSE | M49: FALSE | N49: FALSE
A50: Estimation_data | B50: $C$12 | C50: A1:A143 | D50: 37.291624 | E50: 46136.768 | F50: TRUE | G50: conv2qa(X12(stif_srv.m,MULT,1990m2,2025m12)) | H50: 1990Q2 | I50: 2025Q4 | J50: 0 | K50: Quarterly | L50: FALSE | M50: FALSE | N50: FALSE
A51: Estimation_data | B51: $D$12 | C51: A1:A143 | D51: 109.4919 | E51: 46136.768 | F51: TRUE | G51: conv2qa(X12(stif_gds_xeatfnab.m,MULT,1990m2,2025m12)) | H51: 1990Q2 | I51: 2025Q4 | J51: 0 | K51: Quarterly | L51: FALSE | M51: FALSE | N51: FALSE
A52: Estimation_data | B52: $E$12 | C52: A1:A143 | D52: 46.254605 | E52: 46136.768 | F52: TRUE | G52: conv2qa(X12(cpi_aggregation(stif_fnab.m, booze.m, fags.m,#,#,#,#,#,#,#,#,#,#,#,#,#,#,#,#,#),MULT,1990m2,2025m12)) | H52: 1990Q2 | I52: 2025Q4 | J52: 0 | K52: Quarterly | L52: FALSE | M52: FALSE | N52: FALSE
A53: Estimation_data | B53: $F$12 | C53: A1:A143 | D53: 55.346352 | E53: 46136.768 | F53: TRUE | G53: conv2qa(X12(stif_fnab.m,MULT,1990m2,2025m12)) | H53: 1990Q2 | I53: 2025Q4 | J53: 0 | K53: Quarterly | L53: FALSE | M53: FALSE | N53: FALSE
A54: Estimation_data | B54: $G$12 | C54: A1:A143 | D54: 61.765236 | E54: 46136.768 | F54: TRUE | G54: conv2qa(X12(booze.m,MULT,1990m2,2025m12)) | H54: 1990Q2 | I54: 2025Q4 | J54: 0 | K54: Quarterly | L54: FALSE | M54: FALSE | N54: FALSE
A55: Estimation_data | B55: $H$12 | C55: A1:A143 | D55: 17.935207 | E55: 46136.768 | F55: TRUE | G55: conv2qa(X12(fags.m,MULT,1990m2,2025m12)) | H55: 1990Q2 | I55: 2025Q4 | J55: 0 | K55: Quarterly | L55: FALSE | M55: FALSE | N55: FALSE
A56: Estimation_data | B56: $I$12 | C56: A1:A143 | D56: 33.809155 | E56: 46136.768 | F56: TRUE | G56: conv2qa(X12(stif_pu.m,MULT,1990m2,2025m12)) | H56: 1990Q2 | I56: 2025Q4 | J56: 0 | K56: Quarterly | L56: FALSE | M56: FALSE | N56: FALSE
A57: Estimation_data | B57: $J$12 | C57: A1:A143 | D57: 0.57773628 | E57: 46136.768 | F57: TRUE | G57: pub_pmdef.q | H57: 1990Q2 | I57: 2025Q4 | J57: 0 | K57: Quarterly | L57: FALSE | M57: FALSE | N57: FALSE
A58: Estimation_data | B58: $K$12 | C58: A1:A143 | D58: 93.068646 | E58: 46136.768 | F58: TRUE | G58: pub_eer.q | H58: 1990Q2 | I58: 2025Q4 | J58: 0 | K58: Quarterly | L58: FALSE | M58: FALSE | N58: FALSE
A59: Estimation_data | B59: $B$12 | C59: A1:A143 | D59: 55.216192 | E59: 46136.768 | F59: TRUE | G59: conv2qa(X12(stifidx.m,MULT,1990m2,2025m12)) | H59: 1990Q2 | I59: 2025Q4 | J59: 0 | K59: Quarterly | L59: FALSE | M59: FALSE | N59: FALSE
A60: M26_STIF_BMK | B60: $D$12 | C60: A1:A124 | D60: 120.21246 | E60: 46136.771 | F60: TRUE | G60: conv2qa(X12(M26_stif_gds_xeatfnab_bmk.m,MULT,1996m1,2026m12)) | H60: 1996Q1 | I60: 2026Q4 | J60: 0 | K60: Quarterly | L60: FALSE | M60: FALSE | N60: FALSE
... A78: M26_STIF_BMK | B78: $J$12 | C78: A1:A134 | D78: 68.274786 | E78: 46139.585 | F78: TRUE | G78: M26_cpisa_bmk2.q | H78: 1996Q1 | I78: 2029Q2 | J78: 0 | K78: Quarterly | L78: FALSE | M78: FALSE | N78: FALSE
A79: Data_FAME | B79: $AD$10 | D79: Refresh | E79: 0 | F79: FALSE
A80: Data_FAME | B80: $AE$10 | D80: Refresh | E80: 0 | F80: FALSE
A81: Data_FAME | B81: $N$10 | D81: Refresh | E81: 0 | F81: FALSE
A82: Data_FAME | B82: $BA$10 | D82: Refresh | E82: 0 | F82: FALSE
A83: Data_FAME | B83: $R$10 | D83: Refresh | E83: 0 | F83: FALSE
A84: Data_FAME | B84: $AT$10 | D84: Refresh | E84: 0 | F84: FALSE
A85: Data_FAME | B85: $A$10 | D85: Refresh | E85: 0 | F85: FALSE
A86: Data_FAME | B86: $AA$10 | D86: Refresh | E86: 0 | F86: FALSE
A87: Data_FAME | B87: $AC$10 | D87: Refresh | E87: 0 | F87: FALSE
A88: Data_FAME | B88: $L$10 | D88: Refresh | E88: 0 | F88: FALSE
A89: Data_FAME | B89: $W$10 | D89: Refresh | E89: 0 | F89: FALSE
A90: Data_FAME | B90: $AR$10 | D90: Refresh | E90: 0 | F90: FALSE
... A123: Sheet2 | B123: $K$5 | D123: Refresh | E123: 0 | F123: FALSE

Sheet datav2
A1: Date | B1: cpi | C1: cpi_a | D1: cpi_f | E1: services | F1: core_gds | G1: food | H1: food_at_nsa | I1: food_at | J1: energy | K1: energy_f | L1: gdpkp | M1: gdpkp_f | N1: capu | O1: capu_f | P1: hrs | Q1: hrs_f | R1: unemp | S1: unemp_f | T1: wage | U1: wage_f | V1: eer | W1: eer_f | X1: ois_rate | Y1: bank_rate | Z1: bank_rate_f | AA1: pmdef | AB1: pmdef_f | AC1: pmdef_xf | AD1: cpif | AE1: cpif_f | AF1: infl_exp | AG1: infl_exp_f | AH1: fat_wgt | AI1: cf_wgt | AJ1: e_wgt | AK1: s_wgt | AL1: infl_target | AM1: ied
A2: 33054 | B2: 55.216192 | C2: 53.449601 | D2: 55.931591 | E2: 37.291624 | F2: 109.4919 | G2: 55.346352 | H2: 46.757461 | I2: 46.254605 | J2: 33.809155 | K2: 33.809155 | L2: 381997 | M2: 381997 | N2: -1.1483808 | O2: 0.93596216 | P2: 906588.84 | Q2: 906588.84 | R2: 0.069184781 | S2: 0.069184781 | T2: 189.32838 | U2: 189.32838 | V2: 93.068646 | W2: 93.068646 | X2: 14.519134 | Y2: 14.875 | Z2: 14.875 | AA2: 0.57773628 | AB2: 0.57773628 | AC2: 0.60985266 | AD2: 67.416856 | AE2: 67.416856 | AF2: 8.6373834 | AG2: 8.6373834 | AH2: 251 | AI2: 359 | AJ2: 96 | AK2: 294 | AL2: 2 | AM2: =+AF2-AL2 -> 6.6373834
A3: 33146 | B3: 56.369272 | C3: 54.565685 | D3: 56.730638 | E3: 38.226404 | F3: 110.77076 | G3: 56.069625 | H3: 46.959972 | I3: 47.031491 | J3: 35.502014 | K3: 35.502014 | L3: 377831 | M3: 377831 | N3: -1.7358221 | O3: -0.79049292 | P3: 901813.5 | Q3: 901813.5 | R3: 0.070779647 | S3: 0.070779647 | T3: 193.61239 | U3: 193.61239 | V3: 99.445968 | W3: 99.445968 | X3: 14.377204 | Y3: 14.875 | Z3: 14.875 | AA3: 0.55930606 | AB3: 0.55930606 | AC3: 0.59130693 | AD3: 68.109698 | AE3: 68.109698 | AF3: 9.1039566 | AG3: 9.1039566 | AH3: 251 | AI3: 359 | AJ3: 96 | AK3: 294 | AL3: 2 | AM3: =+AF3-AL3 -> 7.1039566
A4: 33238 | B4: 57.494732 | C4: 55.655628 | D4: 57.774359 | E4: 39.201503 | F4: 112.05037 | G4: 57.003542 | H4: 47.50451 | I4: 47.936474 | J4: 36.723481 | K4: 36.723481 | L4: 375916 | M4: 375916 | N4: -2.1830843 | O4: -1.1706663 | P4: 892410.87 | Q4: 892410.87 | R4: 0.074650616 | S4: 0.074650616 | T4: 197.31141 | U4: 197.31141 | V4: 99.670858 | W4: 99.670858 | X4: 13.268016 | Y4: 13.9531 | Z4: 13.9531 | AA4: 0.56615029 | AB4: 0.56615029 | AC4: 0.5885035 | AD4: 69.42033 | AE4: 69.42033 | AF4: 7.4794737 | AG4: 7.4794737 | AH4: 251 | AI4: 359 | AJ4: 96 | AK4: 294 | AL4: 2 | AM4: =+AF4-AL4 -> 5.4794737
A5: 33328 | B5: 58.131185 | C5: 56.271618 | D5: 58.016017 | E5: 40.047704 | F5: 112.98292 | G5: 57.575944 | H5: 48.473466 | I5: 48.483131 | J5: 36.121607 | K5: 36.121607 | L5: 374060 | M5: 374060 | N5: -2.9343664 | O5: -1.255856 | P5: 881370.83 | Q5: 881370.83 | R5: 0.079969483 | S5: 0.079969483 | T5: 199.57143 | U5: 199.57143 | V5: 99.118131 | W5: 99.118131 | X5: 12.723411 | Y5: 13.3992 | Z5: 13.3992 | AA5: 0.56293382 | AB5: 0.56293382 | AC5: 0.59734507 | AD5: 70.402484 | AE5: 70.402484 | AF5: 7.1724561 | AG5: 7.1724561 | AH5: 242 | AI5: 363 | AJ5: 93 | AK5: 302 | AL5: 2 | AM5: =+AF5-AL5 -> 5.1724561
A6: 33419 | B6: 59.827705 | C6: 57.9136 | D6: 60.59482 | E6: 41.709306 | F6: 115.1372 | G6: 58.344421 | H6: 50.505217 | I6: 49.975838 | J6: 37.362098 | K6: 37.362098 | L6: 373608 | M6: 373608 | N6: -3.3312328 | O6: -1.273024 | P6: 869788.47 | Q6: 869788.47 | R6: 0.086627038 | S6: 0.086627038 | T6: 204.08804 | U6: 204.08804 | V6: 96.421142 | W6: 96.421142 | X6: 11.097574 | Y6: 11.7379 | Z6: 11.7379 | AA6: 0.57235316 | AB6: 0.57235316 | AC6: 0.60942136 | AD6: 71.079089 | AE6: 71.079089 | AF6: 5.5856456 | AG6: 5.5856456 | AH6: 242 | AI6: 363 | AJ6: 93 | AK6: 302 | AL6: 2 | AM6: =+AF6-AL6 -> 3.5856456
A7: 33511 | B7: 60.749441 | C7: 58.805692 | D7: 61.129417 | E7: 42.478114 | F7: 116.63678 | G7: 58.886712 | H7: 50.449029 | I7: 50.515686 | J7: 38.223615 | K7: 38.223615 | L7: 372878 | M7: 372878 | N7: -3.4757524 | O7: -1.2520863 | P7: 859520.46 | Q7: 859520.46 | R7: 0.09159133 | S7: 0.09159133 | T7: 208.2244 | U7: 208.2244 | V7: 95.722653 | W7: 95.722653 | X7: 10.282062 | Y7: 10.7981 | Z7: 10.7981 | AA7: 0.58356049 | AB7: 0.58356049 | AC7: 0.61934117 | AD7: 71.94639 | AE7: 71.94639 | AF7: 4.6085185 | AG7: 4.6085185 | AH7: 242 | AI7: 363 | AJ7: 93 | AK7: 302 | AL7: 2 | AM7: =+AF7-AL7 -> 2.6085185
A8: 33603 | B8: 61.5371 | C8: 59.568663 | D8: 61.822885 | E8: 43.254296 | F8: 117.83569 | G8: 59.515813 | H8: 50.749747 | I8: 51.223588 | J8: 38.311037 | K8: 38.311037 | L8: 373357 | M8: 373357 | N8: -3.1182875 | O8: -1.0417908 | P8: 851930 | Q8: 851930 | R8: 0.094575166 | S8: 0.094575166 | T8: 211.35106 | U8: 211.35106 | V8: 96.172297 | W8: 96.172297 | X8: 10.071213 | Y8: 10.375 | Z8: 10.375 | AA8: 0.57552587 | AB8: 0.57552587 | AC8: 0.61287173 | AD8: 72.918164 | AE8: 72.918164 | AF8: 4.4125673 | AG8: 4.4125673 | AH8: 242 | AI8: 363 | AJ8: 93 | AK8: 302 | AL8: 2 | AM8: =+AF8-AL8 -> 2.4125673
A9: 33694 | B9: 62.131083 | C9: 60.143593 | D9: 62.056834 | E9: 43.882111 | F9: 118.7579 | G9: 59.959978 | H9: 51.685557 | I9: 51.670967 | J9: 38.258535 | K9: 38.258535 | L9: 373317 | M9: 373317 | N9: -3.3500751 | O9: -1.1690213 | P9: 847165.67 | Q9: 847165.67 | R9: 0.097007586 | S9: 0.097007586 | T9: 215.27103 | U9: 215.27103 | V9: 95.797952 | W9: 95.797952 | X9: 10.079292 | Y9: 10.375 | Z9: 10.375 | AA9: 0.56924052 | AB9: 0.56924052 | AC9: 0.61394997 | AD9: 73.684026 | AE9: 73.684026 | AF9: 4.3453333 | AG9: 4.3453333 | AH9: 244 | AI9: 360 | AJ9: 91 | AK9: 305 | AL9: 2 | AM9: =+AF9-AL9 -> 2.3453333
A10: 33785 | B10: 62.416759 | C10: 60.420047 | D10: 63.194403 | E10: 44.452914 | F10: 118.72539 | G10: 59.723829 | H10: 52.427892 | I10: 51.90606 | J10: 38.383855 | K10: 38.383855 | L10: 372751 | M10: 372751 | N10: -3.1236345 | O10: -1.8203614 | P10: 847646.6 | Q10: 847646.6 | R10: 0.09785394 | S10: 0.09785394 | T10: 216.52634 | U10: 216.52634 | V10: 97.573482 | W10: 97.573482 | X10: 9.7404194 | Y10: 10.0471 | Z10: 10.0471 | AA10: 0.56506054 | AB10: 0.56506054 | AC10: 0.60791183 | AD10: 74.734655 | AE10: 74.734655 | AF10: 4.0467864 | AG10: 4.0467864 | AH10: 244 | AI10: 360 | AJ10: 91 | AK10: 305 | AL10: 2 | AM10: =+AF10-AL10 -> 2.0467864
A11: 33877 | B11: 62.691059 | C11: 60.685211 | D11: 63.067373 | E11: 44.967908 | F11: 118.80745 | G11: 59.567454 | H11: 51.973211 | I11: 52.023965 | J11: 38.275282 | K11: 38.275282 | L11: 374537 | M11: 374537 | N11: -3.3243309 | O11: -0.85749752 | P11: 840427.1 | Q11: 840427.1 | R11: 0.099370554 | S11: 0.099370554 | T11: 219.44681 | U11: 219.44681 | V11: 96.710815 | W11: 96.710815 | X11: 9.695813 | Y11: 9.7673 | Z11: 9.7673 | AA11: 0.56539814 | AB11: 0.56539814 | AC11: 0.60273627 | AD11: 75.563565 | AE11: 75.563565 | AF11: 3.8414337 | AG11: 3.8414337 | AH11: 244 | AI11: 360 | AJ11: 91 | AK11: 305 | AL11: 2 | AM11: =+AF11-AL11 -> 1.8414337
A12: 33969 | B12: 63.195466 | C12: 61.173856 | D12: 63.467567 | E12: 45.533479 | F12: 118.62097 | G12: 60.084592 | H12: 52.154689 | I12: 52.659248 | J12: 38.984401 | K12: 38.984401 | L12: 377418 | M12: 377418 | N12: -3.2279251 | O12: -0.27664328 | P12: 832788.39 | Q12: 832788.39 | R12: 0.10371119 | S12: 0.10371119 | T12: 221.35146 | U12: 221.35146 | V12: 84.845339 | W12: 84.845339 | X12: 7.1698732 | Y12: 7.5313 | Z12: 7.5313 | AA12: 0.59920423 | AB12: 0.59920423 | AC12: 0.64263116 | AD12: 76.644093 | AE12: 76.644093 | AF12: 3.5328715 | AG12: 3.5328715 | AH12: 244 | AI12: 360 | AJ12: 91 | AK12: 305 | AL12: 2 | AM12: =+AF12-AL12 -> 1.5328715
A13: 34059 | B13: 63.53193 | C13: 61.499755 | D13: 63.530914 | E13: 46.101573 | F13: 118.15539 | G13: 60.484175 | H13: 53.053856 | I13: 53.005409 | J13: 39.383108 | K13: 39.383108 | L13: 379370 | M13: 379370 | N13: -3.0780999 | O13: -0.54416477 | P13: 832300.53 | Q13: 832300.53 | R13: 0.10618491 | S13: 0.10618491 | T13: 221.58357 | U13: 221.58357 | V13: 83.282759 | W13: 83.282759 | X13: 5.9494269 | Y13: 6.129 | Z13: 6.129 | AA13: 0.62407768 | AB13: 0.62407768 | AC13: 0.67454707 | AD13: 77.756408 | AE13: 77.756408 | AF13: 3.0711828 | AG13: 3.0711828 | AH13: 228 | AI13: 343 | AJ13: 91 | AK13: 338 | AL13: 2 | AM13: =+AF13-AL13 -> 1.0711828
... A142: 45838 | B142: 137.87157 | C142: 137.87146 | D142: 138.04057 | E142: 142.47561 | F142: 122.70051 | G142: 140.78271 | H142: 144.80364 | I142: 144.36323 | J142: 152.26305 | K142: 153.38041 | L142: 705403 | M142: 705403 | N142: -0.53521004 | O142: -1.8925383 | P142: 1092607.1 | Q142: 1092607.1 | R142: 0.04660112 | S142: 0.04660112 | T142: 670.36599 | U142: 670.36599 | V142: 85.433745 | W142: 85.433745 | X142: 4.1790199 | Y142: 3.7371024 | Z142: 3.7425486 | AA142: 0.99181196 | AB142: 0.99106811 | AC142: 1.0097549 | AD142: 169.42098 | AE142: 169.42098 | AF142: 4.0110426 | AG142: 4.0110426 | AH142: 151.1486 | AI142: 286.3633 | AJ142: 61.6527 | AK142: 500.8354 | AL142: 2 | AM142: =+AF142-AL142 -> 2.0110426
A143: 45930 | B143: 139.17556 | C143: 139.17544 | D143: 138.97188 | E143: 143.83211 | F143: 123.18805 | G143: 142.64323 | H143: 146.02696 | I143: 146.17239 | J143: 153.78204 | K143: 152.77858 | L143: 706813.81 | M143: 706813.81 | O143: -1.6978608 | P143: 1088109.9 | Q143: 1088109.9 | R143: 0.048668948 | S143: 0.048668948 | T143: 674.78348 | U143: 675.06649 | V143: 84.985242 | W143: 84.985242 | X143: 3.9805726 | Y143: 3.623433 | Z143: 3.623433 | AA143: 0.98826679 | AB143: 0.98826679 | AC143: 1.006946 | AD143: 170.10292 | AE143: 170.10291 | AF143: 3.9691108 | AG143: 3.9691108 | AH143: 151.1486 | AI143: 286.3633 | AJ143: 61.6527 | AK143: 500.8354 | AL143: 2 | AM143: =+AF143-AL143 -> 1.9691108
A144: 46022 | B144: 139.91004 | C144: 139.90992 | D144: 139.85387 | E144: 144.83827 | F144: 123.51261 | G144: 144.14372 | H144: 146.88064 | I144: 147.33385 | J144: 153.89556 | K144: 154.08739 | L144: 708934.25 | M144: 708934.25 | O144: -1.8289475 | P144: 1089925.4 | Q144: 1089925.4 | R144: 0.049697693 | S144: 0.049697693 | U144: 680.79359 | W144: 84.479013 | Y144: 3.5100422 | Z144: 3.5100422 | AA144: 0.98263827 | AB144: 0.98263827 | AD144: 170.38249 | AE144: 170.38248 | AG144: 3.9221779 | AH144: 151.1486 | AI144: 286.3633 | AJ144: 61.6527 | AK144: 500.8354
A145: 46112 | D145: 140.96006 | H145: 148.75767 | I145: 0 | J145: 0 | K145: 152.38088 | M145: 711292.91 | O145: -1.7040186 | Q145: 1088841.3 | S145: 0.0504 | U145: 686.71173 | W145: 84.252156 | Y145: 3.4154219 | Z145: 3.4154219 | AB145: 0.97725801 | AD145: 170.76719 | AE145: 170.76718 | AG145: 3.4732572 | AH145: 146.37555 | AI145: 277.06973 | AJ145: 58.33398 | AK145: 518.22073
A146: 46203 | D146: 142.0057 | H146: 149.8334 | I146: 0 | J146: 0 | K146: 148.04947 | M146: 713598.35 | O146: -1.7237463 | Q146: 1089619.5 | S146: 0.050541252 | U146: 692.12433 | W146: 84.117539 | Y146: 3.3219454 | Z146: 3.3219454 | AB146: 0.9749504 | AD146: 171.28775 | AE146: 171.28774 | AG146: 3.2071262 | AH146: 146.73083 | AI146: 276.4363 | AJ146: 58.33497 | AK146: 518.4979
A147: 46295 | D147: 142.70719 | H147: 149.92516 | I147: 0 | J147: 0 | K147: 149.5711 | M147: 716034.92 | O147: -1.6558511 | Q147: 1090427.8 | S147: 0.050498257 | U147: 697.3824 | W147: 83.98531 | Y147: 3.3064318 | Z147: 3.3064318 | AB147: 0.97388427 | AD147: 172.08142 | AE147: 172.08141 | AG147: 2.9284517 | AH147: 146.73083 | AI147: 276.4363 | AJ147: 58.33497 | AK147: 518.4979
A148: 46387 | D148: 143.35098 | H148: 151.64689 | I148: 0 | J148: 0 | K148: 149.37929 | M148: 718746.04 | O148: -1.6089581 | Q148: 1092228.2 | S148: 0.050389561 | U148: 702.54561 | W148: 83.853892 | Y148: 3.3371672 | Z148: 3.3371672 | AB148: 0.97306004 | AD148: 172.82848 | AE148: 172.82847 | AG148: 2.7607717 | AH148: 146.73083 | AI148: 276.4363 | AJ148: 58.33497 | AK148: 518.4979
A149: 46477 | D149: 144.03329 | H149: 0 | I149: 0 | J149: 0 | K149: 148.75311 | M149: 721631.31 | O149: -1.5371047 | Q149: 1094167.4 | S149: 0.05021789 | U149: 707.66289 | W149: 83.722428 | Y149: 3.376846 | Z149: 3.376846 | AB149: 0.97240044 | AD149: 173.77928 | AE149: 173.77927 | AG149: 2.6830774 | AH149: 146.37555 | AI149: 277.06973 | AJ149: 58.33398 | AK149: 518.22073
A150: 46568 | D150: 144.76619 | H150: 0 | I150: 0 | J150: 0 | K150: 149.36955 | M150: 724747.91 | O150: -1.4586119 | Q150: 1096113.2 | S150: 0.05003043 | U150: 712.79819 | W150: 83.591451 | Y150: 3.4138167 | Z150: 3.4138167 | AB150: 0.97421349 | AD150: 174.72296 | AE150: 174.72296 | AG150: 2.6433548 | AH150: 146.73083 | AI150: 276.4363 | AJ150: 58.33497 | AK150: 518.4979
A151: 46660 | D151: 145.50721 | H151: 0 | I151: 0 | J151: 0 | K151: 149.91701 | M151: 727950.51 | O151: -1.3726282 | Q151: 1097963.2 | S151: 0.04974273 | U151: 717.99084 | W151: 83.462187 | Y151: 3.4440408 | Z151: 3.4440408 | AB151: 0.97436963 | AD151: 175.63827 | AE151: 175.63827 | AG151: 2.6218393 | AH151: 146.73083 | AI151: 276.4363 | AJ151: 58.33497 | AK151: 518.4979
A152: 46752 | D152: 146.26524 | H152: 0 | I152: 0 | J152: 0 | K152: 136.40861 | M152: 731300.17 | O152: -1.3276231 | Q152: 1100126.6 | S152: 0.049361609 | U152: 723.26555 | W152: 83.335501 | Y152: 3.469114 | Z152: 3.469114 | AB152: 0.97332131 | AD152: 176.37233 | AE152: 176.37234 | AG152: 2.609262 | AH152: 146.73083 | AI152: 276.4363 | AJ152: 58.33497 | AK152: 518.4979
A153: 46843 | D153: 147.00874 | H153: 0 | I153: 0 | J153: 0 | K153: 134.59702 | M153: 734695.69 | O153: -1.3352153 | Q153: 1103179.9 | S153: 0.048942373 | U153: 728.68905 | W153: 83.211438 | Y153: 3.4901568 | Z153: 3.4901568 | AB153: 0.97211634 | AD153: 177.09076 | AE153: 177.09077 | AG153: 2.6222316 | AH153: 146.37555 | AI153: 277.06973 | AJ153: 58.33398 | AK153: 518.22073
A154: 46934 | D154: 147.78016 | H154: 0 | I154: 0 | J154: 0 | K154: 133.93665 | M154: 738059.62 | O154: -1.2781854 | Q154: 1105659.2 | S154: 0.048451841 | U154: 734.32554 | W154: 83.089805 | Y154: 3.5168931 | Z154: 3.5168931 | AB154: 0.97121443 | AD154: 177.87613 | AE154: 177.87615 | AG154: 2.6420013 | AH154: 146.73083 | AI154: 276.4363 | AJ154: 58.33497 | AK154: 518.4979
A155: 47026 | D155: 148.54929 | H155: 0 | I155: 0 | J155: 0 | K155: 134.87225 | M155: 741431.62 | O155: -1.2382119 | Q155: 1108222.5 | S155: 0.047972324 | U155: 740.21052 | W155: 82.970359 | Y155: 3.5462896 | Z155: 3.5462896 | AB155: 0.97018549 | AD155: 178.61289 | AE155: 178.61291 | AG155: 2.6284768 | AH155: 146.73083 | AI155: 276.4363 | AJ155: 58.33497 | AK155: 518.4979
A156: 47118 | D156: 149.33243 | H156: 0 | I156: 0 | J156: 0 | K156: 135.45874 | M156: 744811.57 | O156: -1.1823681 | Q156: 1110769.1 | S156: 0.047406381 | U156: 746.35252 | W156: 82.852815 | Y156: 3.5778306 | Z156: 3.5778306 | AB156: 0.96942556 | AD156: 179.2077 | AE156: 179.20772 | AG156: 2.6276947 | AH156: 146.73083 | AI156: 276.4363 | AJ156: 58.33497 | AK156: 518.4979

Sheet datav1
A1: Date | B1: cpi | C1: cpi_a | D1: cpi_f | E1: services | F1: core_gds | G1: food | H1: food_at | I1: energy | J1: gdpkp | K1: gdpkp_f | L1: capu | M1: capu_f | N1: hrs | O1: hrs_f | P1: unemp | Q1: unemp_f | R1: wage | S1: wage_f | T1: eer | U1: eer_f | V1: ois_rate | W1: bank_rate | X1: bank_rate_f | Y1: pmdef | Z1: pmdef_f | AA1: cpif | AB1: cpif_f | AC1: exp_cpi
A2: 33054 | B2: 55.216192 | C2: 53.449601 | D2: 55.931591 | E2: 37.291624 | F2: 109.4919 | G2: 55.346352 | H2: 46.757461 | I2: 33.809155 | J2: 381997 | K2: 381997 | L2: -1.1483808 | M2: 0.93596216 | N2: 906588.84 | O2: 906588.84 | P2: 0.069184781 | Q2: 0.069184781 | R2: 189.32838 | S2: 189.32838 | T2: 93.068646 | U2: 93.068646 | V2: 14.519134 | W2: 14.875 | X2: 14.875 | Y2: 0.57773628 | Z2: 0.57773628 | AA2: 67.416856 | AB2: 67.416856 | AC2: 8.6373834
A3: 33146 | B3: 56.369272 | C3: 54.565685 | D3: 56.730638 | E3: 38.226404 | F3: 110.77076 | G3: 56.069625 | H3: 46.959972 | I3: 35.502014 | J3: 377831 | K3: 377831 | L3: -1.7358221 | M3: -0.79049292 | N3: 901813.5 | O3: 901813.5 | P3: 0.070779647 | Q3: 0.070779647 | R3: 193.61239 | S3: 193.61239 | T3: 99.445968 | U3: 99.445968 | V3: 14.377204 | W3: 14.875 | X3: 14.875 | Y3: 0.55930606 | Z3: 0.55930606 | AA3: 68.109698 | AB3: 68.109698 | AC3: 9.1039566
A4: 33238 | B4: 57.494732 | C4: 55.655628 | D4: 57.774359 | E4: 39.201503 | F4: 112.05037 | G4: 57.003542 | H4: 47.50451 | I4: 36.723481 | J4: 375916 | K4: 375916 | L4: -2.1830843 | M4: -1.1706663 | N4: 892410.87 | O4: 892410.87 | P4: 0.074650616 | Q4: 0.074650616 | R4: 197.31141 | S4: 197.31141 | T4: 99.670858 | U4: 99.670858 | V4: 13.268016 | W4: 13.9531 | X4: 13.9531 | Y4: 0.56615029 | Z4: 0.56615029 | AA4: 69.42033 | AB4: 69.42033 | AC4: 7.4794737
A5: 33328 | B5: 58.131185 | C5: 56.271618 | D5: 58.016017 | E5: 40.047704 | F5: 112.98292 | G5: 57.575944 | H5: 48.473466 | I5: 36.121607 | J5: 374060 | K5: 374060 | L5: -2.9343664 | M5: -1.255856 | N5: 881370.83 | O5: 881370.83 | P5: 0.079969483 | Q5: 0.079969483 | R5: 199.57143 | S5: 199.57143 | T5: 99.118131 | U5: 99.118131 | V5: 12.723411 | W5: 13.3992 | X5: 13.3992 | Y5: 0.56293382 | Z5: 0.56293382 | AA5: 70.402484 | AB5: 70.402484 | AC5: 7.1724561
A6: 33419 | B6: 59.827705 | C6: 57.9136 | D6: 60.59482 | E6: 41.709306 | F6: 115.1372 | G6: 58.344421 | H6: 50.505217 | I6: 37.362098 | J6: 373608 | K6: 373608 | L6: -3.3312328 | M6: -1.273024 | N6: 869788.47 | O6: 869788.47 | P6: 0.086627038 | Q6: 0.086627038 | R6: 204.08804 | S6: 204.08804 | T6: 96.421142 | U6: 96.421142 | V6: 11.097574 | W6: 11.7379 | X6: 11.7379 | Y6: 0.57235316 | Z6: 0.57235316 | AA6: 71.079089 | AB6: 71.079089 | AC6: 5.5856456
A7: 33511 | B7: 60.749441 | C7: 58.805692 | D7: 61.129417 | E7: 42.478114 | F7: 116.63678 | G7: 58.886712 | H7: 50.449029 | I7: 38.223615 | J7: 372878 | K7: 372878 | L7: -3.4757524 | M7: -1.2520863 | N7: 859520.46 | O7: 859520.46 | P7: 0.09159133 | Q7: 0.09159133 | R7: 208.2244 | S7: 208.2244 | T7: 95.722653 | U7: 95.722653 | V7: 10.282062 | W7: 10.7981 | X7: 10.7981 | Y7: 0.58356049 | Z7: 0.58356049 | AA7: 71.94639 | AB7: 71.94639 | AC7: 4.6085185
A8: 33603 | B8: 61.5371 | C8: 59.568663 | D8: 61.822885 | E8: 43.254296 | F8: 117.83569 | G8: 59.515813 | H8: 50.749747 | I8: 38.311037 | J8: 373357 | K8: 373357 | L8: -3.1182875 | M8: -1.0417908 | N8: 851930 | O8: 851930 | P8: 0.094575166 | Q8: 0.094575166 | R8: 211.35106 | S8: 211.35106 | T8: 96.172297 | U8: 96.172297 | V8: 10.071213 | W8: 10.375 | X8: 10.375 | Y8: 0.57552587 | Z8: 0.57552587 | AA8: 72.918164 | AB8: 72.918164 | AC8: 4.4125673
A9: 33694 | B9: 62.131083 | C9: 60.143593 | D9: 62.056834 | E9: 43.882111 | F9: 118.7579 | G9: 59.959978 | H9: 51.685557 | I9: 38.258535 | J9: 373317 | K9: 373317 | L9: -3.3500751 | M9: -1.1690213 | N9: 847165.67 | O9: 847165.67 | P9: 0.097007586 | Q9: 0.097007586 | R9: 215.27103 | S9: 215.27103 | T9: 95.797952 | U9: 95.797952 | V9: 10.079292 | W9: 10.375 | X9: 10.375 | Y9: 0.56924052 | Z9: 0.56924052 | AA9: 73.684026 | AB9: 73.684026 | AC9: 4.3453333
A10: 33785 | B10: 62.416759 | C10: 60.420047 | D10: 63.194403 | E10: 44.452914 | F10: 118.72539 | G10: 59.723829 | H10: 52.427892 | I10: 38.383855 | J10: 372751 | K10: 372751 | L10: -3.1236345 | M10: -1.8203614 | N10: 847646.6 | O10: 847646.6 | P10: 0.09785394 | Q10: 0.09785394 | R10: 216.52634 | S10: 216.52634 | T10: 97.573482 | U10: 97.573482 | V10: 9.7404194 | W10: 10.0471 | X10: 10.0471 | Y10: 0.56506054 | Z10: 0.56506054 | AA10: 74.734655 | AB10: 74.734655 | AC10: 4.0467864
A11: 33877 | B11: 62.691059 | C11: 60.685211 | D11: 63.067373 | E11: 44.967908 | F11: 118.80745 | G11: 59.567454 | H11: 51.973211 | I11: 38.275282 | J11: 374537 | K11: 374537 | L11: -3.3243309 | M11: -0.85749752 | N11: 840427.1 | O11: 840427.1 | P11: 0.099370554 | Q11: 0.099370554 | R11: 219.44681 | S11: 219.44681 | T11: 96.710815 | U11: 96.710815 | V11: 9.695813 | W11: 9.7673 | X11: 9.7673 | Y11: 0.56539814 | Z11: 0.56539814 | AA11: 75.563565 | AB11: 75.563565 | AC11: 3.8414337
A12: 33969 | B12: 63.195466 | C12: 61.173856 | D12: 63.467567 | E12: 45.533479 | F12: 118.62097 | G12: 60.084592 | H12: 52.154689 | I12: 38.984401 | J12: 377418 | K12: 377418 | L12: -3.2279251 | M12: -0.27664328 | N12: 832788.39 | O12: 832788.39 | P12: 0.10371119 | Q12: 0.10371119 | R12: 221.35146 | S12: 221.35146 | T12: 84.845339 | U12: 84.845339 | V12: 7.1698732 | W12: 7.5313 | X12: 7.5313 | Y12: 0.59920423 | Z12: 0.59920423 | AA12: 76.644093 | AB12: 76.644093 | AC12: 3.5328715
A13: 34059 | B13: 63.53193 | C13: 61.499755 | D13: 63.530914 | E13: 46.101573 | F13: 118.15539 | G13: 60.484175 | H13: 53.053856 | I13: 39.383108 | J13: 379370 | K13: 379370 | L13: -3.0780999 | M13: -0.54416477 | N13: 832300.53 | O13: 832300.53 | P13: 0.10618491 | Q13: 0.10618491 | R13: 221.58357 | S13: 221.58357 | T13: 83.282759 | U13: 83.282759 | V13: 5.9494269 | W13: 6.129 | X13: 6.129 | Y13: 0.62407768 | Z13: 0.62407768 | AA13: 77.756408 | AB13: 77.756408 | AC13: 3.0711828
... A142: 45838 | B142: 137.87157 | C142: 137.87146 | D142: 138.04057 | E142: 142.47561 | F142: 122.70051 | G142: 140.78271 | H142: 144.80364 | I142: 152.26215 | J142: 705403 | K142: 705403 | L142: -0.53521004 | M142: -1.8925383 | N142: 1092607.1 | O142: 1092607.1 | P142: 0.04660112 | Q142: 0.04660112 | R142: 670.36599 | S142: 670.36599 | T142: 85.433745 | U142: 85.433745 | V142: 4.1790199 | W142: 3.7371024 | X142: 3.7425486 | Y142: 0.99181196 | Z142: 0.99106811 | AA142: 169.42098 | AB142: 169.42098 | AC142: 4.0110426
A143: 45930 | B143: 139.17556 | C143: 139.17544 | D143: 138.97188 | E143: 143.83211 | F143: 123.18805 | G143: 142.64323 | H143: 146.02696 | I143: 153.77967 | J143: 706813.81 | K143: 706813.81 | M143: -1.6978608 | N143: 1088109.9 | O143: 1088109.9 | P143: 0.048668948 | Q143: 0.048668948 | R143: 674.78348 | S143: 675.06649 | T143: 84.985242 | U143: 84.985242 | V143: 3.9805726 | W143: 3.623433 | X143: 3.623433 | Y143: 0.98826679 | Z143: 0.98826679 | AA143: 170.10292 | AB143: 170.10291 | AC143: 3.9691108
A144: 46022 | B144: 139.91004 | C144: 139.90992 | D144: 139.85387 | E144: 144.83827 | F144: 123.51261 | G144: 144.14372 | H144: 147.49282 | I144: 153.60509 | J144: 708934.25 | K144: 708934.25 | M144: -1.8289475 | N144: 1089925.4 | O144: 1089925.4 | P144: 0.049697693 | Q144: 0.049697693 | S144: 680.79359 | U144: 84.479013 | W144: 3.5100422 | X144: 3.5100422 | Y144: 0.98263827 | Z144: 0.98263827 | AA144: 170.38249 | AB144: 170.38248
A145: 46112 | D145: 139.85387 | K145: 711292.91 | M145: -1.7040186 | O145: 1088841.3 | Q145: 0.0504 | S145: 686.71173 | U145: 84.252156 | W145: 3.4154219 | X145: 3.4154219 | Z145: 0.97725801 | AA145: 170.76719 | AB145: 170.76718
A146: 46203 | D146: 139.85387 | K146: 713598.35 | M146: -1.7237463 | O146: 1089619.5 | Q146: 0.050541252 | S146: 692.12433 | U146: 84.117539 | W146: 3.3219454 | X146: 3.3219454 | Z146: 0.9749504 | AA146: 171.28775 | AB146: 171.28774
A147: 46295 | D147: 139.85387 | K147: 716034.92 | M147: -1.6558511 | O147: 1090427.8 | Q147: 0.050498257 | S147: 697.3824 | U147: 83.98531 | W147: 3.3064318 | X147: 3.3064318 | Z147: 0.97388427 | AA147: 172.08142 | AB147: 172.08141
A148: 46387 | D148: 139.85387 | K148: 718746.04 | M148: -1.6089581 | O148: 1092228.2 | Q148: 0.050389561 | S148: 702.54561 | U148: 83.853892 | W148: 3.3371672 | X148: 3.3371672 | Z148: 0.97306004 | AA148: 172.82848 | AB148: 172.82847
A149: 46477 | D149: 139.85387 | K149: 721631.31 | M149: -1.5371047 | O149: 1094167.4 | Q149: 0.05021789 | S149: 707.66289 | U149: 83.722428 | W149: 3.376846 | X149: 3.376846 | Z149: 0.97240044 | AA149: 173.77928 | AB149: 173.77927
A150: 46568 | D150: 139.85387 | K150: 724747.91 | M150: -1.4586119 | O150: 1096113.2 | Q150: 0.05003043 | S150: 712.79819 | U150: 83.591451 | W150: 3.4138167 | X150: 3.4138167 | Z150: 0.97421349 | AA150: 174.72296 | AB150: 174.72296
A151: 46660 | D151: 139.85387 | K151: 727950.51 | M151: -1.3726282 | O151: 1097963.2 | Q151: 0.04974273 | S151: 717.99084 | U151: 83.462187 | W151: 3.4440408 | X151: 3.4440408 | Z151: 0.97436963 | AA151: 175.63827 | AB151: 175.63827
A152: 46752 | D152: 139.85387 | K152: 731300.17 | M152: -1.3276231 | O152: 1100126.6 | Q152: 0.049361609 | S152: 723.26555 | U152: 83.335501 | W152: 3.469114 | X152: 3.469114 | Z152: 0.97332131 | AA152: 176.37233 | AB152: 176.37234
A153: 46843 | D153: 139.85387 | K153: 734695.69 | M153: -1.3352153 | O153: 1103179.9 | Q153: 0.048942373 | S153: 728.68905 | U153: 83.211438 | W153: 3.4901568 | X153: 3.4901568 | Z153: 0.97211634 | AA153: 177.09076 | AB153: 177.09077
A154: 46934 | D154: 139.85387 | K154: 738059.62 | M154: -1.2781854 | O154: 1105659.2 | Q154: 0.048451841 | S154: 734.32554 | U154: 83.089805 | W154: 3.5168931 | X154: 3.5168931 | Z154: 0.97121443 | AA154: 177.87613 | AB154: 177.87615
A155: 47026 | D155: 139.85387 | K155: 741431.62 | M155: -1.2382119 | O155: 1108222.5 | Q155: 0.047972324 | S155: 740.21052 | U155: 82.970359 | W155: 3.5462896 | X155: 3.5462896 | Z155: 0.97018549 | AA155: 178.61289 | AB155: 178.61291
A156: 47118 | D156: 139.85387 | K156: 744811.57 | M156: -1.1823681 | O156: 1110769.1 | Q156: 0.047406381 | S156: 746.35252 | U156: 82.852815 | W156: 3.5778306 | X156: 3.5778306 | Z156: 0.96942556 | AA156: 179.2077 | AB156: 179.20772

Sheet data_1
C1: T | D1: T | E1: T | F1: T | G1: T | H1: T | I1: T | K1: T | M1: T | N1: T | O1: L | P1: L | Q1: T | R1: T | S1: L | T1: L | U1: T | V1: T | W1: L | Y1: L | Z1: L | AA1: L | AB1: T | AD1: T | AE1: T | AF1: L | AH1: T | AJ1: L
C2: cpi_qoq | D2: cpi_a_qoq | E2: cpi_f_qoq
B3: Date | C3: =Data_FAME!B9 -> cpi | D3: =Data_FAME!C9 -> cpi_a | E3: =Data_FAME!D9 -> cpi_f | F3: =Data_FAME!F9 -> services | G3: =Data_FAME!H9 -> core_gds | H3: =Data_FAME!J9 -> food | I3: ='Data_FAME (2)'!L9 -> food_at_nsa | J3: ='Data_FAME (2)'!M9 -> food_at | K3: =Data_FAME!N9 -> energy | M3: =Data_FAME!Q9 -> gdpkp | N3: =Data_FAME!R9 -> gdpkp_f | O3: =Data_FAME!T9 -> capu | P3: =Data_FAME!U9 -> capu_f | Q3: =Data_FAME!W9 -> hrs | R3: =Data_FAME!X9 -> hrs_f | S3: =Data_FAME!Z9 -> unemp | T3: =Data_FAME!AA9 -> unemp_f | U3: =Data_FAME!AD9 -> wage | V3: =Data_FAME!AE9 -> wage_f | W3: =Data_FAME!AH9 -> eer | Y3: =Data_FAME!AL9 -> ois_rate | Z3: =Data_FAME!AN9 -> bank_rate | AA3: =Data_FAME!AO9 -> bank_rate_f | AB3: =Data_FAME!AR9 -> pmdef | AC3: =Data_FAME!AT9 -> pmdef_xf | AD3: =Data_FAME!AV9 -> cpif | AE3: =Data_FAME!AW9 -> cpif_f | AF3: =Data_FAME!BA9 -> inf_exp | AG3: N25_inf_exp_FIN | AH3: N25_pmdef_FIN | AI3: N25_pmdef_FIN | AJ3: =Data_FAME!AI9 -> eer_f | AK3: f26_inf_exp | AM3: fat_wgt | AN3: cf_wgt | AO3: e_wgt | AP3: s_wgt
B4: 32963 | C4: =Data_FAME!B11 -> 0 | D4: =Data_FAME!C11 -> 0 | E4: =Data_FAME!D11 -> 54.233282 | F4: =Data_FAME!F11 -> 0 | G4: =Data_FAME!H11 -> 0 | H4: =Data_FAME!J11 -> 0 | I4: ='Data_FAME (2)'!L11 -> 45.323672 | J4: ='Data_FAME (2)'!M11 -> 0 | K4: ='Data_FAME (2)'!O11 -> 0 | M4: =Data_FAME!Q11 -> 379458 | N4: =Data_FAME!R11 -> 379458 | O4: =Data_FAME!T11 -> -0.70757743 | P4: =Data_FAME!U11 -> 0.97333792 | Q4: =Data_FAME!W11 -> 908133 | R4: =Data_FAME!X11 -> 908133 | S4: =Data_FAME!Z11 -> 0.069332964 | T4: =Data_FAME!AA11 -> 0.069332964 | U4: =Data_FAME!AD11 -> 183.54771 | V4: =Data_FAME!AE11 -> 183.54771 | W4: =Data_FAME!AH11 -> 92.432746 | Y4: =Data_FAME!AL11 -> 0 | Z4: =Data_FAME!AN11 -> 14.875 | AA4: =Data_FAME!AO11 -> 14.875 | AB4: =Data_FAME!AR11 -> 0.57372025 | AC4: =Data_FAME!AT11 -> 0.60812747 | AD4: =Data_FAME!AV11 -> 66.518783 | AE4: =Data_FAME!AW11 -> 66.518783 | AF4: =Data_FAME!BB11 -> 7.7756322 | AG4: =Data_FAME!BB11 -> 7.7756322 | AH4: =Data_FAME!AS11 -> 0.57372025 | AI4: ='Data_FAME (2)'!P11 -> 0 | AJ4: =Data_FAME!AI11 -> 92.432746 | AM4: ='Data_FAME (2)'!BF11 -> 251 | AN4: ='Data_FAME (2)'!BG11 -> 359 | AO4: ='Data_FAME (2)'!BH11 -> 96 | AP4: ='Data_FAME (2)'!BI11 -> 294
B5: =Data_FAME!A12 -> 33054 | C5: =Data_FAME!B12 -> 55.216192 | D5: =Data_FAME!C12 -> 53.449601 | E5: =Data_FAME!D12 -> 55.931591 | F5: =Data_FAME!F12 -> 37.291624 | G5: =Data_FAME!H12 -> 109.4919 | H5: =Data_FAME!J12 -> 55.346352 | I5: ='Data_FAME (2)'!L12 -> 46.757461 | J5: ='Data_FAME (2)'!M12 -> 46.254605 | K5: ='Data_FAME (2)'!O12 -> 33.809155 | M5: =Data_FAME!Q12 -> 381997 | N5: =Data_FAME!R12 -> 381997 | O5: =Data_FAME!T12 -> -1.1483808 | P5: =Data_FAME!U12 -> 0.93596216 | Q5: =Data_FAME!W12 -> 906588.84 | R5: =Data_FAME!X12 -> 906588.84 | S5: =Data_FAME!Z12 -> 0.069184781 | T5: =Data_FAME!AA12 -> 0.069184781 | U5: =Data_FAME!AD12 -> 189.32838 | V5: =Data_FAME!AE12 -> 189.32838 | W5: =Data_FAME!AH12 -> 93.068646 | Y5: =Data_FAME!AL12 -> 14.519134 | Z5: =Data_FAME!AN12 -> 14.875 | AA5: =Data_FAME!AO12 -> 14.875 | AB5: =Data_FAME!AR12 -> 0.57773628 | AC5: =Data_FAME!AT12 -> 0.60985266 | AD5: =Data_FAME!AV12 -> 67.416856 | AE5: =Data_FAME!AW12 -> 67.416856 | AF5: =Data_FAME!BB12 -> 8.6373834 | AG5: =Data_FAME!BB12 -> 8.6373834 | AH5: =Data_FAME!AS12 -> 0.57773628 | AI5: ='Data_FAME (2)'!P12 -> 33.809155 | AJ5: =Data_FAME!AI12 -> 93.068646 | AM5: ='Data_FAME (2)'!BF12 -> 251 | AN5: ='Data_FAME (2)'!BG12 -> 359 | AO5: ='Data_FAME (2)'!BH12 -> 96 | AP5: ='Data_FAME (2)'!BI12 -> 294
B6: =Data_FAME!A13 -> 33146 | C6: =Data_FAME!B13 -> 56.369272 | D6: =Data_FAME!C13 -> 54.565685 | E6: =Data_FAME!D13 -> 56.730638 | F6: =Data_FAME!F13 -> 38.226404 | G6: =Data_FAME!H13 -> 110.77076 | H6: =Data_FAME!J13 -> 56.069625 | I6: ='Data_FAME (2)'!L13 -> 46.959972 | J6: ='Data_FAME (2)'!M13 -> 47.031491 | K6: ='Data_FAME (2)'!O13 -> 35.502014 | M6: =Data_FAME!Q13 -> 377831 | N6: =Data_FAME!R13 -> 377831 | O6: =Data_FAME!T13 -> -1.7358221 | P6: =Data_FAME!U13 -> -0.79049292 | Q6: =Data_FAME!W13 -> 901813.5 | R6: =Data_FAME!X13 -> 901813.5 | S6: =Data_FAME!Z13 -> 0.070779647 | T6: =Data_FAME!AA13 -> 0.070779647 | U6: =Data_FAME!AD13 -> 193.61239 | V6: =Data_FAME!AE13 -> 193.61239 | W6: =Data_FAME!AH13 -> 99.445968 | Y6: =Data_FAME!AL13 -> 14.377204 | Z6: =Data_FAME!AN13 -> 14.875 | AA6: =Data_FAME!AO13 -> 14.875 | AB6: =Data_FAME!AR13 -> 0.55930606 | AC6: =Data_FAME!AT13 -> 0.59130693 | AD6: =Data_FAME!AV13 -> 68.109698 | AE6: =Data_FAME!AW13 -> 68.109698 | AF6: =Data_FAME!BB13 -> 9.1039566 | AG6: =Data_FAME!BB13 -> 9.1039566 | AH6: =Data_FAME!AS13 -> 0.55930606 | AI6: ='Data_FAME (2)'!P13 -> 35.502014 | AJ6: =Data_FAME!AI13 -> 99.445968 | AM6: ='Data_FAME (2)'!BF13 -> 251 | AN6: ='Data_FAME (2)'!BG13 -> 359 | AO6: ='Data_FAME (2)'!BH13 -> 96 | AP6: ='Data_FAME (2)'!BI13 -> 294
B7: =Data_FAME!A14 -> 33238 | C7: =Data_FAME!B14 -> 57.494732 | D7: =Data_FAME!C14 -> 55.655628 | E7: =Data_FAME!D14 -> 57.774359 | F7: =Data_FAME!F14 -> 39.201503 | G7: =Data_FAME!H14 -> 112.05037 | H7: =Data_FAME!J14 -> 57.003542 | I7: ='Data_FAME (2)'!L14 -> 47.50451 | J7: ='Data_FAME (2)'!M14 -> 47.936474 | K7: ='Data_FAME (2)'!O14 -> 36.723481 | M7: =Data_FAME!Q14 -> 375916 | N7: =Data_FAME!R14 -> 375916 | O7: =Data_FAME!T14 -> -2.1830843 | P7: =Data_FAME!U14 -> -1.1706663 | Q7: =Data_FAME!W14 -> 892410.87 | R7: =Data_FAME!X14 -> 892410.87 | S7: =Data_FAME!Z14 -> 0.074650616 | T7: =Data_FAME!AA14 -> 0.074650616 | U7: =Data_FAME!AD14 -> 197.31141 | V7: =Data_FAME!AE14 -> 197.31141 | W7: =Data_FAME!AH14 -> 99.670858 | Y7: =Data_FAME!AL14 -> 13.268016 | Z7: =Data_FAME!AN14 -> 13.9531 | AA7: =Data_FAME!AO14 -> 13.9531 | AB7: =Data_FAME!AR14 -> 0.56615029 | AC7: =Data_FAME!AT14 -> 0.5885035 | AD7: =Data_FAME!AV14 -> 69.42033 | AE7: =Data_FAME!AW14 -> 69.42033 | AF7: =Data_FAME!BB14 -> 7.4794737 | AG7: =Data_FAME!BB14 -> 7.4794737 | AH7: =Data_FAME!AS14 -> 0.56615029 | AI7: ='Data_FAME (2)'!P14 -> 36.723481 | AJ7: =Data_FAME!AI14 -> 99.670858 | AM7: ='Data_FAME (2)'!BF14 -> 251 | AN7: ='Data_FAME (2)'!BG14 -> 359 | AO7: ='Data_FAME (2)'!BH14 -> 96 | AP7: ='Data_FAME (2)'!BI14 -> 294
B8: =Data_FAME!A15 -> 33328 | C8: =Data_FAME!B15 -> 58.131185 | D8: =Data_FAME!C15 -> 56.271618 | E8: =Data_FAME!D15 -> 58.016017 | F8: =Data_FAME!F15 -> 40.047704 | G8: =Data_FAME!H15 -> 112.98292 | H8: =Data_FAME!J15 -> 57.575944 | I8: ='Data_FAME (2)'!L15 -> 48.473466 | J8: ='Data_FAME (2)'!M15 -> 48.483131 | K8: ='Data_FAME (2)'!O15 -> 36.121607 | M8: =Data_FAME!Q15 -> 374060 | N8: =Data_FAME!R15 -> 374060 | O8: =Data_FAME!T15 -> -2.9343664 | P8: =Data_FAME!U15 -> -1.255856 | Q8: =Data_FAME!W15 -> 881370.83 | R8: =Data_FAME!X15 -> 881370.83 | S8: =Data_FAME!Z15 -> 0.079969483 | T8: =Data_FAME!AA15 -> 0.079969483 | U8: =Data_FAME!AD15 -> 199.57143 | V8: =Data_FAME!AE15 -> 199.57143 | W8: =Data_FAME!AH15 -> 99.118131 | Y8: =Data_FAME!AL15 -> 12.723411 | Z8: =Data_FAME!AN15 -> 13.3992 | AA8: =Data_FAME!AO15 -> 13.3992 | AB8: =Data_FAME!AR15 -> 0.56293382 | AC8: =Data_FAME!AT15 -> 0.59734507 | AD8: =Data_FAME!AV15 -> 70.402484 | AE8: =Data_FAME!AW15 -> 70.402484 | AF8: =Data_FAME!BB15 -> 7.1724561 | AG8: =Data_FAME!BB15 -> 7.1724561 | AH8: =Data_FAME!AS15 -> 0.56293382 | AI8: ='Data_FAME (2)'!P15 -> 36.121607 | AJ8: =Data_FAME!AI15 -> 99.118131 | AM8: ='Data_FAME (2)'!BF15 -> 242 | AN8: ='Data_FAME (2)'!BG15 -> 363 | AO8: ='Data_FAME (2)'!BH15 -> 93 | AP8: ='Data_FAME (2)'!BI15 -> 302
B9: =Data_FAME!A16 -> 33419 | C9: =Data_FAME!B16 -> 59.827705 | D9: =Data_FAME!C16 -> 57.9136 | E9: =Data_FAME!D16 -> 60.59482 | F9: =Data_FAME!F16 -> 41.709306 | G9: =Data_FAME!H16 -> 115.1372 | H9: =Data_FAME!J16 -> 58.344421 | I9: ='Data_FAME (2)'!L16 -> 50.505217 | J9: ='Data_FAME (2)'!M16 -> 49.975838 | K9: ='Data_FAME (2)'!O16 -> 37.362098 | M9: =Data_FAME!Q16 -> 373608 | N9: =Data_FAME!R16 -> 373608 | O9: =Data_FAME!T16 -> -3.3312328 | P9: =Data_FAME!U16 -> -1.273024 | Q9: =Data_FAME!W16 -> 869788.47 | R9: =Data_FAME!X16 -> 869788.47 | S9: =Data_FAME!Z16 -> 0.086627038 | T9: =Data_FAME!AA16 -> 0.086627038 | U9: =Data_FAME!AD16 -> 204.08804 | V9: =Data_FAME!AE16 -> 204.08804 | W9: =Data_FAME!AH16 -> 96.421142 | Y9: =Data_FAME!AL16 -> 11.097574 | Z9: =Data_FAME!AN16 -> 11.7379 | AA9: =Data_FAME!AO16 -> 11.7379 | AB9: =Data_FAME!AR16 -> 0.57235316 | AC9: =Data_FAME!AT16 -> 0.60942136 | AD9: =Data_FAME!AV16 -> 71.079089 | AE9: =Data_FAME!AW16 -> 71.079089 | AF9: =Data_FAME!BB16 -> 5.5856456 | AG9: =Data_FAME!BB16 -> 5.5856456 | AH9: =Data_FAME!AS16 -> 0.57235316 | AI9: ='Data_FAME (2)'!P16 -> 37.362098 | AJ9: =Data_FAME!AI16 -> 96.421142 | AM9: ='Data_FAME (2)'!BF16 -> 242 | AN9: ='Data_FAME (2)'!BG16 -> 363 | AO9: ='Data_FAME (2)'!BH16 -> 93 | AP9: ='Data_FAME (2)'!BI16 -> 302
B10: =Data_FAME!A17 -> 33511 | C10: =Data_FAME!B17 -> 60.749441 | D10: =Data_FAME!C17 -> 58.805692 | E10: =Data_FAME!D17 -> 61.129417 | F10: =Data_FAME!F17 -> 42.478114 | G10: =Data_FAME!H17 -> 116.63678 | H10: =Data_FAME!J17 -> 58.886712 | I10: ='Data_FAME (2)'!L17 -> 50.449029 | J10: ='Data_FAME (2)'!M17 -> 50.515686 | K10: ='Data_FAME (2)'!O17 -> 38.223615 | M10: =Data_FAME!Q17 -> 372878 | N10: =Data_FAME!R17 -> 372878 | O10: =Data_FAME!T17 -> -3.4757524 | P10: =Data_FAME!U17 -> -1.2520863 | Q10: =Data_FAME!W17 -> 859520.46 | R10: =Data_FAME!X17 -> 859520.46 | S10: =Data_FAME!Z17 -> 0.09159133 | T10: =Data_FAME!AA17 -> 0.09159133 | U10: =Data_FAME!AD17 -> 208.2244 | V10: =Data_FAME!AE17 -> 208.2244 | W10: =Data_FAME!AH17 -> 95.722653 | Y10: =Data_FAME!AL17 -> 10.282062 | Z10: =Data_FAME!AN17 -> 10.7981 | AA10: =Data_FAME!AO17 -> 10.7981 | AB10: =Data_FAME!AR17 -> 0.58356049 | AC10: =Data_FAME!AT17 -> 0.61934117 | AD10: =Data_FAME!AV17 -> 71.94639 | AE10: =Data_FAME!AW17 -> 71.94639 | AF10: =Data_FAME!BB17 -> 4.6085185 | AG10: =Data_FAME!BB17 -> 4.6085185 | AH10: =Data_FAME!AS17 -> 0.58356049 | AI10: ='Data_FAME (2)'!P17 -> 38.223615 | AJ10: =Data_FAME!AI17 -> 95.722653 | AM10: ='Data_FAME (2)'!BF17 -> 242 | AN10: ='Data_FAME (2)'!BG17 -> 363 | AO10: ='Data_FAME (2)'!BH17 -> 93 | AP10: ='Data_FAME (2)'!BI17 -> 302
B11: =Data_FAME!A18 -> 33603 | C11: =Data_FAME!B18 -> 61.5371 | D11: =Data_FAME!C18 -> 59.568663 | E11: =Data_FAME!D18 -> 61.822885 | F11: =Data_FAME!F18 -> 43.254296 | G11: =Data_FAME!H18 -> 117.83569 | H11: =Data_FAME!J18 -> 59.515813 | I11: ='Data_FAME (2)'!L18 -> 50.749747 | J11: ='Data_FAME (2)'!M18 -> 51.223588 | K11: ='Data_FAME (2)'!O18 -> 38.311037 | M11: =Data_FAME!Q18 -> 373357 | N11: =Data_FAME!R18 -> 373357 | O11: =Data_FAME!T18 -> -3.1182875 | P11: =Data_FAME!U18 -> -1.0417908 | Q11: =Data_FAME!W18 -> 851930 | R11: =Data_FAME!X18 -> 851930 | S11: =Data_FAME!Z18 -> 0.094575166 | T11: =Data_FAME!AA18 -> 0.094575166 | U11: =Data_FAME!AD18 -> 211.35106 | V11: =Data_FAME!AE18 -> 211.35106 | W11: =Data_FAME!AH18 -> 96.172297 | Y11: =Data_FAME!AL18 -> 10.071213 | Z11: =Data_FAME!AN18 -> 10.375 | AA11: =Data_FAME!AO18 -> 10.375 | AB11: =Data_FAME!AR18 -> 0.57552587 | AC11: =Data_FAME!AT18 -> 0.61287173 | AD11: =Data_FAME!AV18 -> 72.918164 | AE11: =Data_FAME!AW18 -> 72.918164 | AF11: =Data_FAME!BB18 -> 4.4125673 | AG11: =Data_FAME!BB18 -> 4.4125673 | AH11: =Data_FAME!AS18 -> 0.57552587 | AI11: ='Data_FAME (2)'!P18 -> 38.311037 | AJ11: =Data_FAME!AI18 -> 96.172297 | AM11: ='Data_FAME (2)'!BF18 -> 242 | AN11: ='Data_FAME (2)'!BG18 -> 363 | AO11: ='Data_FAME (2)'!BH18 -> 93 | AP11: ='Data_FAME (2)'!BI18 -> 302
B12: =Data_FAME!A19 -> 33694 | C12: =Data_FAME!B19 -> 62.131083 | D12: =Data_FAME!C19 -> 60.143593 | E12: =Data_FAME!D19 -> 62.056834 | F12: =Data_FAME!F19 -> 43.882111 | G12: =Data_FAME!H19 -> 118.7579 | H12: =Data_FAME!J19 -> 59.959978 | I12: ='Data_FAME (2)'!L19 -> 51.685557 | J12: ='Data_FAME (2)'!M19 -> 51.670967 | K12: ='Data_FAME (2)'!O19 -> 38.258535 | M12: =Data_FAME!Q19 -> 373317 | N12: =Data_FAME!R19 -> 373317 | O12: =Data_FAME!T19 -> -3.3500751 | P12: =Data_FAME!U19 -> -1.1690213 | Q12: =Data_FAME!W19 -> 847165.67 | R12: =Data_FAME!X19 -> 847165.67 | S12: =Data_FAME!Z19 -> 0.097007586 | T12: =Data_FAME!AA19 -> 0.097007586 | U12: =Data_FAME!AD19 -> 215.27103 | V12: =Data_FAME!AE19 -> 215.27103 | W12: =Data_FAME!AH19 -> 95.797952 | Y12: =Data_FAME!AL19 -> 10.079292 | Z12: =Data_FAME!AN19 -> 10.375 | AA12: =Data_FAME!AO19 -> 10.375 | AB12: =Data_FAME!AR19 -> 0.56924052 | AC12: =Data_FAME!AT19 -> 0.61394997 | AD12: =Data_FAME!AV19 -> 73.684026 | AE12: =Data_FAME!AW19 -> 73.684026 | AF12: =Data_FAME!BB19 -> 4.3453333 | AG12: =Data_FAME!BB19 -> 4.3453333 | AH12: =Data_FAME!AS19 -> 0.56924052 | AI12: ='Data_FAME (2)'!P19 -> 38.258535 | AJ12: =Data_FAME!AI19 -> 95.797952 | AM12: ='Data_FAME (2)'!BF19 -> 244 | AN12: ='Data_FAME (2)'!BG19 -> 360 | AO12: ='Data_FAME (2)'!BH19 -> 91 | AP12: ='Data_FAME (2)'!BI19 -> 305
B13: =Data_FAME!A20 -> 33785 | C13: =Data_FAME!B20 -> 62.416759 | D13: =Data_FAME!C20 -> 60.420047 | E13: =Data_FAME!D20 -> 63.194403 | F13: =Data_FAME!F20 -> 44.452914 | G13: =Data_FAME!H20 -> 118.72539 | H13: =Data_FAME!J20 -> 59.723829 | I13: ='Data_FAME (2)'!L20 -> 52.427892 | J13: ='Data_FAME (2)'!M20 -> 51.90606 | K13: ='Data_FAME (2)'!O20 -> 38.383855 | M13: =Data_FAME!Q20 -> 372751 | N13: =Data_FAME!R20 -> 372751 | O13: =Data_FAME!T20 -> -3.1236345 | P13: =Data_FAME!U20 -> -1.8203614 | Q13: =Data_FAME!W20 -> 847646.6 | R13: =Data_FAME!X20 -> 847646.6 | S13: =Data_FAME!Z20 -> 0.09785394 | T13: =Data_FAME!AA20 -> 0.09785394 | U13: =Data_FAME!AD20 -> 216.52634 | V13: =Data_FAME!AE20 -> 216.52634 | W13: =Data_FAME!AH20 -> 97.573482 | Y13: =Data_FAME!AL20 -> 9.7404194 | Z13: =Data_FAME!AN20 -> 10.0471 | AA13: =Data_FAME!AO20 -> 10.0471 | AB13: =Data_FAME!AR20 -> 0.56506054 | AC13: =Data_FAME!AT20 -> 0.60791183 | AD13: =Data_FAME!AV20 -> 74.734655 | AE13: =Data_FAME!AW20 -> 74.734655 | AF13: =Data_FAME!BB20 -> 4.0467864 | AG13: =Data_FAME!BB20 -> 4.0467864 | AH13: =Data_FAME!AS20 -> 0.56506054 | AI13: ='Data_FAME (2)'!P20 -> 38.383855 | AJ13: =Data_FAME!AI20 -> 97.573482 | AM13: ='Data_FAME (2)'!BF20 -> 244 | AN13: ='Data_FAME (2)'!BG20 -> 360 | AO13: ='Data_FAME (2)'!BH20 -> 91 | AP13: ='Data_FAME (2)'!BI20 -> 305
B14: =Data_FAME!A21 -> 33877 | C14: =Data_FAME!B21 -> 62.691059 | D14: =Data_FAME!C21 -> 60.685211 | E14: =Data_FAME!D21 -> 63.067373 | F14: =Data_FAME!F21 -> 44.967908 | G14: =Data_FAME!H21 -> 118.80745 | H14: =Data_FAME!J21 -> 59.567454 | I14: ='Data_FAME (2)'!L21 -> 51.973211 | J14: ='Data_FAME (2)'!M21 -> 52.023965 | K14: ='Data_FAME (2)'!O21 -> 38.275282 | M14: =Data_FAME!Q21 -> 374537 | N14: =Data_FAME!R21 -> 374537 | O14: =Data_FAME!T21 -> -3.3243309 | P14: =Data_FAME!U21 -> -0.85749752 | Q14: =Data_FAME!W21 -> 840427.1 | R14: =Data_FAME!X21 -> 840427.1 | S14: =Data_FAME!Z21 -> 0.099370554 | T14: =Data_FAME!AA21 -> 0.099370554 | U14: =Data_FAME!AD21 -> 219.44681 | V14: =Data_FAME!AE21 -> 219.44681 | W14: =Data_FAME!AH21 -> 96.710815 | Y14: =Data_FAME!AL21 -> 9.695813 | Z14: =Data_FAME!AN21 -> 9.7673 | AA14: =Data_FAME!AO21 -> 9.7673 | AB14: =Data_FAME!AR21 -> 0.56539814 | AC14: =Data_FAME!AT21 -> 0.60273627 | AD14: =Data_FAME!AV21 -> 75.563565 | AE14: =Data_FAME!AW21 -> 75.563565 | AF14: =Data_FAME!BB21 -> 3.8414337 | AG14: =Data_FAME!BB21 -> 3.8414337 | AH14: =Data_FAME!AS21 -> 0.56539814 | AI14: ='Data_FAME (2)'!P21 -> 38.275282 | AJ14: =Data_FAME!AI21 -> 96.710815 | AM14: ='Data_FAME (2)'!BF21 -> 244 | AN14: ='Data_FAME (2)'!BG21 -> 360 | AO14: ='Data_FAME (2)'!BH21 -> 91 | AP14: ='Data_FAME (2)'!BI21 -> 305
B15: =Data_FAME!A22 -> 33969 | C15: =Data_FAME!B22 -> 63.195466 | D15: =Data_FAME!C22 -> 61.173856 | E15: =Data_FAME!D22 -> 63.467567 | F15: =Data_FAME!F22 -> 45.533479 | G15: =Data_FAME!H22 -> 118.62097 | H15: =Data_FAME!J22 -> 60.084592 | I15: ='Data_FAME (2)'!L22 -> 52.154689 | J15: ='Data_FAME (2)'!M22 -> 52.659248 | K15: ='Data_FAME (2)'!O22 -> 38.984401 | M15: =Data_FAME!Q22 -> 377418 | N15: =Data_FAME!R22 -> 377418 | O15: =Data_FAME!T22 -> -3.2279251 | P15: =Data_FAME!U22 -> -0.27664328 | Q15: =Data_FAME!W22 -> 832788.39 | R15: =Data_FAME!X22 -> 832788.39 | S15: =Data_FAME!Z22 -> 0.10371119 | T15: =Data_FAME!AA22 -> 0.10371119 | U15: =Data_FAME!AD22 -> 221.35146 | V15: =Data_FAME!AE22 -> 221.35146 | W15: =Data_FAME!AH22 -> 84.845339 | Y15: =Data_FAME!AL22 -> 7.1698732 | Z15: =Data_FAME!AN22 -> 7.5313 | AA15: =Data_FAME!AO22 -> 7.5313 | AB15: =Data_FAME!AR22 -> 0.59920423 | AC15: =Data_FAME!AT22 -> 0.64263116 | AD15: =Data_FAME!AV22 -> 76.644093 | AE15: =Data_FAME!AW22 -> 76.644093 | AF15: =Data_FAME!BB22 -> 3.5328715 | AG15: =Data_FAME!BB22 -> 3.5328715 | AH15: =Data_FAME!AS22 -> 0.59920423 | AI15: ='Data_FAME (2)'!P22 -> 38.984401 | AJ15: =Data_FAME!AI22 -> 84.845339 | AM15: ='Data_FAME (2)'!BF22 -> 244 | AN15: ='Data_FAME (2)'!BG22 -> 360 | AO15: ='Data_FAME (2)'!BH22 -> 91 | AP15: ='Data_FAME (2)'!BI22 -> 305
B16: =Data_FAME!A23 -> 34059 | C16: =Data_FAME!B23 -> 63.53193 | D16: =Data_FAME!C23 -> 61.499755 | E16: =Data_FAME!D23 -> 63.530914 | F16: =Data_FAME!F23 -> 46.101573 | G16: =Data_FAME!H23 -> 118.15539 | H16: =Data_FAME!J23 -> 60.484175 | I16: ='Data_FAME (2)'!L23 -> 53.053856 | J16: ='Data_FAME (2)'!M23 -> 53.005409 | K16: ='Data_FAME (2)'!O23 -> 39.383108 | M16: =Data_FAME!Q23 -> 379370 | N16: =Data_FAME!R23 -> 379370 | O16: =Data_FAME!T23 -> -3.0780999 | P16: =Data_FAME!U23 -> -0.54416477 | Q16: =Data_FAME!W23 -> 832300.53 | R16: =Data_FAME!X23 -> 832300.53 | S16: =Data_FAME!Z23 -> 0.10618491 | T16: =Data_FAME!AA23 -> 0.10618491 | U16: =Data_FAME!AD23 -> 221.58357 | V16: =Data_FAME!AE23 -> 221.58357 | W16: =Data_FAME!AH23 -> 83.282759 | Y16: =Data_FAME!AL23 -> 5.9494269 | Z16: =Data_FAME!AN23 -> 6.129 | AA16: =Data_FAME!AO23 -> 6.129 | AB16: =Data_FAME!AR23 -> 0.62407768 | AC16: =Data_FAME!AT23 -> 0.67454707 | AD16: =Data_FAME!AV23 -> 77.756408 | AE16: =Data_FAME!AW23 -> 77.756408 | AF16: =Data_FAME!BB23 -> 3.0711828 | AG16: =Data_FAME!BB23 -> 3.0711828 | AH16: =Data_FAME!AS23 -> 0.62407768 | AI16: ='Data_FAME (2)'!P23 -> 39.383108 | AJ16: =Data_FAME!AI23 -> 83.282759 | AM16: ='Data_FAME (2)'!BF23 -> 228 | AN16: ='Data_FAME (2)'!BG23 -> 343 | AO16: ='Data_FAME (2)'!BH23 -> 91 | AP16: ='Data_FAME (2)'!BI23 -> 338
... B145: =Data_FAME!A152 -> 45838 | C145: =Data_FAME!B152 -> 137.87157 | D145: =Data_FAME!C152 -> 137.87146 | E145: =Data_FAME!D152 -> 138.04057 | F145: =Data_FAME!F152 -> 142.47561 | G145: =Data_FAME!H152 -> 122.70051 | H145: =Data_FAME!J152 -> 140.78271 | I145: ='Data_FAME (2)'!L152 -> 144.80364 | J145: ='Data_FAME (2)'!M152 -> 144.36323 | K145: ='Data_FAME (2)'!O152 -> 152.26305 | M145: =Data_FAME!Q152 -> 705403 | N145: =Data_FAME!R152 -> 705403 | O145: =Data_FAME!T152 -> -0.53521004 | P145: =Data_FAME!U152 -> -1.8925383 | Q145: =Data_FAME!W152 -> 1092607.1 | R145: =Data_FAME!X152 -> 1092607.1 | S145: =Data_FAME!Z152 -> 0.04660112 | T145: =Data_FAME!AA152 -> 0.04660112 | U145: =Data_FAME!AD152 -> 670.36599 | V145: =Data_FAME!AE152 -> 670.36599 | W145: =Data_FAME!AH152 -> 85.433745 | Y145: =Data_FAME!AL152 -> 4.1790199 | Z145: =Data_FAME!AN152 -> 3.7371024 | AA145: =Data_FAME!AO152 -> 3.7425486 | AB145: =Data_FAME!AR152 -> 0.99181196 | AC145: =Data_FAME!AT152 -> 1.0097549 | AD145: =Data_FAME!AV152 -> 169.42098 | AE145: =Data_FAME!AW152 -> 169.42098 | AF145: =Data_FAME!BB152 -> 4.0110426 | AG145: =Data_FAME!BB152 -> 4.0110426 | AH145: =Data_FAME!AS152 -> 0.99106811 | AI145: ='Data_FAME (2)'!P152 -> 153.38041 | AJ145: =Data_FAME!AI152 -> 85.433745 | AM145: ='Data_FAME (2)'!BF152 -> 151.1486 | AN145: ='Data_FAME (2)'!BG152 -> 286.3633 | AO145: ='Data_FAME (2)'!BH152 -> 61.6527 | AP145: ='Data_FAME (2)'!BI152 -> 500.8354
B146: =Data_FAME!A153 -> 45930 | C146: =Data_FAME!B153 -> 139.17556 | D146: =Data_FAME!C153 -> 139.17544 | E146: =Data_FAME!D153 -> 138.97188 | F146: =Data_FAME!F153 -> 143.83211 | G146: =Data_FAME!H153 -> 123.18805 | H146: =Data_FAME!J153 -> 142.64323 | I146: ='Data_FAME (2)'!L153 -> 146.02696 | J146: ='Data_FAME (2)'!M153 -> 146.17239 | K146: ='Data_FAME (2)'!O153 -> 153.78204 | M146: =Data_FAME!Q153 -> 706813.81 | N146: =Data_FAME!R153 -> 706813.81 | P146: =Data_FAME!U153 -> -1.6978608 | Q146: =Data_FAME!W153 -> 1088109.9 | R146: =Data_FAME!X153 -> 1088109.9 | S146: =Data_FAME!Z153 -> 0.048668948 | T146: =Data_FAME!AA153 -> 0.048668948 | U146: =Data_FAME!AD153 -> 674.78348 | V146: =Data_FAME!AE153 -> 675.06649 | W146: =Data_FAME!AH153 -> 84.985242 | Y146: =Data_FAME!AL153 -> 3.9805726 | Z146: =Data_FAME!AN153 -> 3.623433 | AA146: =Data_FAME!AO153 -> 3.623433 | AB146: =Data_FAME!AR153 -> 0.98826679 | AC146: =Data_FAME!AT153 -> 1.006946 | AD146: =Data_FAME!AV153 -> 170.10292 | AE146: =Data_FAME!AW153 -> 170.10291 | AF146: =Data_FAME!BB153 -> 3.9691108 | AG146: ='Data_FAME (2)'!BD153 -> 3.9691108 | AH146: =Data_FAME!AS153 -> 0.98826679 | AI146: ='Data_FAME (2)'!P153 -> 152.77858 | AJ146: =Data_FAME!AI153 -> 84.985242 | AM146: ='Data_FAME (2)'!BF153 -> 151.1486 | AN146: ='Data_FAME (2)'!BG153 -> 286.3633 | AO146: ='Data_FAME (2)'!BH153 -> 61.6527 | AP146: ='Data_FAME (2)'!BI153 -> 500.8354
B147: =Data_FAME!A154 -> 46022 | C147: =Data_FAME!B154 -> 139.91004 | D147: =Data_FAME!C154 -> 139.90992 | E147: =Data_FAME!D154 -> 139.85387 | F147: =Data_FAME!F154 -> 144.83827 | G147: =Data_FAME!H154 -> 123.51261 | H147: =Data_FAME!J154 -> 144.14372 | I147: ='Data_FAME (2)'!L154 -> 146.88064 | J147: ='Data_FAME (2)'!M154 -> 147.33385 | K147: ='Data_FAME (2)'!O154 -> 153.89556 | M147: =Data_FAME!Q154 -> 708934.25 | N147: =Data_FAME!R154 -> 708934.25 | P147: =Data_FAME!U154 -> -1.8289475 | Q147: =Data_FAME!W154 -> 1089925.4 | R147: =Data_FAME!X154 -> 1089925.4 | S147: =Data_FAME!Z154 -> 0.049697693 | T147: =Data_FAME!AA154 -> 0.049697693 | V147: =Data_FAME!AE154 -> 680.79359 | Z147: =Data_FAME!AN154 -> 3.5100422 | AA147: =Data_FAME!AO154 -> 3.5100422 | AB147: =Data_FAME!AR154 -> 0.98263827 | AD147: =Data_FAME!AV154 -> 170.38249 | AE147: =Data_FAME!AW154 -> 170.38248 | AG147: ='[2]VAR expectations'!C155 -> 3.9221779 | AH147: =Data_FAME!AS154 -> 0.98263827 | AI147: ='Data_FAME (2)'!P154 -> 154.08739 | AJ147: =Data_FAME!AI154 -> 84.479013 | AM147: ='Data_FAME (2)'!BF154 -> 151.1486 | AN147: ='Data_FAME (2)'!BG154 -> 286.3633 | AO147: ='Data_FAME (2)'!BH154 -> 61.6527 | AP147: ='Data_FAME (2)'!BI154 -> 500.8354
B148: =Data_FAME!A155 -> 46112 | E148: =Data_FAME!D155 -> 139.85387 | I148: ='Data_FAME (2)'!L155 -> 148.75767 | J148: ='Data_FAME (2)'!M155 -> 0 | K148: ='Data_FAME (2)'!O155 -> 0 | N148: =Data_FAME!R155 -> 711292.91 | P148: =Data_FAME!U155 -> -1.7040186 | R148: =Data_FAME!X155 -> 1088841.3 | T148: =Data_FAME!AA155 -> 0.0504 | V148: =Data_FAME!AE155 -> 686.71173 | Z148: =Data_FAME!AN155 -> 3.4154219 | AA148: =Data_FAME!AO155 -> 3.4154219 | AD148: =Data_FAME!AV155 -> 170.76719 | AE148: =Data_FAME!AW155 -> 170.76718 | AG148: ='[2]VAR expectations'!C156 -> 3.4732572 | AH148: =Data_FAME!AS155 -> 0.97725801 | AI148: ='Data_FAME (2)'!P155 -> 152.38088 | AJ148: =Data_FAME!AI155 -> 84.252156 | AM148: ='Data_FAME (2)'!BF155 -> 146.37555 | AN148: ='Data_FAME (2)'!BG155 -> 277.06973 | AO148: ='Data_FAME (2)'!BH155 -> 58.33398 | AP148: ='Data_FAME (2)'!BI155 -> 518.22073
B149: =Data_FAME!A156 -> 46203 | E149: =Data_FAME!D156 -> 139.85387 | I149: ='Data_FAME (2)'!L156 -> 149.8334 | J149: ='Data_FAME (2)'!M156 -> 0 | K149: ='Data_FAME (2)'!O156 -> 0 | N149: =Data_FAME!R156 -> 713598.35 | P149: =Data_FAME!U156 -> -1.7237463 | R149: =Data_FAME!X156 -> 1089619.5 | T149: =Data_FAME!AA156 -> 0.050541252 | V149: =Data_FAME!AE156 -> 692.12433 | Z149: =Data_FAME!AN156 -> 3.3219454 | AA149: =Data_FAME!AO156 -> 3.3219454 | AD149: =Data_FAME!AV156 -> 171.28775 | AE149: =Data_FAME!AW156 -> 171.28774 | AG149: ='[2]VAR expectations'!C157 -> 3.2071262 | AH149: =Data_FAME!AS156 -> 0.9749504 | AI149: ='Data_FAME (2)'!P156 -> 148.04947 | AJ149: =Data_FAME!AI156 -> 84.117539 | AM149: ='Data_FAME (2)'!BF156 -> 146.73083 | AN149: ='Data_FAME (2)'!BG156 -> 276.4363 | AO149: ='Data_FAME (2)'!BH156 -> 58.33497 | AP149: ='Data_FAME (2)'!BI156 -> 518.4979
B150: =Data_FAME!A157 -> 46295 | E150: =Data_FAME!D157 -> 139.85387 | I150: ='Data_FAME (2)'!L157 -> 149.92516 | J150: ='Data_FAME (2)'!M157 -> 0 | K150: ='Data_FAME (2)'!O157 -> 0 | N150: =Data_FAME!R157 -> 716034.92 | P150: =Data_FAME!U157 -> -1.6558511 | R150: =Data_FAME!X157 -> 1090427.8 | T150: =Data_FAME!AA157 -> 0.050498257 | V150: =Data_FAME!AE157 -> 697.3824 | Z150: =Data_FAME!AN157 -> 3.3064318 | AA150: =Data_FAME!AO157 -> 3.3064318 | AD150: =Data_FAME!AV157 -> 172.08142 | AE150: =Data_FAME!AW157 -> 172.08141 | AG150: ='[2]VAR expectations'!C158 -> 2.9284517 | AH150: =Data_FAME!AS157 -> 0.97388427 | AI150: ='Data_FAME (2)'!P157 -> 149.5711 | AJ150: =Data_FAME!AI157 -> 83.98531 | AM150: ='Data_FAME (2)'!BF157 -> 146.73083 | AN150: ='Data_FAME (2)'!BG157 -> 276.4363 | AO150: ='Data_FAME (2)'!BH157 -> 58.33497 | AP150: ='Data_FAME (2)'!BI157 -> 518.4979
B151: =Data_FAME!A158 -> 46387 | E151: =Data_FAME!D158 -> 139.85387 | I151: ='Data_FAME (2)'!L158 -> 151.64689 | J151: ='Data_FAME (2)'!M158 -> 0 | K151: ='Data_FAME (2)'!O158 -> 0 | N151: =Data_FAME!R158 -> 718746.04 | P151: =Data_FAME!U158 -> -1.6089581 | R151: =Data_FAME!X158 -> 1092228.2 | T151: =Data_FAME!AA158 -> 0.050389561 | V151: =Data_FAME!AE158 -> 702.54561 | Z151: =Data_FAME!AN158 -> 3.3371672 | AA151: =Data_FAME!AO158 -> 3.3371672 | AD151: =Data_FAME!AV158 -> 172.82848 | AE151: =Data_FAME!AW158 -> 172.82847 | AG151: ='[2]VAR expectations'!C159 -> 2.7607717 | AH151: =Data_FAME!AS158 -> 0.97306004 | AI151: ='Data_FAME (2)'!P158 -> 149.37929 | AJ151: =Data_FAME!AI158 -> 83.853892 | AM151: ='Data_FAME (2)'!BF158 -> 146.73083 | AN151: ='Data_FAME (2)'!BG158 -> 276.4363 | AO151: ='Data_FAME (2)'!BH158 -> 58.33497 | AP151: ='Data_FAME (2)'!BI158 -> 518.4979
B152: =Data_FAME!A159 -> 46477 | E152: =Data_FAME!D159 -> 139.85387 | I152: ='Data_FAME (2)'!L159 -> 0 | J152: ='Data_FAME (2)'!M159 -> 0 | K152: ='Data_FAME (2)'!O159 -> 0 | N152: =Data_FAME!R159 -> 721631.31 | P152: =Data_FAME!U159 -> -1.5371047 | R152: =Data_FAME!X159 -> 1094167.4 | T152: =Data_FAME!AA159 -> 0.05021789 | V152: =Data_FAME!AE159 -> 707.66289 | Z152: =Data_FAME!AN159 -> 3.376846 | AA152: =Data_FAME!AO159 -> 3.376846 | AD152: =Data_FAME!AV159 -> 173.77928 | AE152: =Data_FAME!AW159 -> 173.77927 | AG152: ='[2]VAR expectations'!C160 -> 2.6830774 | AH152: =Data_FAME!AS159 -> 0.97240044 | AI152: ='Data_FAME (2)'!P159 -> 148.75311 | AJ152: =Data_FAME!AI159 -> 83.722428 | AM152: ='Data_FAME (2)'!BF159 -> 146.37555 | AN152: ='Data_FAME (2)'!BG159 -> 277.06973 | AO152: ='Data_FAME (2)'!BH159 -> 58.33398 | AP152: ='Data_FAME (2)'!BI159 -> 518.22073
B153: =Data_FAME!A160 -> 46568 | E153: =Data_FAME!D160 -> 139.85387 | I153: ='Data_FAME (2)'!L160 -> 0 | J153: ='Data_FAME (2)'!M160 -> 0 | K153: ='Data_FAME (2)'!O160 -> 0 | N153: =Data_FAME!R160 -> 724747.91 | P153: =Data_FAME!U160 -> -1.4586119 | R153: =Data_FAME!X160 -> 1096113.2 | T153: =Data_FAME!AA160 -> 0.05003043 | V153: =Data_FAME!AE160 -> 712.79819 | Z153: =Data_FAME!AN160 -> 3.4138167 | AA153: =Data_FAME!AO160 -> 3.4138167 | AD153: =Data_FAME!AV160 -> 174.72296 | AE153: =Data_FAME!AW160 -> 174.72296 | AG153: ='[2]VAR expectations'!C161 -> 2.6433548 | AH153: =Data_FAME!AS160 -> 0.97421349 | AI153: ='Data_FAME (2)'!P160 -> 149.36955 | AJ153: =Data_FAME!AI160 -> 83.591451 | AM153: ='Data_FAME (2)'!BF160 -> 146.73083 | AN153: ='Data_FAME (2)'!BG160 -> 276.4363 | AO153: ='Data_FAME (2)'!BH160 -> 58.33497 | AP153: ='Data_FAME (2)'!BI160 -> 518.4979
B154: =Data_FAME!A161 -> 46660 | E154: =Data_FAME!D161 -> 139.85387 | I154: ='Data_FAME (2)'!L161 -> 0 | J154: ='Data_FAME (2)'!M161 -> 0 | K154: ='Data_FAME (2)'!O161 -> 0 | N154: =Data_FAME!R161 -> 727950.51 | P154: =Data_FAME!U161 -> -1.3726282 | R154: =Data_FAME!X161 -> 1097963.2 | T154: =Data_FAME!AA161 -> 0.04974273 | V154: =Data_FAME!AE161 -> 717.99084 | Z154: =Data_FAME!AN161 -> 3.4440408 | AA154: =Data_FAME!AO161 -> 3.4440408 | AD154: =Data_FAME!AV161 -> 175.63827 | AE154: =Data_FAME!AW161 -> 175.63827 | AG154: ='[2]VAR expectations'!C162 -> 2.6218393 | AH154: =Data_FAME!AS161 -> 0.97436963 | AI154: ='Data_FAME (2)'!P161 -> 149.91701 | AJ154: =Data_FAME!AI161 -> 83.462187 | AM154: ='Data_FAME (2)'!BF161 -> 146.73083 | AN154: ='Data_FAME (2)'!BG161 -> 276.4363 | AO154: ='Data_FAME (2)'!BH161 -> 58.33497 | AP154: ='Data_FAME (2)'!BI161 -> 518.4979
B155: =Data_FAME!A162 -> 46752 | E155: =Data_FAME!D162 -> 139.85387 | I155: ='Data_FAME (2)'!L162 -> 0 | J155: ='Data_FAME (2)'!M162 -> 0 | K155: ='Data_FAME (2)'!O162 -> 0 | N155: =Data_FAME!R162 -> 731300.17 | P155: =Data_FAME!U162 -> -1.3276231 | R155: =Data_FAME!X162 -> 1100126.6 | T155: =Data_FAME!AA162 -> 0.049361609 | V155: =Data_FAME!AE162 -> 723.26555 | Z155: =Data_FAME!AN162 -> 3.469114 | AA155: =Data_FAME!AO162 -> 3.469114 | AD155: =Data_FAME!AV162 -> 176.37233 | AE155: =Data_FAME!AW162 -> 176.37234 | AG155: ='[2]VAR expectations'!C163 -> 2.609262 | AH155: =Data_FAME!AS162 -> 0.97332131 | AI155: ='Data_FAME (2)'!P162 -> 136.40861 | AJ155: =Data_FAME!AI162 -> 83.335501 | AM155: ='Data_FAME (2)'!BF162 -> 146.73083 | AN155: ='Data_FAME (2)'!BG162 -> 276.4363 | AO155: ='Data_FAME (2)'!BH162 -> 58.33497 | AP155: ='Data_FAME (2)'!BI162 -> 518.4979
B156: =Data_FAME!A163 -> 46843 | E156: =Data_FAME!D163 -> 139.85387 | I156: ='Data_FAME (2)'!L163 -> 0 | J156: ='Data_FAME (2)'!M163 -> 0 | K156: ='Data_FAME (2)'!O163 -> 0 | N156: =Data_FAME!R163 -> 734695.69 | P156: =Data_FAME!U163 -> -1.3352153 | R156: =Data_FAME!X163 -> 1103179.9 | T156: =Data_FAME!AA163 -> 0.048942373 | V156: =Data_FAME!AE163 -> 728.68905 | Z156: =Data_FAME!AN163 -> 3.4901568 | AA156: =Data_FAME!AO163 -> 3.4901568 | AD156: =Data_FAME!AV163 -> 177.09076 | AE156: =Data_FAME!AW163 -> 177.09077 | AG156: ='[2]VAR expectations'!C164 -> 2.6222316 | AH156: =Data_FAME!AS163 -> 0.97211634 | AI156: ='Data_FAME (2)'!P163 -> 134.59702 | AJ156: =Data_FAME!AI163 -> 83.211438 | AM156: ='Data_FAME (2)'!BF163 -> 146.37555 | AN156: ='Data_FAME (2)'!BG163 -> 277.06973 | AO156: ='Data_FAME (2)'!BH163 -> 58.33398 | AP156: ='Data_FAME (2)'!BI163 -> 518.22073
B157: =Data_FAME!A164 -> 46934 | E157: =Data_FAME!D164 -> 139.85387 | I157: ='Data_FAME (2)'!L164 -> 0 | J157: ='Data_FAME (2)'!M164 -> 0 | K157: ='Data_FAME (2)'!O164 -> 0 | N157: =Data_FAME!R164 -> 738059.62 | P157: =Data_FAME!U164 -> -1.2781854 | R157: =Data_FAME!X164 -> 1105659.2 | T157: =Data_FAME!AA164 -> 0.048451841 | V157: =Data_FAME!AE164 -> 734.32554 | Z157: =Data_FAME!AN164 -> 3.5168931 | AA157: =Data_FAME!AO164 -> 3.5168931 | AD157: =Data_FAME!AV164 -> 177.87613 | AE157: =Data_FAME!AW164 -> 177.87615 | AG157: ='[2]VAR expectations'!C165 -> 2.6420013 | AH157: =Data_FAME!AS164 -> 0.97121443 | AI157: ='Data_FAME (2)'!P164 -> 133.93665 | AJ157: =Data_FAME!AI164 -> 83.089805 | AM157: ='Data_FAME (2)'!BF164 -> 146.73083 | AN157: ='Data_FAME (2)'!BG164 -> 276.4363 | AO157: ='Data_FAME (2)'!BH164 -> 58.33497 | AP157: ='Data_FAME (2)'!BI164 -> 518.4979
B158: =Data_FAME!A165 -> 47026 | E158: =Data_FAME!D165 -> 139.85387 | I158: ='Data_FAME (2)'!L165 -> 0 | J158: ='Data_FAME (2)'!M165 -> 0 | K158: ='Data_FAME (2)'!O165 -> 0 | N158: =Data_FAME!R165 -> 741431.62 | P158: =Data_FAME!U165 -> -1.2382119 | R158: =Data_FAME!X165 -> 1108222.5 | T158: =Data_FAME!AA165 -> 0.047972324 | V158: =Data_FAME!AE165 -> 740.21052 | Z158: =Data_FAME!AN165 -> 3.5462896 | AA158: =Data_FAME!AO165 -> 3.5462896 | AD158: =Data_FAME!AV165 -> 178.61289 | AE158: =Data_FAME!AW165 -> 178.61291 | AG158: ='[2]VAR expectations'!C166 -> 2.6284768 | AH158: =Data_FAME!AS165 -> 0.97018549 | AI158: ='Data_FAME (2)'!P165 -> 134.87225 | AJ158: =Data_FAME!AI165 -> 82.970359 | AM158: ='Data_FAME (2)'!BF165 -> 146.73083 | AN158: ='Data_FAME (2)'!BG165 -> 276.4363 | AO158: ='Data_FAME (2)'!BH165 -> 58.33497 | AP158: ='Data_FAME (2)'!BI165 -> 518.4979
B159: =Data_FAME!A166 -> 47118 | E159: =Data_FAME!D166 -> 139.85387 | I159: ='Data_FAME (2)'!L166 -> 0 | J159: ='Data_FAME (2)'!M166 -> 0 | K159: ='Data_FAME (2)'!O166 -> 0 | N159: =Data_FAME!R166 -> 744811.57 | P159: =Data_FAME!U166 -> -1.1823681 | R159: =Data_FAME!X166 -> 1110769.1 | T159: =Data_FAME!AA166 -> 0.047406381 | V159: =Data_FAME!AE166 -> 746.35252 | Z159: =Data_FAME!AN166 -> 3.5778306 | AA159: =Data_FAME!AO166 -> 3.5778306 | AD159: =Data_FAME!AV166 -> 179.2077 | AE159: =Data_FAME!AW166 -> 179.20772 | AG159: ='[2]VAR expectations'!C167 -> 2.6276947 | AH159: =Data_FAME!AS166 -> 0.96942556 | AI159: ='Data_FAME (2)'!P166 -> 135.45874 | AJ159: =Data_FAME!AI166 -> 82.852815 | AM159: ='Data_FAME (2)'!BF166 -> 146.73083 | AN159: ='Data_FAME (2)'!BG166 -> 276.4363 | AO159: ='Data_FAME (2)'!BH166 -> 58.33497 | AP159: ='Data_FAME (2)'!BI166 -> 518.4979

Sheet Data_FAME (2)
C1: Start date | D1: Last date
C2: 1990m2 | D2: 2025m12 | AU2: BPROJM((IKBI.M-BQAT.M)/(IKBL.M-BPIC.M),BQKL.M,"E") | AZ2: PUB12MEAN.Q
A3: Variable | B3: CPI | F3: Services | H3: Core goods | J3: Food | O3: Energy | R3: Resource utilization | AE3: Labour cost | AI3: Exchange rate | AM3: Expected average overnight rate | AO3: Bank Rate (adjusted for QE) | AS3: Import price | AU3: Import price excluding fuel | AW3: Global inflation | AZ3: Inflation expectation | BG3: Weights
A5: Indicator | B5: Headline CPI | C5: Adjusted headline CPI | D5: Forecasted CPI | F5: CPI services | G5: CPI_srv_f | H5: CPI core goods | I5: CPI_cg_f | J5: CPI food | K5: CPI_f_f | M5: CPI food + alcohol & tobacco | N5: CPI Food_at_f | O5: CPI energy | P5: CPI_e_f | R5: GDP | U5: Capac Utiliz | X5: Hours worked | AA5: Unemployment rate | AE5: Wages | AI5: Sterling ERI | AM5: 3-month OIS | AO5: UK instantaneous nominal forward curve (OIS) and Bank calculations
A6: FAME original series | B6: ="conv2qa(X12(stifidx.m,MULT," & TEXT($C$2,"yyyy""m""m") & "," & TEXT($D$2,"yyyy""m""m") & "))" -> conv2qa(X12(stifidx.m,MULT,1990m2,2025m12)) | C6: ="conv2qa(X12(fprojm(stifidx_clothingadjusted.m,stifidx.m,""L""),MULT," & TEXT(C2,"yyyy""m""m") & "," & TEXT(D2,"yyyy""m""m") & "))" -> conv2qa(X12(fprojm(stifidx_clothingadjusted.m,stifidx.m,"L"),MULT,1990m2,2025m12)) | D6: N25_cpisa_FIN.q | F6: ="conv2qa(X12(stif_srv.m,MULT," & TEXT($C$2,"yyyy""m""m") & "," & TEXT($D$2,"yyyy""m""m") & "))" -> conv2qa(X12(stif_srv.m,MULT,1990m2,2025m12)) | H6: ="conv2qa(X12(stif_gds_xeatfnab.m,MULT," & TEXT($C$2,"yyyy""m""m") & "," & TEXT($D$2,"yyyy""m""m") & "))" -> conv2qa(X12(stif_gds_xeatfnab.m,MULT,1990m2,2025m12)) | J6: ="conv2qa(X12(stif_fnab.m,MULT," & TEXT($C$2,"yyyy""m""m") & "," & TEXT($D$2,"yyyy""m""m") & "))" -> conv2qa(X12(stif_fnab.m,MULT,1990m2,2025m12)) | L6: ="conv2qa(cpi_aggregation(stif_fnab.m, booze.m, fags.m,#,#,#,#,#,#,#,#,#,#,#,#,#,#,#,#,#))" -> conv2qa(cpi_aggregation(stif_fnab.m, booze.m, fags.m,#,#,#,#,#,#,#,#,#,#,#,#,#,#,#,#,#)) | M6: ="conv2qa(X12(cpi_aggregation(stif_fnab.m, booze.m, fags.m,#,#,#,#,#,#,#,#,#,#,#,#,#,#,#,#,#),MULT," & TEXT($C$2,"yyyy""m""m") & "," & TEXT($D$2,"yyyy""m""m") & "))" -> conv2qa(X12(cpi_aggregation(stif_fnab.m, booze.m, fags.m,#,#,#,#,#,#,#,#,#,#,#,#,#,#,#,#,#),MULT,1990m2,2025m12)) | O6: ="conv2qa(X12(stif_pu.m,MULT," & TEXT($C$2,"yyyy""m""m") & "," & TEXT($D$2,"yyyy""m""m") & "))" -> conv2qa(X12(stif_pu.m,MULT,1990m2,2025m12)) | P6: conv2qa(X12(stif_pu.m,MULT,1990m2,2028m12)) | R6: mod_gdpkp.q | S6: N25_gdpkp_FIN.q | T6: Combined | U6: mod_capu.q | V6: N25_capu_FIN.q | W6: Combined | X6: mod_hrs.q | Y6: N25_hrs_FIN.q | Z6: Combined | AA6: mod_unemp.q | AB6: N25_unemp_FIN.q | AC6: Combined | AE6: conv2qa(OVERLAY(KAJ2_DP.M,KAJ2_HIST.M)) | AF6: N25_AWERPS_FIN.q | AG6: Combined | AI6: CONV2QA(SERI.B) | AJ6: N25_EER_FIN.q | AK6: Combined | AM6: CONV2QA(BPROJA(VRPSPOT(OIS,UK,0.25),BPROJA(VRPSPOT(NOM,UK,0.25),VRPSPOT(BLC,UK,0.25),3Mar1997),"E")) | AO6: mod_rgawqe.q | AP6: N25_rgawqe_FIN.q | AQ6: Combined | AS6: mod_pmdef.q | AT6: N25_pmdef_FIN.q | AU6: CONV2QA(BPROJM((IKBI.M-BQAT.M)/(IKBL.M-BPIC.M),BQKL.M,"E")) | AW6: mod_cpif.q | AX6: N25_cpif_FIN.q | AZ6: PUB12MEDIAN.Q | BA6: CONV2QA(cgrp.m) | BB6: fprojm(PUB12MEDIAN.Q,CONV2QA(cgrp.m),""L"") | BC6: BPROJA(conv2qa(cgrp.m),PUB12MEDIAN.Q,"E") | BG6: CONV2QA(STIF_GDS_XEATFNAB_wgt.m) | BH6: CONV2QA(stif_pu_wgt.m) | BI6: CONV2QA(stif_srv_wgt.m) | BK6: CONV2QA(stif_fnab_wgt.m) | BL6: CONV2QA(booze_wgt.m) | BM6: CONV2QA(fags_wgt.m)
A7: FAME transformation
A8: Comments | B8: Official STIF headline CPI series interpolated from monthly to quarterly. Seasonally adjusted manually. | C8: Back data adjusted to account for ONS mismeasurement of clothing prices in the late-1990s and early-2000s. Projected forward with the STIF to the official STIF horizon. Seasonally adjusted manually. | F8: Services interpolated STIF series. Seasonally adjusted manually | H8: Core good interpolated STIF series. Seasonally adjusted manually | J8: Food interpolated STIF series. Seasonally adjusted manually | O8: Energy interpolated STIF series. Seasonally adjusted manually | AE8: Private sector regular pay | AZ8: Barclays BASIX 1yr ahead median inflation expectations | BA8: Citigroup inflation expectation for 12 months ahead since Nov-2005 | BB8: Combined expectation ( B + City growth | BC8: Combined expectation (City + Barclays backdata growth) | BF8: Food&at | BG8: Core goods | BH8: Energy | BI8: Services | BK8: Food | BL8: Alcohol | BM8: Tobacco
A9: My R code | B9: cpi | C9: cpi_a | D9: cpi_f | F9: services | G9: services_f | H9: core_gds | I9: core_gds_f | J9: food | K9: food_f | L9: food_at_nsa | M9: food_at | N9: food_at_f | O9: energy | P9: energy_f | R9: gdpkp | S9: gdpkp_f | U9: capu | V9: capu_f | X9: hrs | Y9: hrs_f | AA9: unemp | AB9: unemp_f | AE9: wage | AF9: wage_f | AI9: eer | AJ9: eer_f | AM9: ois_rate | AO9: bank_rate | AP9: bank_rate_f | AS9: pmdef | AT9: pmdef_f | AU9: pmdef_xf | AW9: cpif | AX9: cpif_f | BB9: inf_exp | BD9: inf_exp_f | BF9: fat_wgt | BG9: cf_wgt | BH9: e_wgt | BI9: s_wgt
A10: =[3]!FAMEData("FAMEDATE", "1990", "2028", 0,"Quarterly", "Down", "Heading", "Normal") -> FAMEDATE | B10: =[3]!FAMEData(B6, "1990", "2029", 0,"Quarterly", "Down", "Heading", "Normal") -> conv2qa(X12(stifidx.m,MULT,1990m2,2025m12)) | C10: =[3]!FAMEData(C6, "1990", "2028", 0,"Quarterly", "Down", "Heading", "Normal") -> conv2qa(X12(fprojm(stifidx_clothingadjusted.m,stifidx.m,"L"),MULT,1990m2,2025m12)) | D10: =[3]!FAMEData(D6, "1990", "2028", 0,"Quarterly", "Down", "Heading", "Normal") -> N25_cpisa_FIN.q | F10: =[3]!FAMEData(F6, "1990", "2028", 0,"Quarterly", "Down", "Heading", "Normal") -> conv2qa(X12(stif_srv.m,MULT,1990m2,2025m12)) | H10: =[3]!FAMEData(H6, "1990", "2028", 0,"Quarterly", "Down", "Heading", "Normal") -> conv2qa(X12(stif_gds_xeatfnab.m,MULT,1990m2,2025m12)) | J10: =[3]!FAMEData(J6, "1990", "2028", 0,"Quarterly", "Down", "Heading", "Normal") -> conv2qa(X12(stif_fnab.m,MULT,1990m2,2025m12)) | L10: =[3]!FAMEData(L6, "1990", "2028", 0,"Quarterly", "Down", "Heading", "Normal") -> conv2qa(cpi_aggregation(stif_fnab.m, booze.m, fags.m,#,#,#,#,#,#,#,#,#,#,#,#,#,#,#,#,#)) | M10: =[3]!FAMEData(M6, "1990", "2028", 0,"Quarterly", "Down", "Heading", "Normal") -> conv2qa(X12(cpi_aggregation(stif_fnab.m, booze.m, fags.m,#,#,#,#,#,#,#,#,#,#,#,#,#,#,#,#,#),MULT,1990m2,2025m12)) | O10: =[3]!FAMEData(O6, "1990", "2028", 0,"Quarterly", "Down", "Heading", "Normal") -> Refresh | P10: =[3]!FAMEData(P6, "1990", "2028", 0,"Quarterly", "Down", "Heading", "Normal") -> conv2qa(X12(stif_pu.m,MULT,1990m2,2028m12)) | Q10: =[3]!FAMEData(Q6, "1990", "2028", 0,"Quarterly", "Down", "Heading", "Normal") -> Refresh | R10: =[3]!FAMEData(R6, "1990", "2028", 0,"Quarterly", "Down", "Heading", "Normal") -> mod_gdpkp.q | S10: =[3]!FAMEData(S6, "1990", "2028", 0,"Quarterly", "Down", "Heading", "Normal") -> Refresh | U10: =[3]!FAMEData(U6, "1990", "2028", 0,"Quarterly", "Down", "Heading", "Normal") -> mod_capu.q | V10: =[3]!FAMEData(V6, "1990", "2028", 0,"Quarterly", "Down", "Heading", "Normal") -> Refresh | X10: =[3]!FAMEData(X6, "1990", "2028", 0,"Quarterly", "Down", "Heading", "Normal") -> mod_hrs.q | Y10: =[3]!FAMEData(Y6, "1990", "2028", 0,"Quarterly", "Down", "Heading", "Normal") -> Refresh | AA10: =[3]!FAMEData(AA6, "1990", "2028", 0,"Quarterly", "Down", "Heading", "Normal") -> mod_unemp.q | AB10: =[3]!FAMEData(AB6, "1990", "2028", 0,"Quarterly", "Down", "Heading", "Normal") -> Refresh | AD10: =[3]!FAMEData(AD6, "1990", "2028", 0,"Quarterly", "Down", "Heading", "Normal") -> #N/A | AE10: =[3]!FAMEData(AE6, "1990", "2028", 0,"Quarterly", "Down", "Heading", "Normal") -> conv2qa(OVERLAY(KAJ2_DP.M,KAJ2_HIST.M)) | AF10: =[3]!FAMEData(AF6, "1990", "2028", 0,"Quarterly", "Down", "Heading", "Normal") -> Refresh | AH10: =[3]!FAMEData(AH6, "1990", "2028", 0,"Quarterly", "Down", "Heading", "Normal") -> #N/A | AI10: =[3]!FAMEData(AI6, "1990", "2028", 0,"Quarterly", "Down", "Heading", "Normal") -> CONV2QA(SERI.B) | AJ10: =[3]!FAMEData(AJ6, "1990", "2028", 0,"Quarterly", "Down", "Heading", "Normal") -> Refresh | AL10: =[3]!FAMEData(AL6, "1990", "2028", 0,"Quarterly", "Down", "Heading", "Normal") -> #N/A | AM10: =[3]!FAMEData(AM6, "1990", "2028", 0,"Quarterly", "Down", "Heading", "Normal") -> Refresh | AO10: =[3]!FAMEData(AO6, "1990", "2028", 0,"Quarterly", "Down", "Heading", "Normal") -> mod_rgawqe.q | AP10: =[3]!FAMEData(AP6, "1990", "2028", 0,"Quarterly", "Down", "Heading", "Normal") -> Refresh | AR10: =[3]!FAMEData(AR6, "1990", "2028", 0,"Quarterly", "Down", "Heading", "Normal") -> #N/A | AS10: =[3]!FAMEData(AS6, "1990", "2028", 0,"Quarterly", "Down", "Heading", "Normal") -> mod_pmdef.q | AT10: =[3]!FAMEData(AT6, "1990", "2028", 0,"Quarterly", "Down", "Heading", "Normal") -> N25_pmdef_FIN.q | AU10: =[3]!FAMEData(AU6, "1990", "2028", 0,"Quarterly", "Down", "Heading", "Normal") -> Refresh | AW10: =[3]!FAMEData(AW6, "1990", "2028", 0,"Quarterly", "Down", "Heading", "Normal") -> mod_cpif.q | AX10: =[3]!FAMEData(AX6, "1990", "2028", 0,"Quarterly", "Down", "Heading", "Normal") -> Refresh | AZ10: =[3]!FAMEData(AZ6, "1990", "2028", 0,"Quarterly", "Down", "Heading", "Normal") -> PUB12MEDIAN.Q | BA10: =[3]!FAMEData(BA6, "1990", "2028", 0,"Quarterly", "Down", "Heading", "Normal") -> CONV2QA(cgrp.m) | BB10: =[3]!FAMEData(BB6, "1990", "2028", 0,"Quarterly", "Down", "Heading", "Normal") -> fprojm(PUB12MEDIAN.Q,CONV2QA(cgrp.m),""L"") | BC10: =[3]!FAMEData(BC6, "1990", "2028", 0,"Quarterly", "Down", "Heading", "Normal") -> Refresh | BG10: =[3]!FAMEData(BG6, "1990", "2028", 0,"Quarterly", "Down", "Heading", "Normal") -> CONV2QA(STIF_GDS_XEATFNAB_wgt.m) | BH10: =[3]!FAMEData(BH6, "1990", "2028", 0,"Quarterly", "Down", "Heading", "Normal") -> CONV2QA(stif_pu_wgt.m) | BI10: =[3]!FAMEData(BI6, "1990", "2028", 0,"Quarterly", "Down", "Heading", "Normal") -> CONV2QA(stif_srv_wgt.m) | BK10: =[3]!FAMEData(BK6, "1990", "2028", 0,"Quarterly", "Down", "Heading", "Normal") -> CONV2QA(stif_fnab_wgt.m) | BL10: =[3]!FAMEData(BL6, "1990", "2028", 0,"Quarterly", "Down", "Heading", "Normal") -> CONV2QA(booze_wgt.m) | BM10: =[3]!FAMEData(BM6, "1990", "2028", 0,"Quarterly", "Down", "Heading", "Normal") -> CONV2QA(fags_wgt.m)
A11: 32963 | D11: 54.233282 | L11: 45.323672 | R11: 379458 | S11: 379458 | U11: -0.70757743 | V11: 0.97333792 | X11: 908133 | Y11: 908133 | AA11: 0.069332964 | AB11: 0.069332964 | AE11: 183.54771 | AF11: 183.54771 | AI11: 92.432746 | AJ11: 92.432746 | AO11: 14.875 | AP11: 14.875 | AS11: 0.57372025 | AT11: 0.57372025 | AU11: 0.60812747 | AW11: 66.518783 | AX11: 66.518783 | AZ11: 8.1689655 | BB11: 8.1689655 | BC11: 7.7756322 | BF11: =+BK11+BL11+BM11 -> 251 | BG11: 359 | BH11: 96 | BI11: 294 | BK11: 185 | BL11: 26 | BM11: 40
A12: 33054 | B12: 55.216192 | C12: 53.449601 | D12: 55.931591 | F12: 37.291624 | H12: 109.4919 | J12: 55.346352 | L12: 46.757461 | M12: 46.254605 | O12: 33.809155 | P12: 33.809155 | R12: 381997 | S12: 381997 | U12: -1.1483808 | V12: 0.93596216 | X12: 906588.84 | Y12: 906588.84 | AA12: 0.069184781 | AB12: 0.069184781 | AE12: 189.32838 | AF12: 189.32838 | AI12: 93.068646 | AJ12: 93.068646 | AM12: 14.519134 | AO12: 14.875 | AP12: 14.875 | AS12: 0.57773628 | AT12: 0.57773628 | AU12: 0.60985266 | AW12: 67.416856 | AX12: 67.416856 | AZ12: 9.0307167 | BB12: 9.0307167 | BC12: 8.6373834 | BF12: =+BK12+BL12+BM12 -> 251 | BG12: 359 | BH12: 96 | BI12: 294 | BK12: 185 | BL12: 26 | BM12: 40
A13: 33146 | B13: 56.369272 | C13: 54.565685 | D13: 56.730638 | F13: 38.226404 | H13: 110.77076 | J13: 56.069625 | L13: 46.959972 | M13: 47.031491 | O13: 35.502014 | P13: 35.502014 | R13: 377831 | S13: 377831 | U13: -1.7358221 | V13: -0.79049292 | X13: 901813.5 | Y13: 901813.5 | AA13: 0.070779647 | AB13: 0.070779647 | AE13: 193.61239 | AF13: 193.61239 | AI13: 99.445968 | AJ13: 99.445968 | AM13: 14.377204 | AO13: 14.875 | AP13: 14.875 | AS13: 0.55930606 | AT13: 0.55930606 | AU13: 0.59130693 | AW13: 68.109698 | AX13: 68.109698 | AZ13: 9.49729 | BB13: 9.49729 | BC13: 9.1039566 | BF13: =+BK13+BL13+BM13 -> 251 | BG13: 359 | BH13: 96 | BI13: 294 | BK13: 185 | BL13: 26 | BM13: 40
A14: 33238 | B14: 57.494732 | C14: 55.655628 | D14: 57.774359 | F14: 39.201503 | H14: 112.05037 | J14: 57.003542 | L14: 47.50451 | M14: 47.936474 | O14: 36.723481 | P14: 36.723481 | R14: 375916 | S14: 375916 | U14: -2.1830843 | V14: -1.1706663 | X14: 892410.87 | Y14: 892410.87 | AA14: 0.074650616 | AB14: 0.074650616 | AE14: 197.31141 | AF14: 197.31141 | AI14: 99.670858 | AJ14: 99.670858 | AM14: 13.268016 | AO14: 13.9531 | AP14: 13.9531 | AS14: 0.56615029 | AT14: 0.56615029 | AU14: 0.5885035 | AW14: 69.42033 | AX14: 69.42033 | AZ14: 7.872807 | BB14: 7.872807 | BC14: 7.4794737 | BF14: =+BK14+BL14+BM14 -> 251 | BG14: 359 | BH14: 96 | BI14: 294 | BK14: 185 | BL14: 26 | BM14: 40
A15: 33328 | B15: 58.131185 | C15: 56.271618 | D15: 58.016017 | F15: 40.047704 | H15: 112.98292 | J15: 57.575944 | L15: 48.473466 | M15: 48.483131 | O15: 36.121607 | P15: 36.121607 | R15: 374060 | S15: 374060 | U15: -2.9343664 | V15: -1.255856 | X15: 881370.83 | Y15: 881370.83 | AA15: 0.079969483 | AB15: 0.079969483 | AE15: 199.57143 | AF15: 199.57143 | AI15: 99.118131 | AJ15: 99.118131 | AM15: 12.723411 | AO15: 13.3992 | AP15: 13.3992 | AS15: 0.56293382 | AT15: 0.56293382 | AU15: 0.59734507 | AW15: 70.402484 | AX15: 70.402484 | AZ15: 7.5657895 | BB15: 7.5657895 | BC15: 7.1724561 | BF15: =+BK15+BL15+BM15 -> 242 | BG15: 363 | BH15: 93 | BI15: 302 | BK15: 177 | BL15: 27 | BM15: 38
A16: 33419 | B16: 59.827705 | C16: 57.9136 | D16: 60.59482 | F16: 41.709306 | H16: 115.1372 | J16: 58.344421 | L16: 50.505217 | M16: 49.975838 | O16: 37.362098 | P16: 37.362098 | R16: 373608 | S16: 373608 | U16: -3.3312328 | V16: -1.273024 | X16: 869788.47 | Y16: 869788.47 | AA16: 0.086627038 | AB16: 0.086627038 | AE16: 204.08804 | AF16: 204.08804 | AI16: 96.421142 | AJ16: 96.421142 | AM16: 11.097574 | AO16: 11.7379 | AP16: 11.7379 | AS16: 0.57235316 | AT16: 0.57235316 | AU16: 0.60942136 | AW16: 71.079089 | AX16: 71.079089 | AZ16: 5.978979 | BB16: 5.978979 | BC16: 5.5856456 | BF16: =+BK16+BL16+BM16 -> 242 | BG16: 363 | BH16: 93 | BI16: 302 | BK16: 177 | BL16: 27 | BM16: 38
A17: 33511 | B17: 60.749441 | C17: 58.805692 | D17: 61.129417 | F17: 42.478114 | H17: 116.63678 | J17: 58.886712 | L17: 50.449029 | M17: 50.515686 | O17: 38.223615 | P17: 38.223615 | R17: 372878 | S17: 372878 | U17: -3.4757524 | V17: -1.2520863 | X17: 859520.46 | Y17: 859520.46 | AA17: 0.09159133 | AB17: 0.09159133 | AE17: 208.2244 | AF17: 208.2244 | AI17: 95.722653 | AJ17: 95.722653 | AM17: 10.282062 | AO17: 10.7981 | AP17: 10.7981 | AS17: 0.58356049 | AT17: 0.58356049 | AU17: 0.61934117 | AW17: 71.94639 | AX17: 71.94639 | AZ17: 5.0018519 | BB17: 5.0018519 | BC17: 4.6085185 | BF17: =+BK17+BL17+BM17 -> 242 | BG17: 363 | BH17: 93 | BI17: 302 | BK17: 177 | BL17: 27 | BM17: 38
A18: 33603 | B18: 61.5371 | C18: 59.568663 | D18: 61.822885 | F18: 43.254296 | H18: 117.83569 | J18: 59.515813 | L18: 50.749747 | M18: 51.223588 | O18: 38.311037 | P18: 38.311037 | R18: 373357 | S18: 373357 | U18: -3.1182875 | V18: -1.0417908 | X18: 851930 | Y18: 851930 | AA18: 0.094575166 | AB18: 0.094575166 | AE18: 211.35106 | AF18: 211.35106 | AI18: 96.172297 | AJ18: 96.172297 | AM18: 10.071213 | AO18: 10.375 | AP18: 10.375 | AS18: 0.57552587 | AT18: 0.57552587 | AU18: 0.61287173 | AW18: 72.918164 | AX18: 72.918164 | AZ18: 4.8059006 | BB18: 4.8059006 | BC18: 4.4125673 | BF18: =+BK18+BL18+BM18 -> 242 | BG18: 363 | BH18: 93 | BI18: 302 | BK18: 177 | BL18: 27 | BM18: 38
A19: 33694 | B19: 62.131083 | C19: 60.143593 | D19: 62.056834 | F19: 43.882111 | H19: 118.7579 | J19: 59.959978 | L19: 51.685557 | M19: 51.670967 | O19: 38.258535 | P19: 38.258535 | R19: 373317 | S19: 373317 | U19: -3.3500751 | V19: -1.1690213 | X19: 847165.67 | Y19: 847165.67 | AA19: 0.097007586 | AB19: 0.097007586 | AE19: 215.27103 | AF19: 215.27103 | AI19: 95.797952 | AJ19: 95.797952 | AM19: 10.079292 | AO19: 10.375 | AP19: 10.375 | AS19: 0.56924052 | AT19: 0.56924052 | AU19: 0.61394997 | AW19: 73.684026 | AX19: 73.684026 | AZ19: 4.7386667 | BB19: 4.7386667 | BC19: 4.3453333 | BF19: =+BK19+BL19+BM19 -> 244 | BG19: 360 | BH19: 91 | BI19: 305 | BK19: 172 | BL19: 31 | BM19: 41
A20: 33785 | B20: 62.416759 | C20: 60.420047 | D20: 63.194403 | F20: 44.452914 | H20: 118.72539 | J20: 59.723829 | L20: 52.427892 | M20: 51.90606 | O20: 38.383855 | P20: 38.383855 | R20: 372751 | S20: 372751 | U20: -3.1236345 | V20: -1.8203614 | X20: 847646.6 | Y20: 847646.6 | AA20: 0.09785394 | AB20: 0.09785394 | AE20: 216.52634 | AF20: 216.52634 | AI20: 97.573482 | AJ20: 97.573482 | AM20: 9.7404194 | AO20: 10.0471 | AP20: 10.0471 | AS20: 0.56506054 | AT20: 0.56506054 | AU20: 0.60791183 | AW20: 74.734655 | AX20: 74.734655 | AZ20: 4.4401198 | BB20: 4.4401198 | BC20: 4.0467864 | BF20: =+BK20+BL20+BM20 -> 244 | BG20: 360 | BH20: 91 | BI20: 305 | BK20: 172 | BL20: 31 | BM20: 41
A21: 33877 | B21: 62.691059 | C21: 60.685211 | D21: 63.067373 | F21: 44.967908 | H21: 118.80745 | J21: 59.567454 | L21: 51.973211 | M21: 52.023965 | O21: 38.275282 | P21: 38.275282 | R21: 374537 | S21: 374537 | U21: -3.3243309 | V21: -0.85749752 | X21: 840427.1 | Y21: 840427.1 | AA21: 0.099370554 | AB21: 0.099370554 | AE21: 219.44681 | AF21: 219.44681 | AI21: 96.710815 | AJ21: 96.710815 | AM21: 9.695813 | AO21: 9.7673 | AP21: 9.7673 | AS21: 0.56539814 | AT21: 0.56539814 | AU21: 0.60273627 | AW21: 75.563565 | AX21: 75.563565 | AZ21: 4.234767 | BB21: 4.234767 | BC21: 3.8414337 | BF21: =+BK21+BL21+BM21 -> 244 | BG21: 360 | BH21: 91 | BI21: 305 | BK21: 172 | BL21: 31 | BM21: 41
A22: 33969 | B22: 63.195466 | C22: 61.173856 | D22: 63.467567 | F22: 45.533479 | H22: 118.62097 | J22: 60.084592 | L22: 52.154689 | M22: 52.659248 | O22: 38.984401 | P22: 38.984401 | R22: 377418 | S22: 377418 | U22: -3.2279251 | V22: -0.27664328 | X22: 832788.39 | Y22: 832788.39 | AA22: 0.10371119 | AB22: 0.10371119 | AE22: 221.35146 | AF22: 221.35146 | AI22: 84.845339 | AJ22: 84.845339 | AM22: 7.1698732 | AO22: 7.5313 | AP22: 7.5313 | AS22: 0.59920423 | AT22: 0.59920423 | AU22: 0.64263116 | AW22: 76.644093 | AX22: 76.644093 | AZ22: 3.9262048 | BB22: 3.9262048 | BC22: 3.5328715 | BF22: =+BK22+BL22+BM22 -> 244 | BG22: 360 | BH22: 91 | BI22: 305 | BK22: 172 | BL22: 31 | BM22: 41
A23: 34059 | B23: 63.53193 | C23: 61.499755 | D23: 63.530914 | F23: 46.101573 | H23: 118.15539 | J23: 60.484175 | L23: 53.053856 | M23: 53.005409 | O23: 39.383108 | P23: 39.383108 | R23: 379370 | S23: 379370 | U23: -3.0780999 | V23: -0.54416477 | X23: 832300.53 | Y23: 832300.53 | AA23: 0.10618491 | AB23: 0.10618491 | AE23: 221.58357 | AF23: 221.58357 | AI23: 83.282759 | AJ23: 83.282759 | AM23: 5.9494269 | AO23: 6.129 | AP23: 6.129 | AS23: 0.62407768 | AT23: 0.62407768 | AU23: 0.67454707 | AW23: 77.756408 | AX23: 77.756408 | AZ23: 3.4645161 | BB23: 3.4645161 | BC23: 3.0711828 | BF23: =+BK23+BL23+BM23 -> 228 | BG23: 343 | BH23: 91 | BI23: 338 | BK23: 159 | BL23: 30 | BM23: 39
... A74: 38717 | B74: 78.662785 | C74: 77.824911 | D74: 78.650458 | F74: 72.769712 | H74: 99.585812 | J74: 71.488262 | L74: 69.066725 | M74: 69.148832 | O74: 62.212631 | P74: 62.212631 | R74: 556311 | S74: 556311 | U74: 0.18833164 | V74: -0.32157998 | X74: 929270.73 | Y74: 929270.73 | AA74: 0.051464698 | AB74: 0.051464698 | AE74: 356.56273 | AF74: 356.56273 | AI74: 99.510515 | AJ74: 99.510515 | AM74: 4.3645593 | AO74: 4.5 | AP74: 4.5 | AS74: 0.63647439 | AT74: 0.63649118 | AU74: 0.66417039 | AW74: 106.95005 | AX74: 106.95874 | AZ74: 2.72 | BB74: 2.72 | BC74: 2.3266667 | BF74: =+BK74+BL74+BM74 -> 152 | BG74: 329 | BH74: 55 | BI74: 464 | BK74: 106 | BL74: 20 | BM74: 26
A75: 38807 | B75: 79.029348 | C75: 78.240803 | D75: 78.979696 | F75: 73.378211 | H75: 99.205958 | J75: 71.887081 | L75: 69.399662 | M75: 69.456223 | O75: 63.507441 | P75: 63.507441 | R75: 558314 | S75: 558314 | U75: 0.23866415 | V75: -0.36700616 | X75: 931711.6 | Y75: 931711.6 | AA75: 0.052340419 | AB75: 0.052340419 | AE75: 360.69047 | AF75: 360.69047 | AI75: 98.760283 | AJ75: 98.760283 | AM75: 4.3369085 | AO75: 4.5 | AP75: 4.5 | AS75: 0.64392875 | AT75: 0.64393675 | AU75: 0.66759821 | AW75: 107.52157 | AX75: 107.5325 | AZ75: 2.86 | BA75: 2.4666667 | BB75: 2.86 | BC75: 2.4666667 | BF75: =+BK75+BL75+BM75 -> 146 | BG75: 341 | BH75: 67 | BI75: 446 | BK75: 102 | BL75: 18 | BM75: 26
A76: 38898 | B76: 79.618023 | C76: 78.892208 | D76: 79.688486 | F76: 74.0114 | H76: 98.655423 | J76: 72.380874 | L76: 70.175477 | M76: 69.890028 | O76: 67.672092 | P76: 67.672092 | R76: 559795 | S76: 559795 | U76: 0.57499474 | V76: -0.059382452 | X76: 930502.81 | Y76: 930502.81 | AA76: 0.054720238 | AB76: 0.054720238 | AE76: 364.6037 | AF76: 364.6037 | AI76: 100.27914 | AJ76: 100.27914 | AM76: 4.4311161 | AO76: 4.5 | AP76: 4.5 | AS76: 0.64502189 | AT76: 0.64504573 | AU76: 0.66422754 | AW76: 108.38226 | AX76: 108.4046 | AZ76: 2.58 | BA76: 2.4 | BB76: 2.58 | BC76: 2.4 | BF76: =+BK76+BL76+BM76 -> 146 | BG76: 341 | BH76: 67 | BI76: 446 | BK76: 102 | BL76: 18 | BM76: 26
A77: 38990 | B77: 80.269783 | C77: 79.587648 | D77: 80.314088 | F77: 74.553781 | H77: 98.574413 | J77: 73.986747 | L77: 71.140855 | M77: 71.285671 | O77: 70.05051 | P77: 70.05051 | R77: 560675 | S77: 560675 | U77: 0.7443586 | V77: 0.038059171 | X77: 931829.12 | Y77: 931829.12 | AA77: 0.054843628 | AB77: 0.054843628 | AE77: 367.62989 | AF77: 367.62989 | AI77: 102.33265 | AJ77: 102.33265 | AM77: 4.6392397 | AO77: 4.6602 | AP77: 4.6602 | AS77: 0.644692 | AT77: 0.644692 | AU77: 0.6673308 | AW77: 108.91792 | AX77: 108.92523 | AZ77: 2.83 | BA77: 2.3 | BB77: 2.83 | BC77: 2.3 | BF77: =+BK77+BL77+BM77 -> 146 | BG77: 341 | BH77: 67 | BI77: 446 | BK77: 102 | BL77: 18 | BM77: 26
A78: 39082 | B78: 80.789341 | C78: 80.161173 | D78: 80.767606 | F78: 75.449961 | H78: 98.560412 | J78: 74.86975 | L78: 71.968051 | M78: 72.057899 | O78: 69.842533 | P78: 69.842533 | R78: 562669 | S78: 562669 | U78: 0.83563403 | V78: 0.061568725 | X78: 935596.33 | Y78: 935596.33 | AA78: 0.055011599 | AB78: 0.055011599 | AE78: 372.29684 | AF78: 372.29684 | AI78: 103.71343 | AJ78: 103.71343 | AM78: 4.9426583 | AO78: 4.8889 | AP78: 4.8889 | AS78: 0.63674418 | AT78: 0.63671215 | AU78: 0.66589675 | AW78: 109.24048 | AX78: 109.25189 | AZ78: 3.02 | BA78: 2.4333333 | BB78: 3.02 | BC78: 2.4333333 | BF78: =+BK78+BL78+BM78 -> 146 | BG78: 341 | BH78: 67 | BI78: 446 | BK78: 102 | BL78: 18 | BM78: 26
A79: 39172 | B79: 81.311932 | C79: 80.719798 | D79: 81.26267 | F79: 76.094721 | H79: 98.478151 | J79: 75.238914 | L79: 72.486675 | M79: 72.5512 | O79: 71.12996 | P79: 71.12996 | R79: 568845 | S79: 568845 | U79: 1.0007109 | V79: 0.38739604 | X79: 937123.73 | Y79: 937123.73 | AA79: 0.055137924 | AB79: 0.055137924 | AE79: 375.4149 | AF79: 375.4149 | AI79: 104.73003 | AJ79: 104.73003 | AM79: 5.2602442 | AO79: 5.2227 | AP79: 5.2227 | AS79: 0.62581298 | AT79: 0.62580915 | AU79: 0.6568432 | AW79: 109.94849 | AX79: 109.96318 | AZ79: 3 | BA79: 2.5333333 | BB79: 3 | BC79: 2.5333333 | BF79: =+BK79+BL79+BM79 -> 146 | BG79: 326 | BH79: 75 | BI79: 453 | BK79: 103 | BL79: 18 | BM79: 25
A80: 39263 | B80: 81.649265 | C80: 81.108139 | D80: 81.726258 | F80: 76.651412 | H80: 98.270882 | J80: 76.215934 | L80: 73.602096 | M80: 73.298258 | O80: 71.15527 | P80: 71.15527 | R80: 574194 | S80: 574194 | U80: 1.0016699 | V80: 0.36395734 | X80: 941244.91 | Y80: 941244.91 | AA80: 0.053504741 | AB80: 0.053504741 | AE80: 380.43523 | AF80: 380.43523 | AI80: 104.23937 | AJ80: 104.23937 | AM80: 5.4924851 | AO80: 5.3975 | AP80: 5.3975 | AS80: 0.63252629 | AT80: 0.63249527 | AU80: 0.66057546 | AW80: 110.8856 | AX80: 110.90526 | AZ80: 2.94 | BA80: 2.4666667 | BB80: 2.94 | BC80: 2.4666667 | BF80: =+BK80+BL80+BM80 -> 146 | BG80: 326 | BH80: 75 | BI80: 453 | BK80: 103 | BL80: 18 | BM80: 25
A81: 39355 | B81: 81.697046 | C81: 81.201365 | D81: 81.738763 | F81: 77.222044 | H81: 97.524545 | J81: 76.301598 | L81: 73.414362 | M81: 73.551324 | O81: 70.481994 | P81: 70.481994 | R81: 579605 | S81: 579605 | U81: 1.04885 | V81: 0.32741784 | X81: 943124.64 | Y81: 943124.64 | AA81: 0.053102039 | AB81: 0.053102039 | AE81: 386.18976 | AF81: 386.18976 | AI81: 104.41272 | AJ81: 104.41272 | AM81: 5.7021116 | AO81: 5.7383 | AP81: 5.7383 | AS81: 0.6342972 | AT81: 0.63428596 | AU81: 0.66029191 | AW81: 111.63179 | AX81: 111.64604 | AZ81: 2.8 | BA81: 2.5 | BB81: 2.8 | BC81: 2.5 | BF81: =+BK81+BL81+BM81 -> 146 | BG81: 326 | BH81: 75 | BI81: 453 | BK81: 103 | BL81: 18 | BM81: 25
A82: 39447 | B82: 82.495703 | C82: 82.056664 | D82: 82.455034 | F82: 77.963036 | H82: 97.459759 | J82: 78.596965 | L82: 75.090601 | M82: 75.219863 | O82: 73.077864 | P82: 73.077862 | R82: 584504 | S82: 584504 | U82: -0.52652474 | V82: 0.40657804 | X82: 943113.12 | Y82: 943113.12 | AA82: 0.051566368 | AB82: 0.051566368 | AE82: 388.13105 | AF82: 388.13105 | AI82: 101.59429 | AJ82: 101.59429 | AM82: 5.4667745 | AO82: 5.6875 | AP82: 5.6875 | AS82: 0.65152011 | AT82: 0.65156665 | AU82: 0.67170801 | AW82: 112.88041 | AX82: 112.88538 | AZ82: 3.22 | BA82: 2.7 | BB82: 3.22 | BC82: 2.7 | BF82: =+BK82+BL82+BM82 -> 146 | BG82: 326 | BH82: 75 | BI82: 453 | BK82: 103 | BL82: 18 | BM82: 25
A83: 39538 | B83: 83.242659 | C83: 82.858148 | D83: 83.221734 | F83: 78.592453 | H83: 96.980479 | J83: 79.533887 | L83: 75.946325 | M83: 75.989625 | O83: 77.885282 | P83: 77.885285 | R83: 586690 | S83: 586690 | U83: 0.018664572 | V83: -0.4204313 | X83: 955064.44 | Y83: 955064.44 | AA83: 0.05182662 | AB83: 0.05182662 | AE83: 391.92013 | AF83: 391.92013 | AI83: 95.934954 | AJ83: 95.934954 | AM83: 5.0933638 | AO83: 5.3548 | AP83: 5.3548 | AS83: 0.6775423 | AT83: 0.67751014 | AU83: 0.69147474 | AW83: 114.00672 | AX83: 114.00884 | AZ83: 3.71 | BA83: 3.3233333 | BB83: 3.71 | BC83: 3.3233333 | BF83: =+BK83+BL83+BM83 -> 151 | BG83: 323 | BH83: 73 | BI83: 453 | BK83: 109 | BL83: 18 | BM83: 24
A84: 39629 | B84: 84.397119 | C84: 84.058181 | D84: 84.4784 | F84: 79.544659 | H84: 96.706328 | J84: 82.317616 | L84: 78.715815 | M84: 78.381765 | O84: 82.676197 | P84: 82.676198 | R84: 583541 | S84: 583541 | U84: -0.67527481 | V84: -0.74769076 | X84: 944566.73 | Y84: 944566.73 | AA84: 0.053504884 | AB84: 0.053504884 | AE84: 395.699 | AF84: 395.699 | AI84: 93.071035 | AJ84: 93.071035 | AM84: 4.950754 | AO84: 5.0278 | AP84: 5.0278 | AS84: 0.7052457 | AT84: 0.70527093 | AU84: 0.71113775 | AW84: 115.2465 | AX84: 115.26661 | AZ84: 4.41 | BA84: 4.1266667 | BB84: 4.41 | BC84: 4.1266667 | BF84: =+BK84+BL84+BM84 -> 151 | BG84: 323 | BH84: 73 | BI84: 453 | BK84: 109 | BL84: 18 | BM84: 24
A85: 39721 | B85: 85.60477 | C85: 85.325866 | D85: 85.633338 | F85: 80.566569 | H85: 96.414619 | J85: 85.57378 | L85: 80.67495 | M85: 80.821325 | O85: 87.767591 | P85: 87.767588 | R85: 573961 | S85: 573961 | U85: -1.0541838 | V85: -1.1688856 | X85: 945168.4 | Y85: 945168.4 | AA85: 0.058554666 | AB85: 0.058554666 | AE85: 398.34704 | AF85: 398.34704 | AI85: 91.695079 | AJ85: 91.695079 | AM85: 4.9818732 | AO85: 5 | AP85: 5 | AS85: 0.72643695 | AT85: 0.72646358 | AU85: 0.7260517 | AW85: 115.84348 | AX85: 115.87088 | AZ85: 4.65 | BA85: 4.3404589 | BB85: 4.65 | BC85: 4.3404589 | BF85: =+BK85+BL85+BM85 -> 151 | BG85: 323 | BH85: 73 | BI85: 453 | BK85: 109 | BL85: 18 | BM85: 24
A86: 39813 | B86: 85.715219 | C86: 85.476509 | D86: 85.640878 | F86: 81.438238 | H86: 95.375476 | J86: 86.792972 | L86: 81.597333 | M86: 81.79337 | O86: 85.991099 | P86: 85.991093 | R86: 561816 | S86: 561816 | U86: -2.1036492 | V86: -1.851972 | X86: 939462.58 | Y86: 939462.58 | AA86: 0.063529284 | AB86: 0.063529284 | AE86: 400.68993 | AF86: 400.68993 | AI86: 83.94238 | AJ86: 83.94238 | AM86: 2.583527 | AO86: 3.3672 | AP86: 3.3672 | AS86: 0.72241259 | AT86: 0.72239393 | AU86: 0.74428941 | AW86: 115.15301 | AX86: 115.153 | AZ86: 3.25 | BA86: 1.5441543 | BB86: 3.25 | BC86: 1.5441543 | BF86: =+BK86+BL86+BM86 -> 151 | BG86: 323 | BH86: 73 | BI86: 453 | BK86: 109 | BL86: 18 | BM86: 24
... A131: 43921 | B131: 108.87477 | C131: 108.87464 | D131: 108.76735 | F131: 112.16416 | H131: 103.97765 | J131: 104.04929 | L131: 107.53038 | M131: 107.2733 | O131: 112.82436 | P131: 112.87122 | R131: 652180 | S131: 652180 | U131: -0.55373588 | V131: -0.9417896 | X131: 1028944.4 | Y131: 1028944.4 | AA131: 0.041026955 | AB131: 0.041026955 | AE131: 504.30445 | AF131: 504.30445 | AI131: 79.231538 | AJ131: 79.231538 | AM131: 0.49130055 | AO131: 0.23434676 | AP131: 0.23434676 | AS131: 0.8103644 | AT131: 0.81035288 | AU131: 0.84278423 | AW131: 136.31083 | AX131: 136.35214 | AZ131: 2.222 | BA131: 2.675357 | BB131: 2.222 | BC131: 2.675357 | BF131: =+BK131+BL131+BM131 -> 138.66667 | BG131: 308.33333 | BH131: 63.666667 | BI131: 489.33333 | BK131: 99 | BL131: 19.666667 | BM131: 20
A132: 44012 | B132: 108.33543 | C132: 108.33533 | D132: 108.44287 | F132: 112.3388 | H132: 103.85705 | J132: 104.34192 | L132: 107.96242 | M132: 107.74333 | O132: 102.51054 | P132: 102.46569 | R132: 522356 | S132: 522356 | U132: -4.24003 | V132: -1.5753313 | X132: 845934.54 | Y132: 845934.54 | AA132: 0.040847424 | AB132: 0.040847424 | AE132: 490.2262 | AF132: 490.2262 | AI132: 77.416985 | AJ132: 77.416985 | AM132: 0.064903233 | AO132: -0.53443525 | AP132: -0.53443525 | AS132: 0.79942922 | AT132: 0.79949974 | AU132: 0.84812666 | AW132: 135.90843 | AX132: 135.9625 | BA132: 3.0786651 | BB132: 2.5569649 | BC132: 3.0786651 | BF132: =+BK132+BL132+BM132 -> 139 | BG132: 307 | BH132: 64 | BI132: 490 | BK132: 99 | BL132: 20 | BM132: 20
A133: 44104 | B133: 108.83953 | C133: 108.83947 | D133: 108.83048 | F133: 112.47992 | H133: 104.60742 | J133: 103.9639 | L133: 107.50019 | M133: 107.6367 | O133: 105.09281 | P133: 105.11754 | R133: 610972 | S133: 610972 | U133: -2.0189732 | V133: -0.16911272 | X133: 912370.99 | Y133: 912370.99 | AA133: 0.049594934 | AB133: 0.049594934 | AE133: 506.78792 | AF133: 506.78792 | AI133: 77.450488 | AJ133: 77.453536 | AM133: 0.052329946 | AO133: -0.75116521 | AP133: -0.75116521 | AS133: 0.79831567 | AT133: 0.79834561 | AU133: 0.83443478 | AW133: 136.04156 | AX133: 136.10441 | BA133: 3.1319435 | BB133: 2.6012149 | BC133: 3.1319435 | BF133: =+BK133+BL133+BM133 -> 139 | BG133: 307 | BH133: 64 | BI133: 490 | BK133: 99 | BL133: 20 | BM133: 20
A134: 44196 | B134: 108.88489 | C134: 108.88479 | D134: 108.88648 | F134: 113.00439 | H134: 104.85454 | J134: 103.20192 | L134: 106.99904 | M134: 107.31681 | O134: 102.07296 | P134: 102.03954 | R134: 619330 | S134: 619330 | U134: -1.7193779 | V134: 0.17520396 | X134: 973826.03 | Y134: 973826.03 | AA134: 0.052592199 | AB134: 0.052592199 | AE134: 521.84468 | AF134: 521.84468 | AI134: 77.959994 | AJ134: 77.966817 | AM134: 0.044807315 | AO134: -0.98807905 | AP134: -0.98807905 | AS134: 0.80778747 | AT134: 0.80771956 | AU134: 0.83997056 | AW134: 136.29865 | AX134: 136.36766 | BA134: 3.4145578 | BB134: 2.8359383 | BC134: 3.4145578 | BF134: =+BK134+BL134+BM134 -> 139 | BG134: 307 | BH134: 64 | BI134: 490 | BK134: 99 | BL134: 20 | BM134: 20
A135: 44286 | B135: 109.6222 | C135: 109.62211 | D135: 109.49834 | F135: 113.98626 | H135: 104.7705 | J135: 103.16316 | L135: 107.67965 | M135: 107.47615 | O135: 106.27196 | P135: 106.32704 | R135: 612665 | S135: 612665 | U135: -1.8989207 | V135: 0.53571733 | X135: 952555.24 | Y135: 952555.24 | AA135: 0.049069489 | AB135: 0.049069489 | AE135: 525.88678 | AF135: 525.88678 | AI135: 80.47557 | AJ135: 80.482731 | AM135: 0.044583478 | AO135: -1.1920709 | AP135: -1.1920709 | AS135: 0.80252061 | AT135: 0.80260601 | AU135: 0.82501035 | AW135: 137.71784 | AX135: 137.79296 | BA135: 2.9821807 | BB135: 2.4768305 | BC135: 2.9821807 | BF135: =+BK135+BL135+BM135 -> 158.66667 | BG135: 348.33333 | BH135: 59.666667 | BI135: 433.33333 | BK135: 114 | BL135: 22.666667 | BM135: 22
A136: 44377 | B136: 110.44607 | C136: 110.44597 | D136: 110.61787 | F136: 114.39313 | H136: 105.87678 | J136: 103.53029 | L136: 108.01184 | M136: 107.76596 | O136: 111.43655 | P136: 111.41305 | R136: 655443 | S136: 655443 | U136: 0.039010414 | V136: 1.1160079 | X136: 1006521.1 | Y136: 1006521.1 | AA136: 0.046692031 | AB136: 0.046692031 | AE136: 531.51747 | AF136: 531.51747 | AI136: 81.7804 | AJ136: 81.786428 | AM136: 0.050606925 | AO136: -1.3470819 | AP136: -1.3470819 | AS136: 0.81408904 | AT136: 0.81408904 | AU136: 0.82910866 | AW136: 138.90408 | AX136: 138.99147 | BA136: 2.7653977 | BB136: 2.2967827 | BC136: 2.7653977 | BF136: =+BK136+BL136+BM136 -> 159 | BG136: 347 | BH136: 60 | BI136: 434 | BK136: 114 | BL136: 23 | BM136: 22
A137: 44469 | B137: 111.88904 | C137: 111.88895 | D137: 111.82505 | F137: 115.19242 | H137: 107.72344 | J137: 104.09827 | L137: 108.29735 | M137: 108.4206 | O137: 115.52711 | P137: 115.53219 | R137: 666498 | S137: 666498 | U137: 0.93214669 | V137: 0.23730738 | X137: 1033812.5 | Y137: 1033812.5 | AA137: 0.043738526 | AB137: 0.043738526 | AE137: 535.13556 | AF137: 535.13556 | AI137: 81.766095 | AJ137: 81.769348 | AM137: 0.056322805 | AO137: -1.4409684 | AP137: -1.4409684 | AS137: 0.83581527 | AT137: 0.8357748 | AU137: 0.85017293 | AW137: 140.08344 | AX137: 140.16666 | BA137: 3.4330399 | BB137: 2.8512886 | BC137: 3.4330399 | BF137: =+BK137+BL137+BM137 -> 159 | BG137: 347 | BH137: 60 | BI137: 434 | BK137: 114 | BL137: 23 | BM137: 22
A138: 44561 | B138: 114.22727 | C138: 114.22718 | D138: 114.2337 | F138: 116.70116 | H138: 109.683 | J138: 105.93197 | L138: 110.0924 | M138: 110.41295 | O138: 126.85807 | P138: 126.78731 | R138: 675680 | S138: 675680 | U138: 1.3571838 | V138: 1.2451829 | X138: 1036780 | Y138: 1036780 | AA138: 0.041734239 | AB138: 0.041734239 | AE138: 543.5695 | AF138: 543.5695 | AI138: 81.602417 | AJ138: 81.601332 | AM138: 0.20218077 | AO138: -1.5030493 | AP138: -1.5030493 | AS138: 0.88972454 | AT138: 0.88967799 | AU138: 0.87878505 | AW138: 142.43843 | AX138: 142.51281 | BA138: 4.1496519 | BB138: 3.4464659 | BC138: 4.1496519 | BF138: =+BK138+BL138+BM138 -> 159 | BG138: 347 | BH138: 60 | BI138: 434 | BK138: 114 | BL138: 23 | BM138: 22
A139: 44651 | B139: 116.52348 | C139: 116.52338 | D139: 116.39382 | F139: 118.20318 | H139: 112.14236 | J139: 108.4646 | L139: 112.78318 | M139: 112.62009 | O139: 131.85258 | P139: 131.93635 | R139: 682527 | S139: 682527 | U139: 1.2499228 | V139: 0.95337236 | X139: 1042268.2 | Y139: 1042268.2 | AA139: 0.037902493 | AB139: 0.037902493 | AE139: 553.758 | AF139: 553.758 | AI139: 82.319578 | AJ139: 82.320466 | AM139: 0.67704095 | AO139: -1.1701783 | AP139: -1.1701783 | AS139: 0.9170429 | AT139: 0.91704684 | AU139: 0.89191178 | AW139: 145.5079 | AX139: 145.59556 | BA139: 5.4749404 | BB139: 4.5471755 | BC139: 5.4749404 | BF139: =+BK139+BL139+BM139 -> 165 | BG139: 331.33333 | BH139: 67 | BI139: 436.66667 | BK139: 115.66667 | BL139: 26.333333 | BM139: 23
A140: 44742 | B140: 120.44856 | C140: 120.44845 | D140: 120.6805 | F140: 119.97283 | H140: 113.41431 | J140: 112.1396 | L140: 115.8511 | M140: 115.54942 | O140: 171.20962 | P140: 171.26471 | R140: 686335 | S140: 686335 | U140: 1.1831124 | V140: 1.5832667 | X140: 1046824 | Y140: 1046824 | AA140: 0.037837388 | AB140: 0.037837388 | AE140: 561.59874 | AF140: 561.59874 | AI140: 80.16644 | AJ140: 80.190637 | AM140: 1.2252211 | AO140: -0.6498841 | AP140: -0.6498841 | AS140: 0.9779835 | AT140: 0.97799595 | AU140: 0.93455798 | AW140: 148.88263 | AX140: 149.01661 | BA140: 6.0753476 | BB140: 5.0458397 | BC140: 6.0753476 | BF140: =+BK140+BL140+BM140 -> 166 | BG140: 330 | BH140: 67 | BI140: 437 | BK140: 116 | BL140: 27 | BM140: 23
A141: 44834 | B141: 123.13039 | C141: 123.13029 | D141: 123.00483 | F141: 121.97103 | H141: 114.95401 | J141: 118.03507 | L141: 120.23289 | M141: 120.36449 | O141: 177.94519 | P141: 177.87838 | R141: 687029 | S141: 687029 | U141: 0.85119665 | V141: 1.6762337 | X141: 1046272 | Y141: 1046272 | AA141: 0.037286752 | AB141: 0.037286752 | AE141: 571.14206 | AF141: 571.14206 | AI141: 78.154103 | AJ141: 78.205745 | AM141: 2.19735 | AO141: 0.093339421 | AP141: 0.093339421 | AS141: 1.0191251 | AT141: 1.0191296 | AU141: 0.96856487 | AW141: 151.60699 | AX141: 151.74011 | BA141: 8.3216708 | BB141: 6.9115086 | BC141: 8.3216708 | BF141: =+BK141+BL141+BM141 -> 166 | BG141: 330 | BH141: 67 | BI141: 437 | BK141: 116 | BL141: 27 | BM141: 23
A142: 44926 | B142: 126.54745 | C142: 126.54735 | D142: 126.54049 | F142: 124.23549 | H142: 116.645 | J142: 123.38884 | L142: 124.30799 | M142: 124.66698 | O142: 197.72478 | P142: 197.57542 | R142: 688817 | S142: 688817 | U142: 0.68245656 | V142: 0.52034034 | X142: 1050738.5 | Y142: 1050738.5 | AA142: 0.039158908 | AB142: 0.039158908 | AE142: 583.45782 | AF142: 583.45782 | AI142: 78.079235 | AJ142: 78.079235 | AM142: 3.4175115 | AO142: 1.3695209 | AP142: 1.3695209 | AS142: 1.0076086 | AT142: 1.0075868 | AU142: 0.98644293 | AW142: 154.52379 | AX142: 154.66827 | BA142: 7.2128482 | BB142: 5.9905833 | BC142: 7.2128482 | BF142: =+BK142+BL142+BM142 -> 166 | BG142: 330 | BH142: 67 | BI142: 437 | BK142: 116 | BL142: 27 | BM142: 23
A143: 45016 | B143: 128.41252 | C143: 128.41241 | D143: 128.33162 | F143: 125.92699 | H143: 118.53959 | J143: 127.99275 | L143: 128.75499 | M143: 128.60739 | O143: 192.64227 | P143: 192.65568 | R143: 689206 | S143: 689206 | U143: 0.22929937 | V143: -0.33242865 | X143: 1057548.5 | Y143: 1057548.5 | AA143: 0.039999897 | AB143: 0.039999897 | AE143: 593.67734 | AF143: 593.67734 | AI143: 78.144531 | AJ143: 78.144531 | AM143: 4.0490439 | AO143: 2.4864327 | AP143: 2.4864327 | AS143: 1.0189055 | AT143: 1.018928 | AU143: 1.0096092 | AW143: 156.75329 | AX143: 156.93673 | BA143: 5.4496808 | BB143: 4.5261963 | BC143: 5.4496808 | BF143: =+BK143+BL143+BM143 -> 160.33333 | BG143: 294.66667 | BH143: 80 | BI143: 465 | BK143: 118.33333 | BL143: 21 | BM143: 21
... A152: 45838 | B152: 137.86831 | C152: 137.8682 | D152: 138.04057 | F152: 142.47763 | H152: 122.69643 | J152: 140.77799 | L152: 144.80364 | M152: 144.36323 | O152: 152.26305 | P152: 153.38041 | R152: 704973 | S152: 705403 | U152: -0.53521004 | V152: -1.8925383 | X152: 1092607.1 | Y152: 1092607.1 | AA152: 0.04660112 | AB152: 0.04660112 | AE152: 670.36599 | AF152: 670.36599 | AI152: 85.433745 | AJ152: 85.433745 | AM152: 4.1790199 | AO152: 3.7371024 | AP152: 3.7425486 | AS152: 0.99243724 | AT152: 0.99106811 | AU152: 1.0105901 | AW152: 169.19827 | AX152: 169.42098 | BA152: 4.0110426 | BB152: 3.3313449 | BC152: 4.0110426 | BF152: =+BK152+BL152+BM152 -> 151.1486 | BG152: 286.3633 | BH152: 61.6527 | BI152: 500.8354 | BK152: 112.5699 | BL152: 20.0526 | BM152: 18.5261
A153: 45930 | B153: 139.17186 | C153: 139.17174 | D153: 138.97188 | F153: 143.8349 | H153: 123.18419 | J153: 142.64636 | L153: 146.02696 | M153: 146.17239 | O153: 153.78204 | P153: 152.77858 | R153: 705603 | S153: 706813.81 | U153: 0 | V153: -1.6978608 | X153: 1086239.7 | Y153: 1088109.9 | AA153: 0.049722756 | AB153: 0.048668948 | AE153: 674.94341 | AF153: 675.06649 | AI153: 84.985242 | AJ153: 84.985242 | AM153: 3.9805726 | AO153: 3.6249602 | AP153: 3.623433 | AS153: 0.98677893 | AT153: 0.98826679 | AU153: 1.0092331 | AW153: 170.50554 | AX153: 170.10291 | BA153: 3.9691108 | BB153: 3.2965187 | BD153: 3.9691108 | BF153: =+BK153+BL153+BM153 -> 151.1486 | BG153: 286.3633 | BH153: 61.6527 | BI153: 500.8354 | BK153: 112.5699 | BL153: 20.0526 | BM153: 18.5261
A154: 46022 | B154: 139.81472 | C154: 139.8146 | D154: 139.85387 | F154: 144.82576 | H154: 123.45191 | J154: 143.54214 | L154: 146.88064 | M154: 147.33385 | O154: 153.89556 | P154: 154.08739 | R154: 707014.21 | S154: 708934.25 | U154: 0 | V154: -1.8289475 | X154: 1088788.1 | Y154: 1089925.4 | AA154: 0.051286994 | AB154: 0.049697693 | AE154: 680.46757 | AF154: 680.79359 | AI154: 84.151327 | AJ154: 84.479013 | AM154: 3.8245596 | AO154: 3.5370043 | AP154: 3.5100422 | AS154: 0.98557497 | AT154: 0.98263827 | AU154: 1.0346049 | AW154: 170.77849 | AX154: 170.38248 | BA154: 3.8470567 | BB154: 3.1951475 | BD154: 3.9221779 | BF154: =+BK154+BL154+BM154 -> 151.1486 | BG154: 286.3633 | BH154: 61.6527 | BI154: 500.8354 | BK154: 112.5699 | BL154: 20.0526 | BM154: 18.5261
A155: 46112 | D155: 140.96006 | L155: 148.75767 | P155: 152.38088 | R155: 709135.25 | S155: 711292.91 | U155: 0 | V155: -1.7040186 | X155: 1088755.5 | Y155: 1088841.3 | AA155: 0.051844225 | AB155: 0.0504 | AF155: 686.71173 | AJ155: 84.252156 | AO155: 3.351918 | AP155: 3.4154219 | AS155: 0.98115825 | AT155: 0.97725801 | AW155: 171.06117 | AX155: 170.76718 | BD155: 3.4732572 | BF155: =+BK155+BL155+BM155 -> 146.37555 | BG155: 277.06973 | BH155: 58.33398 | BI155: 518.22073 | BK155: 109.43672 | BL155: 20.778982 | BM155: 16.159856
A156: 46203 | D156: 142.0057 | L156: 149.8334 | P156: 148.04947 | S156: 713598.35 | U156: 0 | V156: -1.7237463 | Y156: 1089619.5 | AB156: 0.050541252 | AF156: 692.12433 | AJ156: 84.117539 | AO156: 3.2631233 | AP156: 3.3219454 | AT156: 0.9749504 | AW156: 171.36907 | AX156: 171.28774 | BD156: 3.2071262 | BF156: =+BK156+BL156+BM156 -> 146.73083 | BG156: 276.4363 | BH156: 58.33497 | BI156: 518.4979 | BK156: 109.57587 | BL156: 20.932272 | BM156: 16.222684
A157: 46295 | D157: 142.70719 | L157: 149.92516 | P157: 149.5711 | S157: 716034.92 | U157: 0 | V157: -1.6558511 | Y157: 1090427.8 | AB157: 0.050498257 | AF157: 697.3824 | AJ157: 83.98531 | AO157: 3.1790597 | AP157: 3.3064318 | AT157: 0.97388427 | AW157: 172.11924 | AX157: 172.08141 | BD157: 2.9284517 | BF157: =+BK157+BL157+BM157 -> 146.73083 | BG157: 276.4363 | BH157: 58.33497 | BI157: 518.4979 | BK157: 109.57587 | BL157: 20.932272 | BM157: 16.222684
A158: 46387 | D158: 143.35098 | L158: 151.64689 | P158: 149.37929 | S158: 718746.04 | U158: 0 | V158: -1.6089581 | Y158: 1092228.2 | AB158: 0.050389561 | AF158: 702.54561 | AJ158: 83.853892 | AO158: 3.173025 | AP158: 3.3371672 | AT158: 0.97306004 | AW158: 172.6729 | AX158: 172.82847 | BD158: 2.7607717 | BF158: =+BK158+BL158+BM158 -> 146.73083 | BG158: 276.4363 | BH158: 58.33497 | BI158: 518.4979 | BK158: 109.57587 | BL158: 20.932272 | BM158: 16.222684
A159: 46477 | D159: 144.03329 | P159: 148.75311 | S159: 721631.31 | U159: 0 | V159: -1.5371047 | Y159: 1094167.4 | AB159: 0.05021789 | AF159: 707.66289 | AJ159: 83.722428 | AO159: 3.2222425 | AP159: 3.376846 | AT159: 0.97240044 | AW159: 173.53255 | AX159: 173.77927 | BD159: 2.6830774 | BF159: =+BK159+BL159+BM159 -> 146.37555 | BG159: 277.06973 | BH159: 58.33398 | BI159: 518.22073 | BK159: 109.43672 | BL159: 20.778982 | BM159: 16.159856
A160: 46568 | D160: 144.76619 | P160: 149.36955 | S160: 724747.91 | U160: 0 | V160: -1.4586119 | Y160: 1096113.2 | AB160: 0.05003043 | AF160: 712.79819 | AJ160: 83.591451 | AO160: 3.2868764 | AP160: 3.4138167 | AT160: 0.97421349 | AW160: 174.41938 | AX160: 174.72296 | BD160: 2.6433548 | BF160: =+BK160+BL160+BM160 -> 146.73083 | BG160: 276.4363 | BH160: 58.33497 | BI160: 518.4979 | BK160: 109.57587 | BL160: 20.932272 | BM160: 16.222684
A161: 46660 | D161: 145.50721 | P161: 149.91701 | S161: 727950.51 | U161: 0 | V161: -1.3726282 | Y161: 1097963.2 | AB161: 0.04974273 | AF161: 717.99084 | AJ161: 83.462187 | AO161: 3.3509593 | AP161: 3.4440408 | AT161: 0.97436963 | AW161: 175.28856 | AX161: 175.63827 | BD161: 2.6218393 | BF161: =+BK161+BL161+BM161 -> 146.73083 | BG161: 276.4363 | BH161: 58.33497 | BI161: 518.4979 | BK161: 109.57587 | BL161: 20.932272 | BM161: 16.222684
A162: 46752 | D162: 146.26524 | P162: 136.40861 | S162: 731300.17 | U162: 0 | V162: -1.3276231 | Y162: 1100126.6 | AB162: 0.049361609 | AF162: 723.26555 | AJ162: 83.335501 | AO162: 3.4078549 | AP162: 3.469114 | AT162: 0.97332131 | AW162: 175.91264 | AX162: 176.37234 | BD162: 2.609262 | BF162: =+BK162+BL162+BM162 -> 146.73083 | BG162: 276.4363 | BH162: 58.33497 | BI162: 518.4979 | BK162: 109.57587 | BL162: 20.932272 | BM162: 16.222684
A163: 46843 | D163: 147.00874 | P163: 134.59702 | S163: 734695.69 | U163: 0 | V163: -1.3352153 | Y163: 1103179.9 | AB163: 0.048942373 | AF163: 728.68905 | AJ163: 83.211438 | AO163: 3.4553117 | AP163: 3.4901568 | AT163: 0.97211634 | AW163: 176.71486 | AX163: 177.09077 | BD163: 2.6222316 | BF163: =+BK163+BL163+BM163 -> 146.37555 | BG163: 277.06973 | BH163: 58.33398 | BI163: 518.22073 | BK163: 109.43672 | BL163: 20.778982 | BM163: 16.159856
A164: 46934 | D164: 147.78016 | P164: 133.93665 | S164: 738059.62 | U164: 0 | V164: -1.2781854 | Y164: 1105659.2 | AB164: 0.048451841 | AF164: 734.32554 | AJ164: 83.089805 | AO164: 3.5024574 | AP164: 3.5168931 | AT164: 0.97121443 | AW164: 177.44761 | AX164: 177.87615 | BD164: 2.6420013 | BF164: =+BK164+BL164+BM164 -> 146.73083 | BG164: 276.4363 | BH164: 58.33497 | BI164: 518.4979 | BK164: 109.57587 | BL164: 20.932272 | BM164: 16.222684
A165: 47026 | D165: 148.54929 | P165: 134.87225 | S165: 741431.62 | U165: 0 | V165: -1.2382119 | Y165: 1108222.5 | AB165: 0.047972324 | AF165: 740.21052 | AJ165: 82.970359 | AO165: 3.5474807 | AP165: 3.5462896 | AT165: 0.97018549 | AW165: 178.22447 | AX165: 178.61291 | BD165: 2.6284768 | BF165: =+BK165+BL165+BM165 -> 146.73083 | BG165: 276.4363 | BH165: 58.33497 | BI165: 518.4979 | BK165: 109.57587 | BL165: 20.932272 | BM165: 16.222684
A166: 47118 | D166: 149.33243 | P166: 135.45874 | S166: 744811.57 | V166: -1.1823681 | Y166: 1110769.1 | AB166: 0.047406381 | AF166: 746.35252 | AJ166: 82.852815 | AO166: 3.5903215 | AP166: 3.5778306 | AT166: 0.96942556 | AW166: 178.72895 | AX166: 179.20772 | BD166: 2.6276947 | BF166: =+BK166+BL166+BM166 -> 146.73083 | BG166: 276.4363 | BH166: 58.33497 | BI166: 518.4979 | BK166: 109.57587 | BL166: 20.932272 | BM166: 16.222684

Sheet Estimation_data
A1: REALISED DATA: 1990Q2-2025Q4
A2: DATA SOURCE: STIF-ONS | I2: DATA SOURCE: FAME
A3: 1990m2 | B3: Current Round: | I3: 1990Q2 | J3: Current Round: | L3: pub_
A4: 2025m12 | B4: Frequency | D4: .m | I4: 2025Q4 | J4: Run: | L4: .q
B5: Calc: | J5: Calc:
B7: Endogenous | I7: Exogenous
A8: variables | B8: cpi | C8: services | D8: core goods | E8: food including alcohol and tobacco | F8: food | G8: alcohol | H8: tobacco | I8: energy | J8: import price | K8: exchange rate | L8: inflation expectation
A9: FAME name | B9: stifidx | C9: stif_srv | D9: stif_gds_xeatfnab | F9: stif_fnab | G9: booze | H9: fags | I9: stif_pu | J9: pmdef | K9: eer
A10: FAME adjust | B10: ="conv2qa(X12("&$D$5&B9&$D$4&",MULT," & TEXT($A$3,"yyyy""m""m") & "," & TEXT($A$4,"yyyy""m""m") & "))" -> conv2qa(X12(stifidx.m,MULT,1990m2,2025m12)) | C10: ="conv2qa(X12("&$D$5&C9&$D$4&",MULT," & TEXT($A$3,"yyyy""m""m") & "," & TEXT($A$4,"yyyy""m""m") & "))" -> conv2qa(X12(stif_srv.m,MULT,1990m2,2025m12)) | D10: ="conv2qa(X12("&$D$5&D9&$D$4&",MULT," & TEXT($A$3,"yyyy""m""m") & "," & TEXT($A$4,"yyyy""m""m") & "))" -> conv2qa(X12(stif_gds_xeatfnab.m,MULT,1990m2,2025m12)) | E10: ="conv2qa(X12(cpi_aggregation(stif_fnab.m, booze.m, fags.m,#,#,#,#,#,#,#,#,#,#,#,#,#,#,#,#,#),MULT," & TEXT($A$3,"yyyy""m""m") & "," & TEXT($A$4,"yyyy""m""m") & "))" -> conv2qa(X12(cpi_aggregation(stif_fnab.m, booze.m, fags.m,#,#,#,#,#,#,#,#,#,#,#,#,#,#,#,#,#),MULT,1990m2,2025m12)) | F10: ="conv2qa(X12("&$D$5&F9&$D$4&",MULT," & TEXT($A$3,"yyyy""m""m") & "," & TEXT($A$4,"yyyy""m""m") & "))" -> conv2qa(X12(stif_fnab.m,MULT,1990m2,2025m12)) | G10: ="conv2qa(X12("&$D$5&G9&$D$4&",MULT," & TEXT($A$3,"yyyy""m""m") & "," & TEXT($A$4,"yyyy""m""m") & "))" -> conv2qa(X12(booze.m,MULT,1990m2,2025m12)) | H10: ="conv2qa(X12("&$D$5&H9&$D$4&",MULT," & TEXT($A$3,"yyyy""m""m") & "," & TEXT($A$4,"yyyy""m""m") & "))" -> conv2qa(X12(fags.m,MULT,1990m2,2025m12)) | I10: ="conv2qa(X12("&$D$5&I9&$D$4&",MULT," & TEXT($A$3,"yyyy""m""m") & "," & TEXT($A$4,"yyyy""m""m") & "))" -> conv2qa(X12(stif_pu.m,MULT,1990m2,2025m12)) | J10: pmdef | K10: eer | L10: BPROJA(conv2qa(cgrp.m),PUB12MEDIAN.Q,"E")
A11: date | B11: cpi | C11: services | D11: core_gds | E11: food_at | F11: food | G11: alcohol | H11: tobacco | I11: energy_f | J11: pmdef_f | K11: eer_f | L11: infl_exp
A12: 33054 | B12: =[3]!FAMEData(B10, $I$3, $I$4, 0,"Quarterly", "Down", "No Heading", "Normal") -> 55.216192 | C12: =[3]!FAMEData(C10, $I$3, $I$4, 0,"Quarterly", "Down", "No Heading", "Normal") -> 37.291624 | D12: =[3]!FAMEData(D10, $I$3, $I$4, 0,"Quarterly", "Down", "No Heading", "Normal") -> 109.4919 | E12: =[3]!FAMEData(E10, $I$3, $I$4, 0,"Quarterly", "Down", "No Heading", "Normal") -> 46.254605 | F12: =[3]!FAMEData(F10, $I$3, $I$4, 0,"Quarterly", "Down", "No Heading", "Normal") -> 55.346352 | G12: =[3]!FAMEData(G10, $I$3, $I$4, 0,"Quarterly", "Down", "No Heading", "Normal") -> 61.765236 | H12: =[3]!FAMEData(H10, $I$3, $I$4, 0,"Quarterly", "Down", "No Heading", "Normal") -> 17.935207 | I12: =[3]!FAMEData(I10, $I$3, $I$4, 0,"Quarterly", "Down", "No Heading", "Normal") -> 33.809155 | J12: =[3]!FAMEData($L$5&$L$3&J9&$L$4, $I$3, $I$4, 0,"Quarterly", "Down", "No Heading", "Normal") -> 0.57773628 | K12: =[3]!FAMEData($L$5&$L$3&K9&$L$4, $I$3, $I$4, 0,"Quarterly", "Down", "No Heading", "Normal") -> 93.068646 | L12: =[3]!FAMEData(L10, $I$3, $I$4, 0,"Quarterly", "Down", "No Heading", "Normal") -> 8.6373834
A13: 33146 | B13: 56.369272 | C13: 38.226404 | D13: 110.77076 | E13: 47.031491 | F13: 56.069625 | G13: 63.670729 | H13: 18.481683 | I13: 35.502014 | J13: 0.55930606 | K13: 99.445968 | L13: 9.1039566
A14: 33238 | B14: 57.494732 | C14: 39.201503 | D14: 112.05037 | E14: 47.936474 | F14: 57.003542 | G14: 64.67603 | H14: 19.002572 | I14: 36.723481 | J14: 0.56615029 | K14: 99.670858 | L14: 7.4794737
A15: 33328 | B15: 58.131185 | C15: 40.047704 | D15: 112.98292 | E15: 48.483131 | F15: 57.575944 | G15: 65.859602 | H15: 19.262094 | I15: 36.121607 | J15: 0.56293382 | K15: 99.118131 | L15: 7.1724561
A16: 33419 | B16: 59.827705 | C16: 41.709306 | D16: 115.1372 | E16: 49.975838 | F16: 58.344421 | G16: 69.935106 | H16: 20.910685 | I16: 37.362098 | J16: 0.57235316 | K16: 96.421142 | L16: 5.5856456
A17: 33511 | B17: 60.749441 | C17: 42.478114 | D17: 116.63678 | E17: 50.515686 | F17: 58.886712 | G17: 70.633968 | H17: 21.411108 | I17: 38.223615 | J17: 0.58356049 | K17: 95.722653 | L17: 4.6085185
A18: 33603 | B18: 61.5371 | C18: 43.254296 | D18: 117.83569 | E18: 51.223588 | F18: 59.515813 | G18: 71.32687 | H18: 21.99049 | I18: 38.311037 | J18: 0.57552587 | K18: 96.172297 | L18: 4.4125673
A19: 33694 | B19: 62.131083 | C19: 43.882111 | D19: 118.7579 | E19: 51.670967 | F19: 59.959978 | G19: 71.937055 | H19: 22.326943 | I19: 38.258535 | J19: 0.56924052 | K19: 95.797952 | L19: 4.3453333
A20: 33785 | B20: 62.416759 | C20: 44.452914 | D20: 118.72539 | E20: 51.90606 | F20: 59.723829 | G20: 72.601834 | H20: 23.022676 | I20: 38.383855 | J20: 0.56506054 | K20: 97.573482 | L20: 4.0467864
A21: 33877 | B21: 62.691059 | C21: 44.967908 | D21: 118.80745 | E21: 52.023965 | F21: 59.567454 | G21: 73.541071 | H21: 23.465848 | I21: 38.275282 | J21: 0.56539814 | K21: 96.710815 | L21: 3.8414337
A22: 33969 | B22: 63.195466 | C22: 45.533479 | D22: 118.62097 | E22: 52.659248 | F22: 60.084592 | G22: 74.542288 | H22: 23.987473 | I22: 38.984401 | J22: 0.59920423 | K22: 84.845339 | L22: 3.5328715
A23: 34059 | B23: 63.53193 | C23: 46.101573 | D23: 118.15539 | E23: 53.005409 | F23: 60.484175 | G23: 74.780188 | H23: 24.233991 | I23: 39.383108 | J23: 0.62407768 | K23: 83.282759 | L23: 3.0711828
A24: 34150 | B24: 63.996848 | C24: 46.686643 | D24: 118.57891 | E24: 53.428432 | F24: 60.784937 | G24: 75.00129 | H24: 24.732092 | I24: 39.523785 | J24: 0.62651505 | K24: 85.35204 | L24: 2.9543939
... A154: 46022 | B154: 139.81472 | C154: 144.82576 | D154: 123.45191 | E154: 147.33385 | F154: 143.54214 | G154: 124.46047 | H154: 193.97045 | I154: 153.89556 | J154: 1.0048139 | K154: 84.160324 | L154: 3.8470567

Sheet M26_STIF_BMK
A1: Source: STIF -CECD | E1: Source: EASE-FAME
A2: REALISED DATA + CECD CONSTRAINS | E2: MPR FORECAST
A3: 1996m1 | B3: Current Round: | D3: M26_ | E3: 1996Q1 | F3: Current Round: | H3: M26_
A4: 2026m12 | B4: Run: | D4: _bmk.m | E4: 2029Q2 | F4: Run: | H4: _bmk2.q
A5: 1996Q1 | B5: Calc: | F5: Calc:
A6: 2026Q4
B7: Endogenous | G7: stif_fnab.m | I7: Exogenous | P7: Weights
B8: CPI | C8: Services | D8: Core goods | E8: Food including alcohol and tobacco | F8: Food | G8: Alcohol | H8: Tobacco | I8: Energy | J8: cpi_MPR | K8: import price | L8: exchange rate | M8: inflation expectation | N8: Energy contrib to CPI (yoy) | O8: Energy contrib to CPI (qoq) | P8: Core goods | Q8: Energy | R8: Services | S8: Food | T8: Alcohol | U8: Tobacco | V8: Food&at
A9: FAME name | B9: stifidx | C9: stif_srv | D9: stif_gds_xeatfnab | F9: stif_fnab | G9: booze.m | H9: fags.m | I9: stif_pu | J9: cpisa | K9: pmdef | L9: eer | N9: encont | O9: encontqoq
A10: FAME data_adj | B10: ="conv2qa(X12("&$D$5&$D$3&B9&$D$4&",MULT," & TEXT($A$3,"yyyy""m""m") & "," & TEXT($A$4,"yyyy""m""m") & "))" -> conv2qa(X12(M26_stifidx_bmk.m,MULT,1996m1,2026m12)) | C10: ="conv2qa(X12("&$D$5&$D$3&C9&$D$4&",MULT," & TEXT($A$3,"yyyy""m""m") & "," & TEXT($A$4,"yyyy""m""m") & "))" -> conv2qa(X12(M26_stif_srv_bmk.m,MULT,1996m1,2026m12)) | D10: ="conv2qa(X12("&$D$5&$D$3&D9&$D$4&",MULT," & TEXT($A$3,"yyyy""m""m") & "," & TEXT($A$4,"yyyy""m""m") & "))" -> conv2qa(X12(M26_stif_gds_xeatfnab_bmk.m,MULT,1996m1,2026m12)) | E10: ="conv2qa(X12(cpi_aggregation("&G7&", "&G9&","&H9&",#,#,#,#,#,#,#,#,#,#,#,#,#,#,#,#,#),MULT," & TEXT($A$3,"yyyy""m""m") & "," & TEXT($A$4,"yyyy""m""m") & "))" -> conv2qa(X12(cpi_aggregation(stif_fnab.m, booze.m,fags.m,#,#,#,#,#,#,#,#,#,#,#,#,#,#,#,#,#),MULT,1996m1,2026m12)) | F10: ="conv2qa(X12("&$D$5&$D$3&F9&$D$4&",MULT," & TEXT($A$3,"yyyy""m""m") & "," & TEXT($A$4,"yyyy""m""m") & "))" -> conv2qa(X12(M26_stif_fnab_bmk.m,MULT,1996m1,2026m12)) | G10: ="conv2qa(X12("&G9&",MULT," & TEXT($A$3,"yyyy""m""m") & "," & TEXT($A$4,"yyyy""m""m") & "))" -> conv2qa(X12(booze.m,MULT,1996m1,2026m12)) | H10: ="conv2qa(X12("&H9&",MULT," & TEXT($A$3,"yyyy""m""m") & "," & TEXT($A$4,"yyyy""m""m") & "))" -> conv2qa(X12(fags.m,MULT,1996m1,2026m12)) | I10: ="conv2qa(X12("&$D$5&$D$3&I9&$D$4&",MULT," & TEXT($A$3,"yyyy""m""m") & "," & TEXT($A$4,"yyyy""m""m") & "))" -> conv2qa(X12(M26_stif_pu_bmk.m,MULT,1996m1,2026m12)) | P10: CONV2QA(STIF_GDS_XEATFNAB_wgt.m) | Q10: CONV2QA(stif_pu_wgt.m) | R10: CONV2QA(stif_srv_wgt.m) | S10: CONV2QA(stif_fnab_wgt.m) | T10: CONV2QA(booze_wgt.m) | U10: CONV2QA(fags_wgt.m)
A11: date | B11: cpi | C11: services | D11: core_gds | E11: food_at | F11: food | G11: alcohol | H11: tobacco | I11: energy_f | J11: cpi_f | K11: pmdef_f | L11: eer_f | M11: infl_exp | N11: encont_f | O11: encontqoq_f | P11: cg_wgt | Q11: e_wgt | R11: s_wgt | S11: food_wgt | T11: a_wgt | U11: t_wgt | V11: f_wgt
A12: 35155 | B12: =[3]!FAMEData(B10, $A$5, $A$6, 0,"Quarterly", "Down", "No Heading", "Normal") -> 68.33625 | C12: =[3]!FAMEData(C10, $A$5, $A$6, 0,"Quarterly", "Down", "No Heading", "Normal") -> 50.96798 | D12: =[3]!FAMEData(D10, $A$5, $A$6, 0,"Quarterly", "Down", "No Heading", "Normal") -> 120.21246 | E12: =[3]!FAMEData(E10, $A$5, $A$6, 0,"Quarterly", "Down", "No Heading", "Normal") -> 58.553707 | F12: =[3]!FAMEData(F10, $A$5, $A$6, 0,"Quarterly", "Down", "No Heading", "Normal") -> 65.579758 | G12: =[3]!FAMEData(G10, $A$5, $A$6, 0,"Quarterly", "Down", "No Heading", "Normal") -> 77.833863 | H12: =[3]!FAMEData(H10, $A$5, $A$6, 0,"Quarterly", "Down", "No Heading", "Normal") -> 30.054561 | I12: =[3]!FAMEData(I10, $E$3, $E$4, 0,"Quarterly", "Down", "No Heading", "Normal") -> 43.611059 | J12: =[3]!FAMEData($H$5&$H$3&J9&$H$4, $E$3, $E$4, 0,"Quarterly", "Down", "No Heading", "Normal") -> 68.274786 | K12: =[3]!FAMEData($H$5&$H$3&K9&$H$4, $E$3, $E$4, 0,"Quarterly", "Down", "No Heading", "Normal") -> 0.69676277 | L12: =[3]!FAMEData($H$5&$H$3&L9&$H$4, $E$3, $E$4, 0,"Quarterly", "Down", "No Heading", "Normal") -> 80.896182 | M12: ='[4]VAR expectations'!C36 -> 2.8151174 | N12: =[3]!FAMEData($H$5&$H$3&N9&$H$4, $E$3, $E$4, 0,"Quarterly", "Down", "No Heading", "Normal") -> 0.3 | O12: =[3]!FAMEData($H$5&$H$3&O9&$H$4, $E$3, $E$4, 0,"Quarterly", "Down", "No Heading", "Normal") -> 0.20789578 | P12: =[3]!FAMEData(P10, $E$3, $E$4, 0,"Quarterly", "Down", "No Heading", "Normal") -> 330 | Q12: =[3]!FAMEData(Q10, $E$3, $E$4, 0,"Quarterly", "Down", "No Heading", "Normal") -> 85 | R12: =[3]!FAMEData(R10, $E$3, $E$4, 0,"Quarterly", "Down", "No Heading", "Normal") -> 359 | S12: =[3]!FAMEData(S10, $E$3, $E$4, 0,"Quarterly", "Down", "No Heading", "Normal") -> 156 | T12: =[3]!FAMEData(T10, $E$3, $E$4, 0,"Quarterly", "Down", "No Heading", "Normal") -> 35 | U12: =[3]!FAMEData(U10, $E$3, $E$4, 0,"Quarterly", "Down", "No Heading", "Normal") -> 35 | V12: =+S12+T12+U12 -> 226
A13: 35246 | B13: 68.723481 | C13: 51.436217 | D13: 120.55768 | E13: 59.150835 | F13: 66.150623 | G13: 78.703574 | H13: 30.476126 | I13: 43.120581 | J13: 68.646172 | K13: 0.6971702 | L13: 81.882197 | M13: ='[4]VAR expectations'!C37 -> 2.6154885 | N13: 0.3 | O13: -0.16120156 | P13: 330 | Q13: 85 | R13: 359 | S13: 156 | T13: 35 | U13: 35 | V13: =+S13+T13+U13 -> 226
A14: 35338 | B14: 68.949457 | C14: 51.916931 | D14: 120.616 | E14: 59.122312 | F14: 65.892032 | G14: 78.989248 | H14: 30.929831 | I14: 43.346267 | J14: 68.991322 | K14: 0.68186345 | L14: 82.869486 | M14: ='[4]VAR expectations'!C38 -> 2.6428562 | N14: 0.3 | O14: 0.32912444 | P14: 330 | Q14: 85 | R14: 359 | S14: 156 | T14: 35 | U14: 35 | V14: =+S14+T14+U14 -> 226
A15: 35430 | B15: 69.259947 | C15: 52.311071 | D15: 120.63002 | E15: 58.834792 | F15: 65.084106 | G15: 79.125643 | H15: 31.483583 | I15: 44.726775 | J15: 69.3819 | K15: 0.67273735 | L15: 88.333556 | M15: ='[4]VAR expectations'!C39 -> 2.8292929 | N15: 0.3 | O15: -0.0022510151 | P15: 330 | Q15: 85 | R15: 359 | S15: 156 | T15: 35 | U15: 35 | V15: =+S15+T15+U15 -> 226
A16: 35520 | B16: 69.656172 | C16: 52.833527 | D16: 120.51832 | E16: 59.07625 | F16: 65.240899 | G16: 78.957703 | H16: 32.032941 | I16: 45.328296 | J16: 69.587124 | K16: 0.64938685 | L16: 92.82032 | M16: ='[4]VAR expectations'!C40 -> 2.7828097 | N16: 0.32542979 | O16: -0.26229056 | P16: 330 | Q16: 87 | R16: 360 | S16: 152 | T16: 35 | U16: 36 | V16: =+S16+T16+U16 -> 223
A17: 35611 | B17: 69.818827 | C17: 53.331405 | D17: 120.31019 | E17: 59.375031 | F17: 65.4085 | G17: 79.267965 | H17: 32.549627 | I17: 44.445946 | J17: 69.779563 | K17: 0.63898761 | L17: 95.131486 | M17: ='[4]VAR expectations'!C41 -> 2.9050115 | N17: 0.2561351 | O17: -0.18076935 | P17: 330 | Q17: 87 | R17: 360 | S17: 152 | T17: 35 | U17: 36 | V17: =+S17+T17+U17 -> 223
A18: 35703 | B18: 70.28178 | C18: 53.83161 | D18: 120.33885 | E18: 59.894854 | F18: 65.912842 | G18: 79.394794 | H18: 33.304621 | I18: 45.375546 | J18: 70.337385 | K18: 0.63319366 | L18: 97.471461 | M18: ='[4]VAR expectations'!C42 -> 3.1797827 | N18: 0.394009 | O18: 0.13507271 | P18: 330 | Q18: 87 | R18: 360 | S18: 152 | T18: 35 | U18: 36 | V18: =+S18+T18+U18 -> 223
A19: 35795 | B19: 70.534191 | C19: 54.35576 | D19: 120.13748 | E19: 60.113281 | F19: 65.85577 | G19: 79.329519 | H19: 34.107616 | I19: 45.165944 | J19: 70.608568 | K19: 0.63129 | L19: 98.626171 | M19: ='[4]VAR expectations'!C43 -> 3.4444391 | N19: 0.082296485 | O19: -0.18038836 | P19: 330 | Q19: 87 | R19: 360 | S19: 152 | T19: 35 | U19: 36 | V19: =+S19+T19+U19 -> 223
A20: 35885 | B20: 70.760832 | C20: 54.867318 | D20: 119.84603 | E20: 60.324796 | F20: 65.556439 | G20: 80.314829 | H20: 35.043738 | I20: 45.066788 | J20: 70.69193 | K20: 0.62538236 | L20: 100.61063 | M20: ='[4]VAR expectations'!C44 -> 3.237114 | N20: -0.057532854 | O20: -0.40106994 | P20: 344 | Q20: 86 | R20: 358 | S20: 144 | T20: 32 | U20: 36 | V20: =+S20+T20+U20 -> 212
A21: 35976 | B21: 71.100692 | C21: 55.376841 | D21: 119.47176 | E21: 60.759838 | F21: 65.968166 | G21: 80.697418 | H21: 35.534825 | I21: 45.512401 | J21: 71.092691 | K21: 0.6157406 | L21: 100.51243 | M21: ='[4]VAR expectations'!C45 -> 3.3504017 | N21: 0.21318487 | O21: -0.12195983 | P21: 344 | Q21: 86 | R21: 358 | S21: 144 | T21: 32 | U21: 36 | V21: =+S21+T21+U21 -> 212
A22: 36068 | B22: 71.255609 | C22: 55.834494 | D22: 118.95367 | E22: 61.326565 | F22: 66.599884 | G22: 81.111237 | H22: 36.009378 | I22: 45.240118 | J22: 71.320298 | K22: 0.61194661 | L22: 100.14717 | M22: ='[4]VAR expectations'!C46 -> 3.4355093 | N22: -0.020958848 | O22: 0.1481489 | P22: 344 | Q22: 86 | R22: 358 | S22: 144 | T22: 32 | U22: 36 | V22: =+S22+T22+U22 -> 212
A23: 36160 | B23: 71.539884 | C23: 56.342645 | D23: 118.50979 | E23: 61.798219 | F23: 66.931586 | G23: 81.345598 | H23: 36.768434 | I23: 45.182611 | J23: 71.57672 | K23: 0.61580078 | L23: 97.166321 | M23: ='[4]VAR expectations'!C47 -> 3.0318467 | N23: -0.0038943112 | O23: -0.44461325 | P23: 344 | Q23: 86 | R23: 358 | S23: 144 | T23: 32 | U23: 36 | V23: =+S23+T23+U23 -> 212
A24: 36250 | B24: 71.869448 | C24: 56.820337 | D24: 117.91126 | E24: 62.464148 | F24: 67.238659 | G24: 81.576404 | H24: 38.383741 | I24: 45.605839 | J24: 71.807724 | K24: 0.61208262 | L24: 97.283789 | M24: ='[4]VAR expectations'!C48 -> 2.9135125 | N24: 0.095197608 | O24: 0.52782221 | P24: 341 | Q24: 83 | R24: 372 | S24: 141 | T24: 30 | U24: 33 | V24: =+S24+T24+U24 -> 204
... A135: 46387 | B135: 145.4181 | C135: 150.75556 | D135: 125.70906 | E135: 155.70182 | F135: 149.93815 | G135: 124.92841 | H135: 220.13614 | I135: 171.45421 | J135: 145.38728 | K135: 1.0289038 | L135: 83.700766 | M135: ='[4]VAR expectations'!C159 -> 3.9613434 | N135: 0.65364 | O135: -0.15 | P135: 276.5116 | Q135: 58.3509 | R135: 518.3666 | S135: 109.6059 | T135: 20.9379 | U135: 16.2271 | V135: =+S135+T135+U135 -> 146.7709
A136: 46477 | J136: 146.06378 | K136: 1.0240089 | L136: 83.566283 | M136: ='[4]VAR expectations'!C160 -> 3.2779595 | N136: 0.50201 | O136: -0.06 | P136: 277.11993 | Q136: 58.3446 | R136: 518.1332 | S136: 109.45673 | T136: 20.782733 | U136: 16.1628 | V136: =+S136+T136+U136 -> 146.40227
A137: 46568 | J137: 146.67196 | K137: 1.02073 | L137: 83.43245 | M137: ='[4]VAR expectations'!C161 -> 2.8709031 | N137: -0.13643 | O137: -0.09 | P137: 276.5116 | Q137: 58.3509 | R137: 518.3666 | S137: 109.6059 | T137: 20.9379 | U137: 16.2271 | V137: =+S137+T137+U137 -> 146.7709
A138: 46660 | J138: 147.27507 | K138: 1.0182916 | L138: 83.298178 | M138: ='[4]VAR expectations'!C162 -> 2.6322219 | N138: -0.42908 | O138: -0.1 | P138: 276.5116 | Q138: 58.3509 | R138: 518.3666 | S138: 109.6059 | T138: 20.9379 | U138: 16.2271 | V138: =+S138+T138+U138 -> 146.7709
A139: 46752 | J139: 147.8791 | K139: 1.0161953 | L139: 83.164741 | M139: ='[4]VAR expectations'!C163 -> 2.4911848 | N139: -0.34881 | O139: -0.08 | P139: 276.5116 | Q139: 58.3509 | R139: 518.3666 | S139: 109.6059 | T139: 20.9379 | U139: 16.2271 | V139: =+S139+T139+U139 -> 146.7709
A140: 46843 | J140: 148.39535 | K140: 1.0145198 | L140: 83.034222 | M140: ='[4]VAR expectations'!C164 -> 2.4241616 | N140: -0.35678 | O140: -0.09 | P140: 277.11993 | Q140: 58.3446 | R140: 518.1332 | S140: 109.45673 | T140: 20.782733 | U140: 16.1628 | V140: =+S140+T140+U140 -> 146.40227
A141: 46934 | J141: 149.15985 | K141: 1.0129137 | L141: 82.907767 | M141: ='[4]VAR expectations'!C165 -> 2.4392216 | N141: -0.30877 | O141: -0.04 | P141: 276.5116 | Q141: 58.3509 | R141: 518.3666 | S141: 109.6059 | T141: 20.9379 | U141: 16.2271 | V141: =+S141+T141+U141 -> 146.7709
A142: 47026 | J142: 149.75305 | K142: 1.0114707 | L142: 82.785328 | M142: ='[4]VAR expectations'!C166 -> 2.4429234 | N142: -0.23567 | O142: -0.02 | P142: 276.5116 | Q142: 58.3509 | R142: 518.3666 | S142: 109.6059 | T142: 20.9379 | U142: 16.2271 | V142: =+S142+T142+U142 -> 146.7709
A143: 47118 | J143: 150.35552 | K143: 1.0101584 | L143: 82.666622 | M143: ='[4]VAR expectations'!C167 -> 2.484646 | N143: -0.16808 | O143: -0.01 | P143: 276.5116 | Q143: 58.3509 | R143: 518.3666 | S143: 109.6059 | T143: 20.9379 | U143: 16.2271 | V143: =+S143+T143+U143 -> 146.7709
A144: 47208 | J144: 150.93033 | K144: 1.0088684 | L144: 82.551116 | M144: ='[4]VAR expectations'!C168 -> 2.5644821 | N144: -0.09576 | O144: -0.02 | P144: 277.11993 | Q144: 58.3446 | R144: 518.1332 | S144: 109.45673 | T144: 20.782733 | U144: 16.1628 | V144: =+S144+T144+U144 -> 146.40227
A145: 47299 | J145: 151.80207 | K145: 1.0075529 | L145: 82.438014 | M145: ='[4]VAR expectations'!C169 -> 2.7218437 | N145: 0.01787 | O145: 0.09 | P145: 276.5116 | Q145: 58.3509 | R145: 518.3666 | S145: 109.6059 | T145: 20.9379 | U145: 16.2271 | V145: =+S145+T145+U145 -> 146.7709

Sheet Data_FAME
C1: Start date | D1: Last date
C2: 1990m2 | D2: 2025m12 | AT2: BPROJM((IKBI.M-BQAT.M)/(IKBL.M-BPIC.M),BQKL.M,"E") | AY2: PUB12MEAN.Q
A3: Variable | B3: CPI | F3: Services | H3: Core goods | J3: Food | N3: Energy | Q3: Resource utilization | AD3: Labour cost | AH3: Exchange rate | AL3: Expected average overnight rate | AN3: Bank Rate (adjusted for QE) | AR3: Import price | AT3: Import price excluding fuel | AV3: Global inflation | AY3: Inflation expectation
A5: Indicator | B5: Headline CPI | C5: Adjusted headline CPI | D5: Forecasted CPI | F5: CPI services | G5: CPI_srv_f | H5: CPI core goods | I5: CPI_cg_f | J5: CPI food | K5: CPI_f_f | L5: CPI food + alcohol & tobacco | M5: CPI Food_at_f | N5: CPI energy | O5: CPI_e_f | Q5: GDP | T5: Capac Utiliz | W5: Hours worked | Z5: Unemployment rate | AD5: Wages | AH5: Sterling ERI | AL5: 3-month OIS | AN5: UK instantaneous nominal forward curve (OIS) and Bank calculations
A6: FAME original series | B6: ="conv2qa(X12(stifidx.m,MULT," & TEXT($C$2,"yyyy""m""m") & "," & TEXT($D$2,"yyyy""m""m") & "))" -> conv2qa(X12(stifidx.m,MULT,1990m2,2025m12)) | C6: ="conv2qa(X12(fprojm(stifidx_clothingadjusted.m,stifidx.m,""L""),MULT," & TEXT(C2,"yyyy""m""m") & "," & TEXT(D2,"yyyy""m""m") & "))" -> conv2qa(X12(fprojm(stifidx_clothingadjusted.m,stifidx.m,"L"),MULT,1990m2,2025m12)) | D6: N25_cpisa_FIN.q | F6: ="conv2qa(X12(stif_srv.m,MULT," & TEXT($C$2,"yyyy""m""m") & "," & TEXT($D$2,"yyyy""m""m") & "))" -> conv2qa(X12(stif_srv.m,MULT,1990m2,2025m12)) | H6: ="conv2qa(X12(stif_gds_xeatfnab.m,MULT," & TEXT($C$2,"yyyy""m""m") & "," & TEXT($D$2,"yyyy""m""m") & "))" -> conv2qa(X12(stif_gds_xeatfnab.m,MULT,1990m2,2025m12)) | J6: ="conv2qa(X12(stif_fnab.m,MULT," & TEXT($C$2,"yyyy""m""m") & "," & TEXT($D$2,"yyyy""m""m") & "))" -> conv2qa(X12(stif_fnab.m,MULT,1990m2,2025m12)) | L6: ="conv2qa(X12(cpi_aggregation(stif_fnab.m, booze.m, fags.m,#,#,#,#,#,#,#,#,#,#,#,#,#,#,#,#,#),MULT," & TEXT($C$2,"yyyy""m""m") & "," & TEXT($D$2,"yyyy""m""m") & "))" -> conv2qa(X12(cpi_aggregation(stif_fnab.m, booze.m, fags.m,#,#,#,#,#,#,#,#,#,#,#,#,#,#,#,#,#),MULT,1990m2,2025m12)) | N6: ="conv2qa(X12(stif_pu.m,MULT," & TEXT($C$2,"yyyy""m""m") & "," & TEXT($D$2,"yyyy""m""m") & "))" -> conv2qa(X12(stif_pu.m,MULT,1990m2,2025m12)) | Q6: mod_gdpkp.q | R6: N25_gdpkp_FIN.q | S6: Combined | T6: mod_capu.q | U6: N25_capu_FIN.q | V6: Combined | W6: mod_hrs.q | X6: N25_hrs_FIN.q | Y6: Combined | Z6: mod_unemp.q | AA6: N25_unemp_FIN.q | AB6: Combined | AD6: conv2qa(OVERLAY(KAJ2_DP.M,KAJ2_HIST.M)) | AE6: N25_AWERPS_FIN.q | AF6: Combined | AH6: CONV2QA(SERI.B) | AI6: N25_EER_FIN.q | AJ6: Combined | AL6: CONV2QA(BPROJA(VRPSPOT(OIS,UK,0.25),BPROJA(VRPSPOT(NOM,UK,0.25),VRPSPOT(BLC,UK,0.25),3Mar1997),"E")) | AN6: mod_rgawqe.q | AO6: N25_rgawqe_FIN.q | AP6: Combined | AR6: mod_pmdef.q | AS6: N25_pmdef_FIN.q | AT6: CONV2QA(BPROJM((IKBI.M-BQAT.M)/(IKBL.M-BPIC.M),BQKL.M,"E")) | AV6: mod_cpif.q | AW6: N25_cpif_FIN.q | AY6: PUB12MEDIAN.Q | AZ6: CONV2QA(cgrp.m) | BA6: fprojm(PUB12MEDIAN.Q,CONV2QA(cgrp.m),""L"") | BB6: BPROJA(conv2qa(cgrp.m),PUB12MEDIAN.Q,"E")
A7: FAME transformation
A8: Comments | B8: Official STIF headline CPI series interpolated from monthly to quarterly. Seasonally adjusted manually. | C8: Back data adjusted to account for ONS mismeasurement of clothing prices in the late-1990s and early-2000s. Projected forward with the STIF to the official STIF horizon. Seasonally adjusted manually. | F8: Services interpolated STIF series. Seasonally adjusted manually | H8: Core good interpolated STIF series. Seasonally adjusted manually | J8: Food interpolated STIF series. Seasonally adjusted manually | N8: Energy interpolated STIF series. Seasonally adjusted manually | AD8: Private sector regular pay | AY8: Barclays BASIX 1yr ahead median inflation expectations | AZ8: Citigroup inflation expectation for 12 months ahead since Nov-2005 | BA8: Combined expectation ( B + City growth | BB8: Combined expectation (City + Barclays backdata growth)
A9: My R code | B9: cpi | C9: cpi_a | D9: cpi_f | F9: services | G9: services_f | H9: core_gds | I9: core_gds_f | J9: food | K9: food_f | L9: food_at | M9: food_at_f | N9: energy | O9: energy_f | Q9: gdpkp | R9: gdpkp_f | T9: capu | U9: capu_f | W9: hrs | X9: hrs_f | Z9: unemp | AA9: unemp_f | AD9: wage | AE9: wage_f | AH9: eer | AI9: eer_f | AL9: ois_rate | AN9: bank_rate | AO9: bank_rate_f | AR9: pmdef | AS9: pmdef_f | AT9: pmdef_xf | AV9: cpif | AW9: cpif_f | BA9: inf_exp
A10: =[3]!FAMEData("FAMEDATE", "1990", "2028", 0,"Quarterly", "Down", "Heading", "Normal") -> Refresh | B10: =[3]!FAMEData(B6, "1990", "2028", 0,"Quarterly", "Down", "Heading", "Normal") -> Refresh | C10: =[3]!FAMEData(C6, "1990", "2028", 0,"Quarterly", "Down", "Heading", "Normal") -> Refresh | D10: =[3]!FAMEData(D6, "1990", "2028", 0,"Quarterly", "Down", "Heading", "Normal") -> Refresh | F10: =[3]!FAMEData(F6, "1990", "2028", 0,"Quarterly", "Down", "Heading", "Normal") -> Refresh | H10: =[3]!FAMEData(H6, "1990", "2028", 0,"Quarterly", "Down", "Heading", "Normal") -> Refresh | J10: =[3]!FAMEData(J6, "1990", "2028", 0,"Quarterly", "Down", "Heading", "Normal") -> Refresh | L10: =[3]!FAMEData(L4, "1990", "2028", 0,"Quarterly", "Down", "Heading", "Normal") -> Refresh | N10: =[3]!FAMEData(N6, "1990", "2028", 0,"Quarterly", "Down", "Heading", "Normal") -> Refresh | P10: =[3]!FAMEData(P6, "1990", "2028", 0,"Quarterly", "Down", "Heading", "Normal") -> Refresh | Q10: =[3]!FAMEData(Q6, "1990", "2028", 0,"Quarterly", "Down", "Heading", "Normal") -> Refresh | R10: =[3]!FAMEData(R6, "1990", "2028", 0,"Quarterly", "Down", "Heading", "Normal") -> Refresh | T10: =[3]!FAMEData(T6, "1990", "2028", 0,"Quarterly", "Down", "Heading", "Normal") -> Refresh | U10: =[3]!FAMEData(U6, "1990", "2028", 0,"Quarterly", "Down", "Heading", "Normal") -> Refresh | W10: =[3]!FAMEData(W6, "1990", "2028", 0,"Quarterly", "Down", "Heading", "Normal") -> Refresh | X10: =[3]!FAMEData(X6, "1990", "2028", 0,"Quarterly", "Down", "Heading", "Normal") -> Refresh | Z10: =[3]!FAMEData(Z6, "1990", "2028", 0,"Quarterly", "Down", "Heading", "Normal") -> Refresh | AA10: =[3]!FAMEData(AA6, "1990", "2028", 0,"Quarterly", "Down", "Heading", "Normal") -> Refresh | AC10: =[3]!FAMEData(AC6, "1990", "2028", 0,"Quarterly", "Down", "Heading", "Normal") -> Refresh | AD10: =[3]!FAMEData(AD6, "1990", "2028", 0,"Quarterly", "Down", "Heading", "Normal") -> Refresh | AE10: =[3]!FAMEData(AE6, "1990", "2028", 0,"Quarterly", "Down", "Heading", "Normal") -> Refresh | AG10: =[3]!FAMEData(AG6, "1990", "2028", 0,"Quarterly", "Down", "Heading", "Normal") -> Refresh | AH10: =[3]!FAMEData(AH6, "1990", "2028", 0,"Quarterly", "Down", "Heading", "Normal") -> Refresh | AI10: =[3]!FAMEData(AI6, "1990", "2028", 0,"Quarterly", "Down", "Heading", "Normal") -> Refresh | AK10: =[3]!FAMEData(AK6, "1990", "2028", 0,"Quarterly", "Down", "Heading", "Normal") -> Refresh | AL10: =[3]!FAMEData(AL6, "1990", "2028", 0,"Quarterly", "Down", "Heading", "Normal") -> Refresh | AN10: =[3]!FAMEData(AN6, "1990", "2028", 0,"Quarterly", "Down", "Heading", "Normal") -> Refresh | AO10: =[3]!FAMEData(AO6, "1990", "2028", 0,"Quarterly", "Down", "Heading", "Normal") -> Refresh | AQ10: =[3]!FAMEData(AQ6, "1990", "2028", 0,"Quarterly", "Down", "Heading", "Normal") -> Refresh | AR10: =[3]!FAMEData(AR6, "1990", "2028", 0,"Quarterly", "Down", "Heading", "Normal") -> Refresh | AS10: =[3]!FAMEData(AS6, "1990", "2028", 0,"Quarterly", "Down", "Heading", "Normal") -> Refresh | AT10: =[3]!FAMEData(AT6, "1990", "2028", 0,"Quarterly", "Down", "Heading", "Normal") -> Refresh | AV10: =[3]!FAMEData(AV6, "1990", "2028", 0,"Quarterly", "Down", "Heading", "Normal") -> Refresh | AW10: =[3]!FAMEData(AW6, "1990", "2028", 0,"Quarterly", "Down", "Heading", "Normal") -> Refresh | AY10: =[3]!FAMEData(AY6, "1990", "2028", 0,"Quarterly", "Down", "Heading", "Normal") -> Refresh | AZ10: =[3]!FAMEData(AZ6, "1990", "2028", 0,"Quarterly", "Down", "Heading", "Normal") -> Refresh | BA10: =[3]!FAMEData(BA6, "1990", "2028", 0,"Quarterly", "Down", "Heading", "Normal") -> Refresh | BB10: =[3]!FAMEData(BB6, "1990", "2028", 0,"Quarterly", "Down", "Heading", "Normal") -> Refresh
A11: 32963 | D11: 54.233282 | Q11: 379458 | R11: 379458 | T11: -0.70757743 | U11: 0.97333792 | W11: 908133 | X11: 908133 | Z11: 0.069332964 | AA11: 0.069332964 | AD11: 183.54771 | AE11: 183.54771 | AH11: 92.432746 | AI11: 92.432746 | AN11: 14.875 | AO11: 14.875 | AR11: 0.57372025 | AS11: 0.57372025 | AT11: 0.60812747 | AV11: 66.518783 | AW11: 66.518783 | AY11: 8.1689655 | BA11: 8.1689655 | BB11: 7.7756322
A12: 33054 | B12: 55.216192 | C12: 53.449601 | D12: 55.931591 | F12: 37.291624 | H12: 109.4919 | J12: 55.346352 | L12: 46.254605 | N12: 33.809155 | Q12: 381997 | R12: 381997 | T12: -1.1483808 | U12: 0.93596216 | W12: 906588.84 | X12: 906588.84 | Z12: 0.069184781 | AA12: 0.069184781 | AD12: 189.32838 | AE12: 189.32838 | AH12: 93.068646 | AI12: 93.068646 | AL12: 14.519134 | AN12: 14.875 | AO12: 14.875 | AR12: 0.57773628 | AS12: 0.57773628 | AT12: 0.60985266 | AV12: 67.416856 | AW12: 67.416856 | AY12: 9.0307167 | BA12: 9.0307167 | BB12: 8.6373834
A13: 33146 | B13: 56.369272 | C13: 54.565685 | D13: 56.730638 | F13: 38.226404 | H13: 110.77076 | J13: 56.069625 | L13: 47.031491 | N13: 35.502014 | Q13: 377831 | R13: 377831 | T13: -1.7358221 | U13: -0.79049292 | W13: 901813.5 | X13: 901813.5 | Z13: 0.070779647 | AA13: 0.070779647 | AD13: 193.61239 | AE13: 193.61239 | AH13: 99.445968 | AI13: 99.445968 | AL13: 14.377204 | AN13: 14.875 | AO13: 14.875 | AR13: 0.55930606 | AS13: 0.55930606 | AT13: 0.59130693 | AV13: 68.109698 | AW13: 68.109698 | AY13: 9.49729 | BA13: 9.49729 | BB13: 9.1039566
A14: 33238 | B14: 57.494732 | C14: 55.655628 | D14: 57.774359 | F14: 39.201503 | H14: 112.05037 | J14: 57.003542 | L14: 47.936474 | N14: 36.723481 | Q14: 375916 | R14: 375916 | T14: -2.1830843 | U14: -1.1706663 | W14: 892410.87 | X14: 892410.87 | Z14: 0.074650616 | AA14: 0.074650616 | AD14: 197.31141 | AE14: 197.31141 | AH14: 99.670858 | AI14: 99.670858 | AL14: 13.268016 | AN14: 13.9531 | AO14: 13.9531 | AR14: 0.56615029 | AS14: 0.56615029 | AT14: 0.5885035 | AV14: 69.42033 | AW14: 69.42033 | AY14: 7.872807 | BA14: 7.872807 | BB14: 7.4794737
A15: 33328 | B15: 58.131185 | C15: 56.271618 | D15: 58.016017 | F15: 40.047704 | H15: 112.98292 | J15: 57.575944 | L15: 48.483131 | N15: 36.121607 | Q15: 374060 | R15: 374060 | T15: -2.9343664 | U15: -1.255856 | W15: 881370.83 | X15: 881370.83 | Z15: 0.079969483 | AA15: 0.079969483 | AD15: 199.57143 | AE15: 199.57143 | AH15: 99.118131 | AI15: 99.118131 | AL15: 12.723411 | AN15: 13.3992 | AO15: 13.3992 | AR15: 0.56293382 | AS15: 0.56293382 | AT15: 0.59734507 | AV15: 70.402484 | AW15: 70.402484 | AY15: 7.5657895 | BA15: 7.5657895 | BB15: 7.1724561
A16: 33419 | B16: 59.827705 | C16: 57.9136 | D16: 60.59482 | F16: 41.709306 | H16: 115.1372 | J16: 58.344421 | L16: 49.975838 | N16: 37.362098 | Q16: 373608 | R16: 373608 | T16: -3.3312328 | U16: -1.273024 | W16: 869788.47 | X16: 869788.47 | Z16: 0.086627038 | AA16: 0.086627038 | AD16: 204.08804 | AE16: 204.08804 | AH16: 96.421142 | AI16: 96.421142 | AL16: 11.097574 | AN16: 11.7379 | AO16: 11.7379 | AR16: 0.57235316 | AS16: 0.57235316 | AT16: 0.60942136 | AV16: 71.079089 | AW16: 71.079089 | AY16: 5.978979 | BA16: 5.978979 | BB16: 5.5856456
A17: 33511 | B17: 60.749441 | C17: 58.805692 | D17: 61.129417 | F17: 42.478114 | H17: 116.63678 | J17: 58.886712 | L17: 50.515686 | N17: 38.223615 | Q17: 372878 | R17: 372878 | T17: -3.4757524 | U17: -1.2520863 | W17: 859520.46 | X17: 859520.46 | Z17: 0.09159133 | AA17: 0.09159133 | AD17: 208.2244 | AE17: 208.2244 | AH17: 95.722653 | AI17: 95.722653 | AL17: 10.282062 | AN17: 10.7981 | AO17: 10.7981 | AR17: 0.58356049 | AS17: 0.58356049 | AT17: 0.61934117 | AV17: 71.94639 | AW17: 71.94639 | AY17: 5.0018519 | BA17: 5.0018519 | BB17: 4.6085185
A18: 33603 | B18: 61.5371 | C18: 59.568663 | D18: 61.822885 | F18: 43.254296 | H18: 117.83569 | J18: 59.515813 | L18: 51.223588 | N18: 38.311037 | Q18: 373357 | R18: 373357 | T18: -3.1182875 | U18: -1.0417908 | W18: 851930 | X18: 851930 | Z18: 0.094575166 | AA18: 0.094575166 | AD18: 211.35106 | AE18: 211.35106 | AH18: 96.172297 | AI18: 96.172297 | AL18: 10.071213 | AN18: 10.375 | AO18: 10.375 | AR18: 0.57552587 | AS18: 0.57552587 | AT18: 0.61287173 | AV18: 72.918164 | AW18: 72.918164 | AY18: 4.8059006 | BA18: 4.8059006 | BB18: 4.4125673
A19: 33694 | B19: 62.131083 | C19: 60.143593 | D19: 62.056834 | F19: 43.882111 | H19: 118.7579 | J19: 59.959978 | L19: 51.670967 | N19: 38.258535 | Q19: 373317 | R19: 373317 | T19: -3.3500751 | U19: -1.1690213 | W19: 847165.67 | X19: 847165.67 | Z19: 0.097007586 | AA19: 0.097007586 | AD19: 215.27103 | AE19: 215.27103 | AH19: 95.797952 | AI19: 95.797952 | AL19: 10.079292 | AN19: 10.375 | AO19: 10.375 | AR19: 0.56924052 | AS19: 0.56924052 | AT19: 0.61394997 | AV19: 73.684026 | AW19: 73.684026 | AY19: 4.7386667 | BA19: 4.7386667 | BB19: 4.3453333
A20: 33785 | B20: 62.416759 | C20: 60.420047 | D20: 63.194403 | F20: 44.452914 | H20: 118.72539 | J20: 59.723829 | L20: 51.90606 | N20: 38.383855 | Q20: 372751 | R20: 372751 | T20: -3.1236345 | U20: -1.8203614 | W20: 847646.6 | X20: 847646.6 | Z20: 0.09785394 | AA20: 0.09785394 | AD20: 216.52634 | AE20: 216.52634 | AH20: 97.573482 | AI20: 97.573482 | AL20: 9.7404194 | AN20: 10.0471 | AO20: 10.0471 | AR20: 0.56506054 | AS20: 0.56506054 | AT20: 0.60791183 | AV20: 74.734655 | AW20: 74.734655 | AY20: 4.4401198 | BA20: 4.4401198 | BB20: 4.0467864
A21: 33877 | B21: 62.691059 | C21: 60.685211 | D21: 63.067373 | F21: 44.967908 | H21: 118.80745 | J21: 59.567454 | L21: 52.023965 | N21: 38.275282 | Q21: 374537 | R21: 374537 | T21: -3.3243309 | U21: -0.85749752 | W21: 840427.1 | X21: 840427.1 | Z21: 0.099370554 | AA21: 0.099370554 | AD21: 219.44681 | AE21: 219.44681 | AH21: 96.710815 | AI21: 96.710815 | AL21: 9.695813 | AN21: 9.7673 | AO21: 9.7673 | AR21: 0.56539814 | AS21: 0.56539814 | AT21: 0.60273627 | AV21: 75.563565 | AW21: 75.563565 | AY21: 4.234767 | BA21: 4.234767 | BB21: 3.8414337
A22: 33969 | B22: 63.195466 | C22: 61.173856 | D22: 63.467567 | F22: 45.533479 | H22: 118.62097 | J22: 60.084592 | L22: 52.659248 | N22: 38.984401 | Q22: 377418 | R22: 377418 | T22: -3.2279251 | U22: -0.27664328 | W22: 832788.39 | X22: 832788.39 | Z22: 0.10371119 | AA22: 0.10371119 | AD22: 221.35146 | AE22: 221.35146 | AH22: 84.845339 | AI22: 84.845339 | AL22: 7.1698732 | AN22: 7.5313 | AO22: 7.5313 | AR22: 0.59920423 | AS22: 0.59920423 | AT22: 0.64263116 | AV22: 76.644093 | AW22: 76.644093 | AY22: 3.9262048 | BA22: 3.9262048 | BB22: 3.5328715
A23: 34059 | B23: 63.53193 | C23: 61.499755 | D23: 63.530914 | F23: 46.101573 | H23: 118.15539 | J23: 60.484175 | L23: 53.005409 | N23: 39.383108 | Q23: 379370 | R23: 379370 | T23: -3.0780999 | U23: -0.54416477 | W23: 832300.53 | X23: 832300.53 | Z23: 0.10618491 | AA23: 0.10618491 | AD23: 221.58357 | AE23: 221.58357 | AH23: 83.282759 | AI23: 83.282759 | AL23: 5.9494269 | AN23: 6.129 | AO23: 6.129 | AR23: 0.62407768 | AS23: 0.62407768 | AT23: 0.67454707 | AV23: 77.756408 | AW23: 77.756408 | AY23: 3.4645161 | BA23: 3.4645161 | BB23: 3.0711828
... A74: 38717 | B74: 78.662785 | C74: 77.824911 | D74: 78.650458 | F74: 72.769712 | H74: 99.585812 | J74: 71.488262 | L74: 69.148832 | N74: 62.212631 | Q74: 556311 | R74: 556311 | T74: 0.18833164 | U74: -0.32157998 | W74: 929270.73 | X74: 929270.73 | Z74: 0.051464698 | AA74: 0.051464698 | AD74: 356.56273 | AE74: 356.56273 | AH74: 99.510515 | AI74: 99.510515 | AL74: 4.3645593 | AN74: 4.5 | AO74: 4.5 | AR74: 0.63647439 | AS74: 0.63649118 | AT74: 0.66417039 | AV74: 106.95874 | AW74: 106.95874 | AY74: 2.72 | BA74: 2.72 | BB74: 2.3266667
A75: 38807 | B75: 79.029348 | C75: 78.240803 | D75: 78.979696 | F75: 73.378211 | H75: 99.205958 | J75: 71.887081 | L75: 69.456223 | N75: 63.507441 | Q75: 558314 | R75: 558314 | T75: 0.23866415 | U75: -0.36700616 | W75: 931711.6 | X75: 931711.6 | Z75: 0.052340419 | AA75: 0.052340419 | AD75: 360.69047 | AE75: 360.69047 | AH75: 98.760283 | AI75: 98.760283 | AL75: 4.3369085 | AN75: 4.5 | AO75: 4.5 | AR75: 0.64392875 | AS75: 0.64393675 | AT75: 0.66759821 | AV75: 107.5325 | AW75: 107.5325 | AY75: 2.86 | AZ75: 2.4666667 | BA75: 2.86 | BB75: 2.4666667
A76: 38898 | B76: 79.618023 | C76: 78.892208 | D76: 79.688486 | F76: 74.0114 | H76: 98.655423 | J76: 72.380874 | L76: 69.890028 | N76: 67.672092 | Q76: 559795 | R76: 559795 | T76: 0.57499474 | U76: -0.059382452 | W76: 930502.81 | X76: 930502.81 | Z76: 0.054720238 | AA76: 0.054720238 | AD76: 364.6037 | AE76: 364.6037 | AH76: 100.27914 | AI76: 100.27914 | AL76: 4.4311161 | AN76: 4.5 | AO76: 4.5 | AR76: 0.64502189 | AS76: 0.64504573 | AT76: 0.66422754 | AV76: 108.4046 | AW76: 108.4046 | AY76: 2.58 | AZ76: 2.4 | BA76: 2.58 | BB76: 2.4
A77: 38990 | B77: 80.269783 | C77: 79.587648 | D77: 80.314088 | F77: 74.553781 | H77: 98.574413 | J77: 73.986747 | L77: 71.285671 | N77: 70.05051 | Q77: 560675 | R77: 560675 | T77: 0.7443586 | U77: 0.038059171 | W77: 931829.12 | X77: 931829.12 | Z77: 0.054843628 | AA77: 0.054843628 | AD77: 367.62989 | AE77: 367.62989 | AH77: 102.33265 | AI77: 102.33265 | AL77: 4.6392397 | AN77: 4.6602 | AO77: 4.6602 | AR77: 0.644692 | AS77: 0.644692 | AT77: 0.6673308 | AV77: 108.92523 | AW77: 108.92523 | AY77: 2.83 | AZ77: 2.3 | BA77: 2.83 | BB77: 2.3
A78: 39082 | B78: 80.789341 | C78: 80.161173 | D78: 80.767606 | F78: 75.449961 | H78: 98.560412 | J78: 74.86975 | L78: 72.057899 | N78: 69.842533 | Q78: 562669 | R78: 562669 | T78: 0.83563403 | U78: 0.061568725 | W78: 935596.33 | X78: 935596.33 | Z78: 0.055011599 | AA78: 0.055011599 | AD78: 372.29684 | AE78: 372.29684 | AH78: 103.71343 | AI78: 103.71343 | AL78: 4.9426583 | AN78: 4.8889 | AO78: 4.8889 | AR78: 0.63674418 | AS78: 0.63671215 | AT78: 0.66589675 | AV78: 109.25189 | AW78: 109.25189 | AY78: 3.02 | AZ78: 2.4333333 | BA78: 3.02 | BB78: 2.4333333
A79: 39172 | B79: 81.311932 | C79: 80.719798 | D79: 81.26267 | F79: 76.094721 | H79: 98.478151 | J79: 75.238914 | L79: 72.5512 | N79: 71.12996 | Q79: 568845 | R79: 568845 | T79: 1.0007109 | U79: 0.38739604 | W79: 937123.73 | X79: 937123.73 | Z79: 0.055137924 | AA79: 0.055137924 | AD79: 375.4149 | AE79: 375.4149 | AH79: 104.73003 | AI79: 104.73003 | AL79: 5.2602442 | AN79: 5.2227 | AO79: 5.2227 | AR79: 0.62581298 | AS79: 0.62580915 | AT79: 0.6568432 | AV79: 109.96318 | AW79: 109.96318 | AY79: 3 | AZ79: 2.5333333 | BA79: 3 | BB79: 2.5333333
A80: 39263 | B80: 81.649265 | C80: 81.108139 | D80: 81.726258 | F80: 76.651412 | H80: 98.270882 | J80: 76.215934 | L80: 73.298258 | N80: 71.15527 | Q80: 574194 | R80: 574194 | T80: 1.0016699 | U80: 0.36395734 | W80: 941244.91 | X80: 941244.91 | Z80: 0.053504741 | AA80: 0.053504741 | AD80: 380.43523 | AE80: 380.43523 | AH80: 104.23937 | AI80: 104.23937 | AL80: 5.4924851 | AN80: 5.3975 | AO80: 5.3975 | AR80: 0.63252629 | AS80: 0.63249527 | AT80: 0.66057546 | AV80: 110.90526 | AW80: 110.90526 | AY80: 2.94 | AZ80: 2.4666667 | BA80: 2.94 | BB80: 2.4666667
A81: 39355 | B81: 81.697046 | C81: 81.201365 | D81: 81.738763 | F81: 77.222044 | H81: 97.524545 | J81: 76.301598 | L81: 73.551324 | N81: 70.481994 | Q81: 579605 | R81: 579605 | T81: 1.04885 | U81: 0.32741784 | W81: 943124.64 | X81: 943124.64 | Z81: 0.053102039 | AA81: 0.053102039 | AD81: 386.18976 | AE81: 386.18976 | AH81: 104.41272 | AI81: 104.41272 | AL81: 5.7021116 | AN81: 5.7383 | AO81: 5.7383 | AR81: 0.6342972 | AS81: 0.63428596 | AT81: 0.66029191 | AV81: 111.64604 | AW81: 111.64604 | AY81: 2.8 | AZ81: 2.5 | BA81: 2.8 | BB81: 2.5
A82: 39447 | B82: 82.495703 | C82: 82.056664 | D82: 82.455034 | F82: 77.963036 | H82: 97.459759 | J82: 78.596965 | L82: 75.219863 | N82: 73.077864 | Q82: 584504 | R82: 584504 | T82: -0.52652474 | U82: 0.40657804 | W82: 943113.12 | X82: 943113.12 | Z82: 0.051566368 | AA82: 0.051566368 | AD82: 388.13105 | AE82: 388.13105 | AH82: 101.59429 | AI82: 101.59429 | AL82: 5.4667745 | AN82: 5.6875 | AO82: 5.6875 | AR82: 0.65152011 | AS82: 0.65156665 | AT82: 0.67170801 | AV82: 112.88538 | AW82: 112.88538 | AY82: 3.22 | AZ82: 2.7 | BA82: 3.22 | BB82: 2.7
A83: 39538 | B83: 83.242659 | C83: 82.858148 | D83: 83.221734 | F83: 78.592453 | H83: 96.980479 | J83: 79.533887 | L83: 75.989625 | N83: 77.885282 | Q83: 586690 | R83: 586690 | T83: 0.018664572 | U83: -0.4204313 | W83: 955064.44 | X83: 955064.44 | Z83: 0.05182662 | AA83: 0.05182662 | AD83: 391.92013 | AE83: 391.92013 | AH83: 95.934954 | AI83: 95.934954 | AL83: 5.0933638 | AN83: 5.3548 | AO83: 5.3548 | AR83: 0.6775423 | AS83: 0.67751014 | AT83: 0.69147474 | AV83: 114.00884 | AW83: 114.00884 | AY83: 3.71 | AZ83: 3.3233333 | BA83: 3.71 | BB83: 3.3233333
A84: 39629 | B84: 84.397119 | C84: 84.058181 | D84: 84.4784 | F84: 79.544659 | H84: 96.706328 | J84: 82.317616 | L84: 78.381765 | N84: 82.676197 | Q84: 583541 | R84: 583541 | T84: -0.67527481 | U84: -0.74769076 | W84: 944566.73 | X84: 944566.73 | Z84: 0.053504884 | AA84: 0.053504884 | AD84: 395.699 | AE84: 395.699 | AH84: 93.071035 | AI84: 93.071035 | AL84: 4.950754 | AN84: 5.0278 | AO84: 5.0278 | AR84: 0.7052457 | AS84: 0.70527093 | AT84: 0.71113775 | AV84: 115.26661 | AW84: 115.26661 | AY84: 4.41 | AZ84: 4.1266667 | BA84: 4.41 | BB84: 4.1266667
A85: 39721 | B85: 85.60477 | C85: 85.325866 | D85: 85.633338 | F85: 80.566569 | H85: 96.414619 | J85: 85.57378 | L85: 80.821325 | N85: 87.767591 | Q85: 573961 | R85: 573961 | T85: -1.0541838 | U85: -1.1688856 | W85: 945168.4 | X85: 945168.4 | Z85: 0.058554666 | AA85: 0.058554666 | AD85: 398.34704 | AE85: 398.34704 | AH85: 91.695079 | AI85: 91.695079 | AL85: 4.9818732 | AN85: 5 | AO85: 5 | AR85: 0.72643695 | AS85: 0.72646358 | AT85: 0.7260517 | AV85: 115.87088 | AW85: 115.87088 | AY85: 4.65 | AZ85: 4.3404589 | BA85: 4.65 | BB85: 4.3404589
A86: 39813 | B86: 85.715219 | C86: 85.476509 | D86: 85.640878 | F86: 81.438238 | H86: 95.375476 | J86: 86.792971 | L86: 81.79337 | N86: 85.991099 | Q86: 561816 | R86: 561816 | T86: -2.1036492 | U86: -1.851972 | W86: 939462.58 | X86: 939462.58 | Z86: 0.063529284 | AA86: 0.063529284 | AD86: 400.68993 | AE86: 400.68993 | AH86: 83.94238 | AI86: 83.94238 | AL86: 2.583527 | AN86: 3.3672 | AO86: 3.3672 | AR86: 0.72241259 | AS86: 0.72239393 | AT86: 0.74428941 | AV86: 115.153 | AW86: 115.153 | AY86: 3.25 | AZ86: 1.5441543 | BA86: 3.25 | BB86: 1.5441543
... A131: 43921 | B131: 108.87455 | C131: 108.87442 | D131: 108.76735 | F131: 112.16404 | H131: 103.97905 | J131: 104.0506 | L131: 107.2733 | N131: 112.82475 | Q131: 652180 | R131: 652180 | T131: -0.55373588 | U131: -0.9417896 | W131: 1028944.4 | X131: 1028944.4 | Z131: 0.041026955 | AA131: 0.041026955 | AD131: 504.30445 | AE131: 504.30445 | AH131: 79.231538 | AI131: 79.231538 | AL131: 0.49130055 | AN131: 0.23434676 | AO131: 0.23434676 | AR131: 0.8103644 | AS131: 0.81035288 | AT131: 0.84278423 | AV131: 136.35214 | AW131: 136.35214 | AY131: 2.222 | AZ131: 2.675357 | BA131: 2.222 | BB131: 2.675357
A132: 44012 | B132: 108.33473 | C132: 108.33464 | D132: 108.44287 | F132: 112.33883 | H132: 103.85904 | J132: 104.34059 | L132: 107.74333 | N132: 102.51128 | Q132: 522356 | R132: 522356 | T132: -4.24003 | U132: -1.5753313 | W132: 845934.54 | X132: 845934.54 | Z132: 0.040847424 | AA132: 0.040847424 | AD132: 490.2262 | AE132: 490.2262 | AH132: 77.416985 | AI132: 77.416985 | AL132: 0.064903233 | AN132: -0.53443525 | AO132: -0.53443525 | AR132: 0.79942922 | AS132: 0.79949974 | AT132: 0.84812666 | AV132: 135.9625 | AW132: 135.9625 | AZ132: 3.0786651 | BA132: 2.5569649 | BB132: 3.0786651
A133: 44104 | B133: 108.84021 | C133: 108.84015 | D133: 108.83048 | F133: 112.47956 | H133: 104.60933 | J133: 103.96235 | L133: 107.6367 | N133: 105.09145 | Q133: 610972 | R133: 610972 | T133: -2.0189732 | U133: -0.16911272 | W133: 912370.99 | X133: 912370.99 | Z133: 0.049594934 | AA133: 0.049594934 | AD133: 506.78792 | AE133: 506.78792 | AH133: 77.450488 | AI133: 77.453536 | AL133: 0.052329946 | AN133: -0.75116521 | AO133: -0.75116521 | AR133: 0.79831567 | AS133: 0.79834561 | AT133: 0.83443478 | AV133: 136.10441 | AW133: 136.10441 | AZ133: 3.1319435 | BA133: 2.6012149 | BB133: 3.1319435
A134: 44196 | B134: 108.88508 | C134: 108.88498 | D134: 108.88648 | F134: 113.00516 | H134: 104.84834 | J134: 103.20354 | L134: 107.31681 | N134: 102.07296 | Q134: 619330 | R134: 619330 | T134: -1.7193779 | U134: 0.17520396 | W134: 973826.03 | X134: 973826.03 | Z134: 0.052592199 | AA134: 0.052592199 | AD134: 521.84468 | AE134: 521.84468 | AH134: 77.959994 | AI134: 77.966817 | AL134: 0.044807315 | AN134: -0.98807905 | AO134: -0.98807905 | AR134: 0.80778747 | AS134: 0.80771956 | AT134: 0.83997056 | AV134: 136.36766 | AW134: 136.36766 | AZ134: 3.4145578 | BA134: 2.8359383 | BB134: 3.4145578
A135: 44286 | B135: 109.62172 | C135: 109.62163 | D135: 109.49834 | F135: 113.98605 | H135: 104.77256 | J135: 103.16418 | L135: 107.47615 | N135: 106.27267 | Q135: 612665 | R135: 612665 | T135: -1.8989207 | U135: 0.53571733 | W135: 952555.24 | X135: 952555.24 | Z135: 0.049069489 | AA135: 0.049069489 | AD135: 525.88678 | AE135: 525.88678 | AH135: 80.47557 | AI135: 80.482731 | AL135: 0.044583478 | AN135: -1.1920709 | AO135: -1.1920709 | AR135: 0.80252061 | AS135: 0.80260601 | AT135: 0.82501035 | AV135: 137.79296 | AW135: 137.79296 | AZ135: 2.9821807 | BA135: 2.4768305 | BB135: 2.9821807
A136: 44377 | B136: 110.44568 | C136: 110.44559 | D136: 110.61787 | F136: 114.39296 | H136: 105.87933 | J136: 103.52958 | L136: 107.76596 | N136: 111.43747 | Q136: 655443 | R136: 655443 | T136: 0.039010414 | U136: 1.1160079 | W136: 1006521.1 | X136: 1006521.1 | Z136: 0.046692031 | AA136: 0.046692031 | AD136: 531.51747 | AE136: 531.51747 | AH136: 81.7804 | AI136: 81.786428 | AL136: 0.050606925 | AN136: -1.3470819 | AO136: -1.3470819 | AR136: 0.81408904 | AS136: 0.81408904 | AT136: 0.82910866 | AV136: 138.99147 | AW136: 138.99147 | AZ136: 2.7653977 | BA136: 2.2967827 | BB136: 2.7653977
A137: 44469 | B137: 111.89016 | C137: 111.89007 | D137: 111.82505 | F137: 115.19159 | H137: 107.72572 | J137: 104.09639 | L137: 108.4206 | N137: 115.52495 | Q137: 666498 | R137: 666498 | T137: 0.93214669 | U137: 0.23730738 | W137: 1033812.5 | X137: 1033812.5 | Z137: 0.043738526 | AA137: 0.043738526 | AD137: 535.13556 | AE137: 535.13556 | AH137: 81.766095 | AI137: 81.769348 | AL137: 0.056322805 | AN137: -1.4409684 | AO137: -1.4409684 | AR137: 0.83581527 | AS137: 0.8357748 | AT137: 0.85017293 | AV137: 140.16666 | AW137: 140.16666 | AZ137: 3.4330399 | BA137: 2.8512886 | BB137: 3.4330399
A138: 44561 | B138: 114.22624 | C138: 114.22614 | D138: 114.2337 | F138: 116.70298 | H138: 109.67512 | J138: 105.93461 | L138: 110.41295 | N138: 126.85828 | Q138: 675680 | R138: 675680 | T138: 1.3571838 | U138: 1.2451829 | W138: 1036780 | X138: 1036780 | Z138: 0.041734239 | AA138: 0.041734239 | AD138: 543.5695 | AE138: 543.5695 | AH138: 81.602417 | AI138: 81.601332 | AL138: 0.20218077 | AN138: -1.5030493 | AO138: -1.5030493 | AR138: 0.88972454 | AS138: 0.88967799 | AT138: 0.87878505 | AV138: 142.51281 | AW138: 142.51281 | AZ138: 4.1496519 | BA138: 3.4464659 | BB138: 4.1496519
A139: 44651 | B139: 116.52329 | C139: 116.52319 | D139: 116.39382 | F139: 118.20274 | H139: 112.14539 | J139: 108.46399 | L139: 112.62009 | N139: 131.85396 | Q139: 682527 | R139: 682527 | T139: 1.2499228 | U139: 0.95337236 | W139: 1042268.2 | X139: 1042268.2 | Z139: 0.037902493 | AA139: 0.037902493 | AD139: 553.758 | AE139: 553.758 | AH139: 82.319578 | AI139: 82.320466 | AL139: 0.67704095 | AN139: -1.1701783 | AO139: -1.1701783 | AR139: 0.9170429 | AS139: 0.91704684 | AT139: 0.89191178 | AV139: 145.59556 | AW139: 145.59556 | AZ139: 5.4749404 | BA139: 4.5471755 | BB139: 5.4749404
A140: 44742 | B140: 120.44895 | C140: 120.44885 | D140: 120.6805 | F140: 119.97231 | H140: 113.41738 | J140: 112.13988 | L140: 115.54942 | N140: 171.21114 | Q140: 686335 | R140: 686335 | T140: 1.1831124 | U140: 1.5832667 | W140: 1046824 | X140: 1046824 | Z140: 0.037837388 | AA140: 0.037837388 | AD140: 561.59874 | AE140: 561.59874 | AH140: 80.16644 | AI140: 80.190637 | AL140: 1.2252211 | AN140: -0.6498841 | AO140: -0.6498841 | AR140: 0.9779835 | AS140: 0.97799595 | AT140: 0.93455798 | AV140: 149.01661 | AW140: 149.01661 | AZ140: 6.0753476 | BA140: 5.0458397 | BB140: 6.0753476
A141: 44834 | B141: 123.13188 | C141: 123.13178 | D141: 123.00483 | F141: 121.96955 | H141: 114.95687 | J141: 118.03257 | L141: 120.36449 | N141: 177.94153 | Q141: 687029 | R141: 687029 | T141: 0.85119665 | U141: 1.6762337 | W141: 1046272 | X141: 1046272 | Z141: 0.037286752 | AA141: 0.037286752 | AD141: 571.14206 | AE141: 571.14206 | AH141: 78.154103 | AI141: 78.205745 | AL141: 2.19735 | AN141: 0.093339421 | AO141: 0.093339421 | AR141: 1.0191251 | AS141: 1.0191296 | AT141: 0.96856487 | AV141: 151.74011 | AW141: 151.74011 | AZ141: 8.3216708 | BA141: 6.9115086 | BB141: 8.3216708
A142: 44926 | B142: 126.54441 | C142: 126.5443 | D142: 126.54049 | F142: 124.23922 | H142: 116.63495 | J142: 123.39302 | L142: 124.66698 | N142: 197.72579 | Q142: 688817 | R142: 688817 | T142: 0.68245656 | U142: 0.52034034 | W142: 1050738.5 | X142: 1050738.5 | Z142: 0.039158908 | AA142: 0.039158908 | AD142: 583.45782 | AE142: 583.45782 | AH142: 78.079235 | AI142: 78.079235 | AL142: 3.4175115 | AN142: 1.3695209 | AO142: 1.3695209 | AR142: 1.0076086 | AS142: 1.0075868 | AT142: 0.98644293 | AV142: 154.66827 | AW142: 154.66827 | AZ142: 7.2128482 | BA142: 5.9905833 | BB142: 7.2128482
A143: 45016 | B143: 128.41304 | C143: 128.41293 | D143: 128.33162 | F143: 125.92576 | H143: 118.54373 | J143: 127.98953 | L143: 128.60739 | N143: 192.64472 | Q143: 689206 | R143: 689206 | T143: 0.22929937 | U143: -0.33242865 | W143: 1057548.5 | X143: 1057548.5 | Z143: 0.039999897 | AA143: 0.039999897 | AD143: 593.67734 | AE143: 593.67734 | AH143: 78.144531 | AI143: 78.144531 | AL143: 4.0490439 | AN143: 2.4864327 | AO143: 2.4864327 | AR143: 1.0189055 | AS143: 1.018928 | AT143: 1.0096092 | AV143: 156.93673 | AW143: 156.93673 | AZ143: 5.4496808 | BA143: 4.5261963 | BB143: 5.4496808
... A153: 45930 | B153: 139.17556 | C153: 139.17544 | D153: 138.97188 | F153: 143.83211 | H153: 123.18805 | J153: 142.64323 | L153: 146.17239 | N153: 153.77967 | Q153: 706813.81 | R153: 706813.81 | T153: 0 | U153: -1.6978608 | W153: 1088109.9 | X153: 1088109.9 | Z153: 0.048668948 | AA153: 0.048668948 | AD153: 674.78348 | AE153: 675.06649 | AH153: 84.985242 | AI153: 84.985242 | AL153: 3.9805726 | AN153: 3.623433 | AO153: 3.623433 | AR153: 0.98826679 | AS153: 0.98826679 | AT153: 1.006946 | AV153: 170.10292 | AW153: 170.10291 | AZ153: 3.9691108 | BA153: 3.2965187 | BB153: 3.9691108
A154: 46022 | B154: 139.91004 | C154: 139.90992 | D154: 139.85387 | F154: 144.83827 | H154: 123.51261 | J154: 144.14372 | L154: 147.33385 | N154: 153.60509 | Q154: 708934.25 | R154: 708934.25 | T154: 0 | U154: -1.8289475 | W154: 1089925.4 | X154: 1089925.4 | Z154: 0.049697693 | AA154: 0.049697693 | AE154: 680.79359 | AI154: 84.479013 | AN154: 3.5100422 | AO154: 3.5100422 | AR154: 0.98263827 | AS154: 0.98263827 | AV154: 170.38249 | AW154: 170.38248
A155: 46112 | D155: 139.85387 | R155: 711292.91 | T155: 0 | U155: -1.7040186 | X155: 1088841.3 | AA155: 0.0504 | AE155: 686.71173 | AI155: 84.252156 | AN155: 3.4154219 | AO155: 3.4154219 | AS155: 0.97725801 | AV155: 170.76719 | AW155: 170.76718
A156: 46203 | D156: 139.85387 | R156: 713598.35 | T156: 0 | U156: -1.7237463 | X156: 1089619.5 | AA156: 0.050541252 | AE156: 692.12433 | AI156: 84.117539 | AN156: 3.3219454 | AO156: 3.3219454 | AS156: 0.9749504 | AV156: 171.28775 | AW156: 171.28774
A157: 46295 | D157: 139.85387 | R157: 716034.92 | T157: 0 | U157: -1.6558511 | X157: 1090427.8 | AA157: 0.050498257 | AE157: 697.3824 | AI157: 83.98531 | AN157: 3.3064318 | AO157: 3.3064318 | AS157: 0.97388427 | AV157: 172.08142 | AW157: 172.08141
A158: 46387 | D158: 139.85387 | R158: 718746.04 | T158: 0 | U158: -1.6089581 | X158: 1092228.2 | AA158: 0.050389561 | AE158: 702.54561 | AI158: 83.853892 | AN158: 3.3371672 | AO158: 3.3371672 | AS158: 0.97306004 | AV158: 172.82848 | AW158: 172.82847
A159: 46477 | D159: 139.85387 | R159: 721631.31 | T159: 0 | U159: -1.5371047 | X159: 1094167.4 | AA159: 0.05021789 | AE159: 707.66289 | AI159: 83.722428 | AN159: 3.376846 | AO159: 3.376846 | AS159: 0.97240044 | AV159: 173.77928 | AW159: 173.77927
A160: 46568 | D160: 139.85387 | R160: 724747.91 | T160: 0 | U160: -1.4586119 | X160: 1096113.2 | AA160: 0.05003043 | AE160: 712.79819 | AI160: 83.591451 | AN160: 3.4138167 | AO160: 3.4138167 | AS160: 0.97421349 | AV160: 174.72296 | AW160: 174.72296
A161: 46660 | D161: 139.85387 | R161: 727950.51 | T161: 0 | U161: -1.3726282 | X161: 1097963.2 | AA161: 0.04974273 | AE161: 717.99084 | AI161: 83.462187 | AN161: 3.4440408 | AO161: 3.4440408 | AS161: 0.97436963 | AV161: 175.63827 | AW161: 175.63827
A162: 46752 | D162: 139.85387 | R162: 731300.17 | T162: 0 | U162: -1.3276231 | X162: 1100126.6 | AA162: 0.049361609 | AE162: 723.26555 | AI162: 83.335501 | AN162: 3.469114 | AO162: 3.469114 | AS162: 0.97332131 | AV162: 176.37233 | AW162: 176.37234
A163: 46843 | D163: 139.85387 | R163: 734695.69 | T163: 0 | U163: -1.3352153 | X163: 1103179.9 | AA163: 0.048942373 | AE163: 728.68905 | AI163: 83.211438 | AN163: 3.4901568 | AO163: 3.4901568 | AS163: 0.97211634 | AV163: 177.09076 | AW163: 177.09077
A164: 46934 | D164: 139.85387 | R164: 738059.62 | T164: 0 | U164: -1.2781854 | X164: 1105659.2 | AA164: 0.048451841 | AE164: 734.32554 | AI164: 83.089805 | AN164: 3.5168931 | AO164: 3.5168931 | AS164: 0.97121443 | AV164: 177.87613 | AW164: 177.87615
A165: 47026 | D165: 139.85387 | R165: 741431.62 | T165: 0 | U165: -1.2382119 | X165: 1108222.5 | AA165: 0.047972324 | AE165: 740.21052 | AI165: 82.970359 | AN165: 3.5462896 | AO165: 3.5462896 | AS165: 0.97018549 | AV165: 178.61289 | AW165: 178.61291
A166: 47118 | D166: 139.85387 | R166: 744811.57 | U166: -1.1823681 | X166: 1110769.1 | AA166: 0.047406381 | AE166: 746.35252 | AI166: 82.852815 | AN166: 3.5778306 | AO166: 3.5778306 | AS166: 0.96942556 | AV166: 179.2077 | AW166: 179.20772

Sheet BVAR-FAME
A1: FAME code | B1: FAMEDATE | C1: CONV2MA(BPROJA(VRPSPOT(OIS,UK,0.25),BPROJA(VRPSPOT(NOM,UK,0.25),VRPSPOT(BLC,UK,0.25),3Mar1997),"E")) | F1: ="X12(fprojm(stifidx_clothingadjusted.m,stifidx.m,""L""),MULT," & TEXT(StartDate,"yyyy""m""m") & "," & TEXT(F2,"yyyy""m""m") & ")" -> X12(fprojm(stifidx_clothingadjusted.m,stifidx.m,"L"),MULT,1990m2,2025m12) | G1: ="convgen("&ForecastRound&"_CPISA_"&ForecastVersion&".q,monthly,averaged,cubic,yes)" -> convgen(A25_CPISA_draft1.q,monthly,averaged,cubic,yes) | H1: ="FPROJM("&F1&","&G1&","&TEXT(STIFHorizon,"mmmyyyy")&")" -> FPROJM(X12(fprojm(stifidx_clothingadjusted.m,stifidx.m,"L"),MULT,1990m2,2025m12),convgen(A25_CPISA_draft1.q,monthly,averaged,cubic,yes),Dec2025) | I1: ="X12(fprojm(stif_xefnab_clothingadjusted.m,stif_xeatfnab.M,""L""),MULT," & TEXT(StartDate,"yyyy""m""m") & "," & TEXT(I2,"yyyy""m""m") & ")" -> X12(fprojm(stif_xefnab_clothingadjusted.m,stif_xeatfnab.M,"L"),MULT,1990m2,2025m12) | J1: ="X12(OVERLAY(STIF_SRV.M,D7F53DPM.M),MULT," & TEXT(StartDate,"yyyy""m""m") & "," & TEXT(J2,"yyyy""m""m") & ")" -> X12(OVERLAY(STIF_SRV.M,D7F53DPM.M),MULT,1990m2,2025m12) | K1: ="X12(fprojm(stif_gds_xefnab_clothingadjusted.m,stif_gds_xeatfnab.m,""L""),MULT," & TEXT(StartDate,"yyyy""m""m") & "," & TEXT(K2,"yyyy""m""m") & ")" -> X12(fprojm(stif_gds_xefnab_clothingadjusted.m,stif_gds_xeatfnab.m,"L"),MULT,1990m2,2025m12) | L1: ="BPROJA(STIF_PU.M,X12(DK9T3DPM.M,MULT," & TEXT(StartDate,"yyyy""m""m") & ",2019m12),2019m12)" -> BPROJA(STIF_PU.M,X12(DK9T3DPM.M,MULT,1990m2,2019m12),2019m12) | M1: ="X12(OVERLAY(cpi_aggregation(booze.m,fags.m,#,#,#,#,#,#,#,#,#,#,#,#,#,#,#,#,#,#),D7BV3DPM.M),MULT," & TEXT(StartDate,"yyyy""m""m") & "," & TEXT(M2,"yyyy""m""m") & ")" -> X12(OVERLAY(cpi_aggregation(booze.m,fags.m,#,#,#,#,#,#,#,#,#,#,#,#,#,#,#,#,#,#),D7BV3DPM.M),MULT,1990m2,2025m12) | N1: ="X12(OVERLAY(STIF_FNAB.M,D7BU3DPM.M),MULT," & TEXT(StartDate,"yyyy""m""m") & "," & TEXT(N2,"yyyy""m""m") & ")" -> X12(OVERLAY(STIF_FNAB.M,D7BU3DPM.M),MULT,1990m2,2025m12) | O1: bprojm(LPMVVHR.M,convgen(M4PSA.Q,monthly,averaged,cubic,yes),"E") | P1: BPROJM((IKBI.M-BQAT.M)/(IKBL.M-BPIC.M),BQKL.M,"E") | Q1: ="convgen("&ForecastRound&"_pmdefxf_"&ForecastVersion&".q,monthly,averaged,cubic,yes)" -> convgen(A25_pmdefxf_draft1.q,monthly,averaged,cubic,yes) | R1: ="fprojm("&P1&","&Q1&",""L"")" -> fprojm(BPROJM((IKBI.M-BQAT.M)/(IKBL.M-BPIC.M),BQKL.M,"E"),convgen(A25_pmdefxf_draft1.q,monthly,averaged,cubic,yes),"L") | S1: BPROJM(ECY2_DP.M,K222.M,"E") | T1: ="convgen("&ForecastRound&"_GDPKP_"&ForecastVersion&".q,monthly,averaged,cubic,yes)" -> convgen(A25_GDPKP_draft1.q,monthly,averaged,cubic,yes) | U1: ="fprojm("&S1&","&T1&",""L"")" -> fprojm(BPROJM(ECY2_DP.M,K222.M,"E"),convgen(A25_GDPKP_draft1.q,monthly,averaged,cubic,yes),"L") | V1: YBUS.M | W1: ="convgen("&ForecastRound&"_HRS_"&ForecastVersion&".q,monthly,averaged,cubic,yes)" -> convgen(A25_HRS_draft1.q,monthly,averaged,cubic,yes) | X1: ="fprojm("&V1&","&W1&",""L"")" -> fprojm(YBUS.M,convgen(A25_HRS_draft1.q,monthly,averaged,cubic,yes),"L") | Y1: =U1&"*1000/"&X1 -> fprojm(BPROJM(ECY2_DP.M,K222.M,"E"),convgen(A25_GDPKP_draft1.q,monthly,averaged,cubic,yes),"L")*1000/fprojm(YBUS.M,convgen(A25_HRS_draft1.q,monthly,averaged,cubic,yes),"L") | Z1: OVERLAY(KAJ2_DP.M,KAJ2_HIST.M) | AA1: ="convgen("&ForecastRound&"_AWERPS_"&ForecastVersion&".q,monthly,averaged,cubic,yes)" -> convgen(A25_AWERPS_draft1.q,monthly,averaged,cubic,yes) | AB1: ="fprojm("&Z1&","&AA1&",""L"")" -> fprojm(OVERLAY(KAJ2_DP.M,KAJ2_HIST.M),convgen(A25_AWERPS_draft1.q,monthly,averaged,cubic,yes),"L") | AC1: CONV2MA(SERI.B) | AD1: ="convgen("&ForecastRound&"_EER_"&ForecastVersion&".q,monthly,averaged,cubic,yes)" -> convgen(A25_EER_draft1.q,monthly,averaged,cubic,yes) | AE1: ="fprojm("&AC1&","&AD1&",""L"")" -> fprojm(CONV2MA(SERI.B),convgen(A25_EER_draft1.q,monthly,averaged,cubic,yes),"L") | AF1: BPROJA(cgrp.m,CONVGEN(PUB12MEDIAN.Q,Monthly,Averaged,Cubic,YES),"E") | AI1: ="convgen("&ForecastRound&"_NHDS_"&ForecastVersion&".q,monthly,averaged,cubic,yes)" -> convgen(A25_NHDS_draft1.q,monthly,averaged,cubic,yes)
A2: Horizon | B2: =ForecastHorizon -> 47026 | C2: =ForecastHorizon -> 47026 | F2: =STIFHorizon -> 46022 | G2: =ForecastHorizon -> 47026 | H2: =ForecastHorizon -> 47026 | I2: =STIFHorizon -> 46022 | J2: =STIFHorizon -> 46022 | K2: =STIFHorizon -> 46022 | L2: =ForecastHorizon -> 47026 | M2: =STIFHorizon -> 46022 | N2: =STIFHorizon -> 46022 | O2: =ForecastHorizon -> 47026 | P2: =ForecastHorizon -> 47026 | Q2: =ForecastHorizon -> 47026 | R2: =ForecastHorizon -> 47026 | S2: =ForecastHorizon -> 47026 | T2: =ForecastHorizon -> 47026 | U2: =ForecastHorizon -> 47026 | V2: =ForecastHorizon -> 47026 | ... AF2: =ForecastHorizon -> 47026 | AI2: =ForecastHorizon -> 47026
A3: Notes | C3: OIS as far back as it goes (2008), then projected back additively with the gilt curve to 3 March 1997, then projected back additively with the Bank Liability Curve. | D3: The Market Curve, from the "OIS" tab. | E3: 3m OIS - combined | F3: Back data adjusted to account for ONS mismeasurement of clothing prices in the late-1990s and early-2000s. Projected forward with the STIF to the official STIF horizon. Seasonally adjusted manually. | G3: The official forecast, interpolated to monthly (this also includes back data, but we ignore it as it is only interpolated from quarterly and hasn't been adjusted for clothing mismeasurement). This is already seasonally adjusted. | H3: Combined from the two columns to the left of here. | I3: Back data adjusted to account for ONS mismeasurement of clothing prices in the late-1990s and early-2000s. Carleton Webb assures me that although the backdata is coded here as xefnab and not xeatfnab, it does nevertheless still exclude alcohol and tobacco. Projected forward with the STIF to the official STIF horizon. Seasonally adjusted manually. | J3: Seasonally adjusted manually. | K3: Back data adjusted to account for ONS mismeasurement of clothing prices in the late-1990s and early-2000s. Carleton Webb assures me that although the backdata is coded here as xefnab and not xeatfnab, it does nevertheless still exclude alcohol and tobacco. Projected forward with the STIF to the official STIF horizon. Seasonally adjusted manually. | L3: Includes both household energy and motor fuels. Manually perform seasonal adjustment over the pre-Covid period, but don't seasonally adjust things for 2020 onwards. That's because the magnitude of the shocks, when multiplied by the SA factors, makes the forecast look stupid. | M3: A&T are heavily regulated prices in the UK, so we separate them out. Manually perform seasonal adjustment. | N3: Seasonally adjusted manually. | O3: LPMVVHR (monthly) data goes back to Sep 1997. Project back from there with an interpolated version of M4PS (quarterly). Already seasonally adjusted. | P3: For 1993-1996 (when this is projected back with BQKL) this is excluding service imports, which isn't technically right but they should be small so it's okay. Already seasonally adjusted. | Q3: The forecast, interpolated. Already seasonally adjusted. | R3: Combined | S3: Official monthly GDP data back to 1997, then projected back multiplicatively with monthly industrial production. Already seasonally adjusted. | T3: The forecast, interpolated. Already seasonally adjusted. | U3: Combined | Z3: The KAJ2_DP series goes back to 2000 and can be trusted, while the KAJ2_HIST series is less trust-worthy, but is the best we have. Already seasonally adjusted. | AA3: The forecast, interpolated. Already seasonally adjusted. | AB3: Combined | AC3: Sterling exchange rate index - Back data. Shouldn't need any seasonal adjustment. | AD3: The forecast, interpolated. Shouldn't need any seasonal adjustment. | AE3: Combined | AF3: Citigroup measure back as far as it goes, then projected back additively with the Barclays Basix measure (itself interpolated to monthly). | AG3: Structural break in Citi series when in August 2022 extra bucketts were added in for respondents to choose for high inflation. Adjusted series over earlier period. | AH3: InflExp combined
A4: Name | B4: Month end | C4: 3m OIS Backdata | D4: 3m OIS forward | E4: 3m OIS | F4: CPI Backdata (clothing adjusted) and STIF | G4: CPI Forecast | H4: CPI | I4: Core (ex Energy, AT & FNAB) Backdata (clothing adjusted) and STIF | J4: All Services | K4: Core goods (ex Energy, AT & FNAB) Clothing Adjusted | L4: HH Energy | M4: Alcohol & tobacco | N4: Food & non-alcoholic beverages | O4: Household M4 | P4: Import prices (excluding fuels) | Q4: Import prices (excluding fuels) | R4: Import prices (excluding fuels) | S4: GDP Back Data | T4: GDP Forecast | U4: GDP | V4: Total Hours Back Data | W4: Total Hours Forecast | X4: Total Hours | Y4: Labour productivity (hours) | Z4: Private sector regular pay Back Data | AA4: Private sector regular pay Forecast | AB4: Private sector regular pay | AC4: Sterling ERI Back Data | AD4: Sterling ERI Forecast | AE4: Sterling ERI | AF4: 1-year-ahead HH inflation expectations | AI4: Population
A5: My code | B5: date | C5: 3mOISBackdata | D5: 3mOISforward | E5: OIS3m | F5: cpiBackdataSTIF | G5: cpiForecast | H5: cpi | I5: cpiCore | J5: cpiServices | K5: cpiCoreGoods | L5: cpiEnergy | M5: cpiAT | N5: cpiFNAB | O5: m4HH | P5: pmdefxfBackData | Q5: pmdefxfForecast | R5: pmdefxf | S5: gdpBackData | T5: gdpForecast | U5: gdp | V5: hrsBackData | W5: hrsForecast | X5: hrs | Y5: prodHrs | Z5: awePSRBackData | AA5: awePSRForecast | AB5: awePSR | AC5: seriBackData | AD5: seriForecast | AE5: seri | AF5: inflExpUnadjusted | AG5: inflExpBackdata | AH5: inflExp | AI5: nhds
B6: =[5]!FAMEData(B1, StartDate, B$2, 0,"Monthly", "Down", "No Heading", "Normal") -> #NAME? | C6: =[5]!FAMEData(C$1, StartDate, C$2, 0,"Monthly", "Down", "No Heading", "Normal") -> #NAME? | D6: =VLOOKUP($B6,[1]OIS!$A$6:$B$43,2) -> #NAME? | E6: =_xlfn.IFNA(D6,C6) -> #NAME? | F6: =[5]!FAMEData(F$1, StartDate, F$2, 0,"Monthly", "Down", "No Heading", "Normal") -> #NAME? | G6: =[5]!FAMEData(G$1, StartDate, G$2, 0,"Monthly", "Down", "No Heading", "Normal") -> #NAME? | H6: =[5]!FAMEData(H$1, StartDate, H$2, 0,"Monthly", "Down", "No Heading", "Normal") -> #NAME? | I6: =[5]!FAMEData(I$1, StartDate, I$2, 0,"Monthly", "Down", "No Heading", "Normal") -> #NAME? | J6: =[5]!FAMEData(J$1, StartDate, J$2, 0,"Monthly", "Down", "No Heading", "Normal") -> #NAME? | K6: =[5]!FAMEData(K$1, StartDate, K$2, 0,"Monthly", "Down", "No Heading", "Normal") -> #NAME? | L6: =[5]!FAMEData(L$1, StartDate, L$2, 0,"Monthly", "Down", "No Heading", "Normal") -> #NAME? | M6: =[5]!FAMEData(M$1, StartDate, M$2, 0,"Monthly", "Down", "No Heading", "Normal") -> #NAME? | ... AF6: =[5]!FAMEData(AF$1, StartDate, AF$2, 0,"Monthly", "Down", "No Heading", "Normal") -> #NAME? | AH6: =IF(ISNUMBER(AG6),AG6,AF6) -> #NAME? | AI6: =[5]!FAMEData(AI$1, StartDate, AI$2, 0,"Monthly", "Down", "No Heading", "Normal") -> #NAME?
B7: 32963 | C7: 14.681639 | D7: =VLOOKUP($B7,[1]OIS!$A$6:$B$43,2) -> #N/A | E7: =_xlfn.IFNA(D7,C7) -> 14.681639 | F7: 52.776102 | G7: 54.708953 | H7: 52.776102 | I7: 57.088771 | J7: 36.602495 | K7: 98.43152 | L7: 33.455588 | M7: 29.872873 | N7: 54.544501 | O7: 284383.42 | P7: 0.66726572 | Q7: 0.6811551 | R7: 0.66726572 | S7: 57.218242 | T7: 352533.06 | U7: 57.218242 | V7: 907.7 | W7: 907730.68 | X7: 907.7 | Y7: 63.036512 | Z7: 183.46475 | AA7: 185.35369 | AB7: 183.46475 | AC7: 91.347332 | AD7: 92.296146 | AE7: 91.347332 | AF7: 8.0243537 | AH7: =IF(ISNUMBER(AG7),AG7,AF7) -> 8.0243537 | AI7: 44836.812
B8: 32993 | C8: 14.64849 | D8: =VLOOKUP($B8,[1]OIS!$A$6:$B$43,2) -> #N/A | E8: =_xlfn.IFNA(D8,C8) -> 14.64849 | F8: 53.164758 | G8: 55.442055 | H8: 53.164758 | I8: 57.456971 | J8: 37.059962 | K8: 98.775003 | L8: 33.987222 | M8: 30.112161 | N8: 55.091831 | O8: 287559.25 | P8: 0.6679681 | Q8: 0.68659476 | R8: 0.6679681 | S8: 57.580383 | T8: 353803 | U8: 57.580383 | V8: 907.3 | W8: 907336.49 | X8: 907.3 | Y8: 63.463444 | Z8: 186.96061 | AA8: 187.50031 | AB8: 186.96061 | AC8: 91.532767 | AD8: 91.9002 | AE8: 91.532767 | AF8: 8.2710056 | AH8: =IF(ISNUMBER(AG8),AG8,AF8) -> 8.2710056 | AI8: 44844.444
B9: 33024 | C9: 14.539193 | D9: =VLOOKUP($B9,[1]OIS!$A$6:$B$43,2) -> #N/A | E9: =_xlfn.IFNA(D9,C9) -> 14.539193 | F9: 53.451956 | G9: 56.034771 | H9: 53.451956 | I9: 57.754698 | J9: 37.270886 | K9: 99.074445 | L9: 34.209048 | M9: 30.492021 | N9: 55.386162 | O9: 290760.19 | P9: 0.66234902 | Q9: 0.68622357 | R9: 0.66234902 | S9: 57.218242 | T9: 354121.36 | U9: 57.218242 | V9: 906.6 | W9: 906721.98 | X9: 906.6 | Y9: 63.112996 | Z9: 189.03201 | AA9: 189.46263 | AB9: 189.03201 | AC9: 92.675526 | AD9: 92.540364 | AE9: 92.675526 | AF9: 8.5974669 | AH9: =IF(ISNUMBER(AG9),AG9,AF9) -> 8.5974669 | AI9: 44851.976
B10: 33054 | C10: 14.384904 | D10: =VLOOKUP($B10,[1]OIS!$A$6:$B$43,2) -> #N/A | E10: =_xlfn.IFNA(D10,C10) -> 14.384904 | F10: 53.732088 | G10: 56.314505 | H10: 53.732088 | I10: 58.024588 | J10: 37.544024 | K10: 99.388307 | L10: 34.469457 | M10: 30.757678 | N10: 55.561063 | O10: 293787.59 | P10: 0.65602756 | Q10: 0.67788364 | R10: 0.65602756 | S10: 58.08738 | T10: 353049.36 | U10: 58.08738 | V10: 905.8 | W10: 905703.61 | X10: 905.8 | Y10: 64.128262 | Z10: 191.99253 | AA10: 191.01772 | AB10: 191.99253 | AC10: 95.035086 | AD10: 94.782983 | AE10: 95.035086 | AF10: 9.0160069 | AH10: =IF(ISNUMBER(AG10),AG10,AF10) -> 9.0160069 | AI10: 44859.581
B11: 33085 | C11: 14.376025 | D11: =VLOOKUP($B11,[1]OIS!$A$6:$B$43,2) -> #N/A | E11: =_xlfn.IFNA(D11,C11) -> 14.376025 | F11: 54.080075 | G11: 56.431898 | H11: 54.080075 | I11: 58.445952 | J11: 37.909933 | K11: 99.891105 | L11: 34.384594 | M11: 31.218367 | N11: 55.689533 | O11: 296560.26 | P11: 0.65040848 | Q11: 0.66576 | R11: 0.65040848 | S11: 56.711245 | T11: 351187.6 | U11: 56.711245 | V11: 904.1 | W11: 904165.01 | X11: 904.1 | Y11: 62.726739 | Z11: 192.69997 | AA11: 192.29961 | AB11: 192.69997 | AC11: 98.431405 | AD11: 97.731689 | AE11: 98.431405 | AF11: 9.327044 | AH11: =IF(ISNUMBER(AG11),AG11,AF11) -> 9.327044 | AI11: 44867.27
B12: 33116 | C12: 14.409696 | D12: =VLOOKUP($B12,[1]OIS!$A$6:$B$43,2) -> #N/A | E12: =_xlfn.IFNA(D12,C12) -> 14.409696 | F12: 54.536056 | G12: 56.653491 | H12: 54.536056 | I12: 58.759667 | J12: 38.204418 | K12: 100.23671 | L12: 35.892048 | M12: 31.35691 | N12: 56.015896 | O12: 299080.06 | P12: 0.63706316 | Q12: 0.65613215 | R12: 0.63706316 | S12: 56.783673 | T12: 349479.2 | U12: 56.783673 | V12: 901.8 | W12: 901984.29 | X12: 901.8 | Y12: 62.967036 | Z12: 193.79871 | AA12: 193.58833 | AB12: 193.79871 | AC12: 100.64483 | AD12: 100.01288 | AE12: 100.64483 | AF12: 9.2585117 | AH12: =IF(ISNUMBER(AG12),AG12,AF12) -> 9.2585117 | AI12: 44875.128
B13: 33146 | C13: 14.340885 | D13: =VLOOKUP($B13,[1]OIS!$A$6:$B$43,2) -> #N/A | E13: =_xlfn.IFNA(D13,C13) -> 14.340885 | F13: 55.080924 | G13: 57.11905 | H13: 55.080924 | I13: 59.125363 | J13: 38.564861 | K13: 100.5817 | L13: 37.468286 | M13: 31.616601 | N13: 56.503445 | O13: 301283.13 | P13: 0.63846793 | Q13: 0.6535942 | R13: 0.63846793 | S13: 56.49396 | T13: 348636.3 | U13: 56.49396 | V13: 898.8 | W13: 899207.12 | X13: 898.8 | Y13: 62.854873 | Z13: 194.33849 | AA13: 194.99379 | AB13: 194.33849 | AC13: 99.183295 | AD13: 100.63158 | AE13: 99.183295 | AF13: 8.684406 | AH13: =IF(ISNUMBER(AG13),AG13,AF13) -> 8.684406 | AI13: 44882.855
B14: 33177 | C14: 13.469716 | D14: =VLOOKUP($B14,[1]OIS!$A$6:$B$43,2) -> #N/A | E14: =_xlfn.IFNA(D14,C14) -> 13.469716 | F14: 55.534101 | G14: 57.636966 | H14: 55.534101 | I14: 59.510094 | J14: 38.909523 | K14: 101.02007 | L14: 38.111669 | M14: 31.987816 | N14: 56.697636 | O14: 303392.81 | P14: 0.63846793 | Q14: 0.65597807 | R14: 0.63846793 | S14: 56.421532 | T14: 348369.86 | U14: 56.421532 | V14: 895.8 | W14: 895954.91 | X14: 895.8 | Y14: 62.984519 | Z14: 195.32369 | AA14: 196.3703 | AB14: 195.32369 | AC14: 100.39715 | AD14: 100.13629 | AE14: 100.39715 | AF14: 7.8953278 | AH14: =IF(ISNUMBER(AG14),AG14,AF14) -> 7.8953278 | AI14: 44890.516
B15: 33207 | C15: 13.100426 | D15: =VLOOKUP($B15,[1]OIS!$A$6:$B$43,2) -> #N/A | E15: =_xlfn.IFNA(D15,C15) -> 13.100426 | F15: 55.626993 | G15: 57.90779 | H15: 55.626993 | I15: 59.857808 | J15: 39.19269 | K15: 101.47963 | L15: 37.018989 | M15: 32.127374 | N15: 57.076686 | O15: 305640.8 | P15: 0.63425362 | Q15: 0.65925378 | R15: 0.63425362 | S15: 56.13182 | T15: 348125.06 | U15: 56.13182 | V15: 892.4 | W15: 892443.64 | X15: 892.4 | Y15: 62.899843 | Z15: 197.18892 | AA15: 197.45487 | AB15: 197.18892 | AC15: 99.839586 | AD15: 99.496194 | AE15: 99.839586 | AF15: 7.3118543 | AH15: =IF(ISNUMBER(AG15),AG15,AF15) -> 7.3118543 | AI15: 44898.052
B16: 33238 | C16: 13.228521 | D16: =VLOOKUP($B16,[1]OIS!$A$6:$B$43,2) -> #N/A | E16: =_xlfn.IFNA(D16,C16) -> 13.228521 | F16: 55.805791 | G16: 57.782622 | H16: 55.805791 | I16: 60.140787 | J16: 39.502296 | K16: 101.68505 | L16: 36.279129 | M16: 32.326637 | N16: 57.236304 | O16: 308173.56 | P16: 0.64408701 | Q16: 0.66057639 | R16: 0.64408701 | S16: 55.842107 | T16: 347526.93 | U16: 55.842107 | V16: 889 | W16: 888835.12 | X16: 889 | Y16: 62.814518 | Z16: 199.42161 | AA16: 198.11367 | AB16: 199.42161 | AC16: 98.698629 | AD16: 99.37445 | AE16: 98.698629 | AF16: 7.1974576 | AH16: =IF(ISNUMBER(AG16),AG16,AF16) -> 7.1974576 | AI16: 44905.434
B17: 33269 | C17: 13.358802 | D17: =VLOOKUP($B17,[1]OIS!$A$6:$B$43,2) -> #N/A | E17: =_xlfn.IFNA(D17,C17) -> 13.358802 | F17: 56.096123 | G17: 57.589499 | H17: 56.096123 | I17: 60.481263 | J17: 39.839647 | K17: 102.05532 | L17: 36.866416 | M17: 32.45302 | N17: 57.404909 | O17: 310911.04 | P17: 0.64268224 | Q17: 0.66069056 | R17: 0.64268224 | S17: 55.697251 | T17: 346741.14 | U17: 55.697251 | V17: 885.2 | W17: 885085.16 | X17: 885.2 | Y17: 62.920527 | Z17: 199.46778 | AA17: 198.63974 | AB17: 199.46778 | AC17: 99.608009 | AD17: 99.505044 | AE17: 99.608009 | AF17: 7.3208325 | AH17: =IF(ISNUMBER(AG17),AG17,AF17) -> 7.3208325 | AI17: 44912.864
B18: 33297 | C18: 12.739959 | D18: =VLOOKUP($B18,[1]OIS!$A$6:$B$43,2) -> #N/A | E18: =_xlfn.IFNA(D18,C18) -> 12.739959 | F18: 56.358307 | G18: 57.793163 | H18: 56.358307 | I18: 60.748327 | J18: 40.075019 | K18: 102.39408 | L18: 36.472884 | M18: 32.626815 | N18: 57.66991 | O18: 313471.86 | P18: 0.64759894 | Q18: 0.66143363 | R18: 0.64759894 | S18: 55.697251 | T18: 346160.04 | U18: 55.697251 | V18: 881.4 | W18: 881409.94 | X18: 881.4 | Y18: 63.191798 | Z18: 200.60012 | AA18: 199.39427 | AB18: 200.60012 | AC18: 99.706985 | AD18: 99.33597 | AE18: 99.706985 | AF18: 7.296592 | AH18: =IF(ISNUMBER(AG18),AG18,AF18) -> 7.296592 | AI18: 44919.976
... B384: 44439 | C384: 0.054039459 | D384: =VLOOKUP($B384,[1]OIS!$A$6:$B$43,2) -> #N/A | E384: =_xlfn.IFNA(D384,C384) -> 0.054039459 | F384: 112.04392 | G384: 111.72984 | H384: 112.04392 | I384: 112.23762 | J384: 115.16692 | K384: 107.84306 | L384: 115.49967 | M384: 119.90107 | N384: 104.27482 | O384: 1727285 | P384: 0.89296472 | Q384: 0.89875707 | R384: 0.89296472 | S384: 97.8608 | T384: 614601.63 | U384: 97.8608 | V384: 1033.8 | W384: 1034301.6 | X384: 1033.8 | Y384: 94.66125 | Z384: 535.15698 | AA384: 534.82867 | AB384: 535.15698 | AC384: 81.959232 | AD384: 81.801005 | AE384: 81.959232 | AF384: 3.1 | AH384: =IF(ISNUMBER(AG384),AG384,AF384) -> 3.1 | AI384: 53949.711
B385: 44469 | C385: 0.062003047 | D385: =VLOOKUP($B385,[1]OIS!$A$6:$B$43,2) -> #N/A | E385: =_xlfn.IFNA(D385,C385) -> 0.062003047 | F385: 112.29841 | G385: 112.5714 | H385: 112.29841 | I385: 112.63008 | J385: 115.60229 | K385: 108.09541 | L385: 115.72094 | M385: 120.41608 | N385: 104.49563 | O385: 1733372 | P385: 0.90776882 | Q385: 0.90937398 | R385: 0.90776882 | S385: 98.5057 | T385: 616924.19 | U385: 98.5057 | V385: 1032.2 | W385: 1035102.9 | X385: 1032.2 | Y385: 95.432765 | Z385: 536.65908 | AA385: 536.98926 | AB385: 536.65908 | AC385: 81.535259 | AD385: 81.575595 | AE385: 81.535259 | AF385: 4.1052632 | AG385: 4.5810854 | AH385: =IF(ISNUMBER(AG385),AG385,AF385) -> 4.5810854 | AI385: 53990.307
B386: 44500 | C386: 0.19222367 | D386: =VLOOKUP($B386,[1]OIS!$A$6:$B$43,2) -> #N/A | E386: =_xlfn.IFNA(D386,C386) -> 0.19222367 | F386: 113.37995 | G386: 113.5362 | H386: 113.37995 | I386: 113.30009 | J386: 116.24679 | K386: 108.78364 | L386: 124.71809 | M386: 119.96588 | N386: 104.9904 | O386: 1741536 | P386: 0.92082743 | Q386: 0.92055208 | R386: 0.92082743 | S386: 98.8219 | T386: 621133.22 | U386: 98.8219 | V386: 1030.6 | W386: 1035700.1 | X386: 1030.6 | Y386: 95.887735 | Z386: 540.23629 | AA386: 540.01024 | AB386: 540.23629 | AC386: 82.019843 | AD386: 81.405603 | AE386: 82.019843 | AF386: 4.4 | AG386: 5.3216281 | AH386: =IF(ISNUMBER(AG386),AG386,AF386) -> 5.3216281 | AI386: 54031.429
B387: 44530 | C387: 0.17908085 | D387: =VLOOKUP($B387,[1]OIS!$A$6:$B$43,2) -> #N/A | E387: =_xlfn.IFNA(D387,C387) -> 0.17908085 | F387: 114.28919 | G387: 114.33924 | H387: 114.28919 | I387: 114.02068 | J387: 116.74464 | K387: 109.73562 | L387: 127.64618 | M387: 123.04402 | N387: 105.93553 | O387: 1745411 | P387: 0.92593401 | Q387: 0.92883714 | R387: 0.92593401 | S387: 99.2879 | T387: 625156.8 | U387: 99.2879 | V387: 1036.8 | W387: 1036573.9 | X387: 1036.8 | Y387: 95.763792 | Z387: 542.8181 | AA387: 543.5187 | AB387: 542.8181 | AC387: 81.441623 | AD387: 81.488184 | AE387: 81.441623 | AF387: 4.0349206 | AG387: 5.6783207 | AH387: =IF(ISNUMBER(AG387),AG387,AF387) -> 5.6783207 | AI387: 54073.144
B388: 44561 | C388: 0.23633779 | D388: =VLOOKUP($B388,[1]OIS!$A$6:$B$43,2) -> #N/A | E388: =_xlfn.IFNA(D388,C388) -> 0.23633779 | F388: 115.00529 | G388: 114.83517 | H388: 115.00529 | I388: 114.56768 | J388: 117.14816 | K388: 110.56181 | L388: 127.61071 | M388: 122.99701 | N388: 106.85823 | O388: 1748281 | P388: 0.93993219 | Q388: 0.9324812 | R388: 0.93993219 | S388: 99.1591 | T388: 627504.21 | U388: 99.1591 | V388: 1036.2 | W388: 1038059.3 | X388: 1036.2 | Y388: 95.694943 | Z388: 547.65411 | AA388: 547.17792 | AB388: 547.65411 | AC388: 81.375091 | AD388: 81.906558 | AE388: 81.375091 | AF388: 4.0140351 | AG388: 5.8838311 | AH388: =IF(ISNUMBER(AG388),AG388,AF388) -> 5.8838311 | AI388: 54115.366
B389: 44592 | C389: 0.42352663 | D389: =VLOOKUP($B389,[1]OIS!$A$6:$B$43,2) -> #N/A | E389: =_xlfn.IFNA(D389,C389) -> 0.42352663 | F389: 115.60479 | G389: 115.32623 | H389: 115.60479 | I389: 115.29056 | J389: 117.69699 | K389: 111.40341 | L389: 127.59737 | M389: 122.76481 | N389: 107.79641 | O389: 1754523 | P389: 0.93842933 | Q389: 0.93521619 | R389: 0.93842933 | S389: 99.388 | T389: 628521.93 | U389: 99.388 | V389: 1041.6 | W389: 1040087.5 | X389: 1041.6 | Y389: 95.418587 | Z389: 552.52548 | AA389: 550.7874 | AB389: 552.52548 | AC389: 82.6933 | AD389: 82.384475 | AE389: 82.6933 | AF389: 4.8173759 | AG389: 6.6732619 | AH389: =IF(ISNUMBER(AG389),AG389,AF389) -> 6.6732619 | AI389: 54158.151
B390: 44620 | C390: 0.70906908 | D390: =VLOOKUP($B390,[1]OIS!$A$6:$B$43,2) -> #N/A | E390: =_xlfn.IFNA(D390,C390) -> 0.70906908 | F390: 116.43191 | G390: 116.18433 | H390: 116.43191 | I390: 115.91557 | J390: 118.10063 | K390: 112.10513 | L390: 128.9026 | M390: 123.20955 | N390: 108.65156 | O390: 1760182 | P390: 0.93981311 | Q390: 0.94194363 | R390: 0.93981311 | S390: 99.9572 | T390: 629074.46 | U390: 99.9572 | V390: 1042.3 | W390: 1042273.7 | X390: 1042.3 | Y390: 95.900604 | Z390: 552.965 | AA390: 553.90838 | AB390: 552.965 | AC390: 82.55288 | AD390: 82.516788 | AE390: 82.55288 | AF390: 5.5529801 | AG390: 7.4626927 | AH390: =IF(ISNUMBER(AG390),AG390,AF390) -> 7.4626927 | AI390: 54198.001
B391: 44651 | C391: 0.86963763 | D391: =VLOOKUP($B391,[1]OIS!$A$6:$B$43,2) -> #N/A | E391: =_xlfn.IFNA(D391,C391) -> 0.86963763 | F391: 117.53711 | G391: 117.65288 | H391: 117.53711 | I391: 116.59082 | J391: 118.77919 | K391: 112.8881 | L391: 135.86741 | M391: 124.0161 | N391: 108.94367 | O391: 1767407 | P391: 0.95218368 | Q391: 0.95587871 | R391: 0.95218368 | S391: 99.923 | T391: 629843.4 | U391: 99.923 | V391: 1045.4 | W391: 1044443.9 | X391: 1045.4 | Y391: 95.583509 | Z391: 555.78354 | AA391: 556.59279 | AB391: 555.78354 | AC391: 81.775483 | AD391: 82.079132 | AE391: 81.775483 | AF391: 6.0544652 | AG391: 8.2521236 | AH391: =IF(ISNUMBER(AG391),AG391,AF391) -> 8.2521236 | AI391: 54236.797
B392: 44681 | C392: 1.0133573 | D392: =VLOOKUP($B392,[1]OIS!$A$6:$B$43,2) -> #N/A | E392: =_xlfn.IFNA(D392,C392) -> 1.0133573 | F392: 119.80757 | G392: 119.4285 | H392: 119.80757 | I392: 116.98765 | J392: 119.43815 | K392: 113.10824 | L392: 170.25312 | M392: 124.04537 | N392: 110.50775 | O392: 1772933 | P392: 0.97670493 | Q392: 0.9744984 | R392: 0.97670493 | S392: 99.9317 | T392: 630750.44 | U392: 99.9317 | V392: 1047.1 | W392: 1046264.2 | X392: 1047.1 | Y392: 95.436635 | Z392: 558.18575 | AA392: 559.08041 | AB392: 558.18575 | AC392: 81.311343 | AD392: 81.195381 | AE392: 81.311343 | AF392: 6.0068027 | AG392: 8.8679537 | AH392: =IF(ISNUMBER(AG392),AG392,AF392) -> 8.8679537 | AI392: 54277.383
B393: 44712 | C393: 1.1919728 | D393: =VLOOKUP($B393,[1]OIS!$A$6:$B$43,2) -> #N/A | E393: =_xlfn.IFNA(D393,C393) -> 1.1919728 | F393: 120.24881 | G393: 120.89505 | H393: 120.24881 | I393: 117.38358 | J393: 119.88314 | K393: 113.36568 | L393: 172.14236 | M393: 124.51159 | N393: 112.1956 | O393: 1780220 | P393: 0.98337344 | Q393: 0.99210993 | R393: 0.98337344 | S393: 100.4501 | T393: 631409.32 | U393: 100.4501 | V393: 1046.8 | W393: 1047185.2 | X393: 1046.8 | Y393: 95.959209 | Z393: 562.39259 | AA393: 561.52981 | AB393: 562.39259 | AC393: 79.907191 | AD393: 80.15766 | AE393: 79.907191 | AF393: 6.112337 | AG393: 9.1142857 | AH393: =IF(ISNUMBER(AG393),AG393,AF393) -> 9.1142857 | AI393: 54320.646
B394: 44742 | C394: 1.4614025 | D394: =VLOOKUP($B394,[1]OIS!$A$6:$B$43,2) -> #N/A | E394: =_xlfn.IFNA(D394,C394) -> 1.4614025 | F394: 121.30906 | G394: 121.69867 | H394: 121.30906 | I394: 117.92887 | J394: 120.57748 | K394: 113.81273 | L394: 178.86618 | M394: 125.10723 | N394: 113.72304 | O394: 1783458 | P394: 1.0027232 | Q394: 1.0048564 | R394: 1.0027232 | S394: 99.5098 | T394: 631609.19 | U394: 99.5098 | V394: 1044.4 | W394: 1047010.6 | X394: 1044.4 | Y394: 95.279395 | Z394: 564.21788 | AA394: 564.18829 | AB394: 564.21788 | AC394: 79.332827 | AD394: 79.219969 | AE394: 79.332827 | AF394: 6.1069032 | AG394: 9.1142857 | AH394: =IF(ISNUMBER(AG394),AG394,AF394) -> 9.1142857 | AI394: 54368.052
B395: 44773 | C395: 1.7033949 | D395: =VLOOKUP($B395,[1]OIS!$A$6:$B$43,2) -> #N/A | E395: =_xlfn.IFNA(D395,C395) -> 1.7033949 | F395: 122.52221 | G395: 122.15825 | H395: 122.52221 | I395: 118.50799 | J395: 121.27215 | K395: 114.25803 | L395: 181.23469 | M395: 125.74357 | N395: 116.53972 | O395: 1788506 | P395: 1.0043677 | Q395: 1.0135395 | R395: 1.0043677 | S395: 100.1071 | T395: 631607.16 | U395: 100.1071 | V395: 1052 | W395: 1046316 | X395: 1052 | Y395: 95.15884 | Z395: 567.71069 | AA395: 567.26199 | AB395: 567.71069 | AC395: 78.947014 | AD395: 78.507206 | AE395: 78.947014 | AF395: 6.0179671 | AG395: 8.9911197 | AH395: =IF(ISNUMBER(AG395),AG395,AF395) -> 8.9911197 | AI395: 54418.969
B396: 44804 | C396: 2.1014639 | D396: =VLOOKUP($B396,[1]OIS!$A$6:$B$43,2) -> #N/A | E396: =_xlfn.IFNA(D396,C396) -> 2.1014639 | F396: 123.15881 | G396: 122.83806 | H396: 123.15881 | I396: 119.24671 | J396: 121.98231 | K396: 114.93345 | L396: 175.56023 | M396: 126.38875 | N396: 117.901 | O396: 1793502 | P396: 1.026117 | Q396: 1.0207085 | R396: 1.026117 | S396: 100.1539 | T396: 631826.94 | U396: 100.1539 | V396: 1046.3 | W396: 1045948.8 | X396: 1046.3 | Y396: 95.721973 | Z396: 570.93959 | AA396: 570.9991 | AB396: 570.93959 | AC396: 79.137413 | AD396: 78.093127 | AE396: 79.137413 | AF396: 10.325424 | AH396: =IF(ISNUMBER(AG396),AG396,AF396) -> 10.325424 | AI396: 54472.859
B397: 44834 | C397: 2.7917572 | D397: =VLOOKUP($B397,[1]OIS!$A$6:$B$43,2) -> #N/A | E397: =_xlfn.IFNA(D397,C397) -> 2.7917572 | F397: 123.69179 | G397: 124.05356 | H397: 123.69179 | I397: 119.96687 | J397: 122.67093 | K397: 115.62806 | L397: 173.07017 | M397: 127.00861 | N397: 119.66513 | O397: 1801665 | P397: 1.0448134 | Q397: 1.0281021 | R397: 1.0448134 | S397: 99.5746 | T397: 632514.23 | U397: 99.5746 | V397: 1045.4 | W397: 1046560.4 | X397: 1045.4 | Y397: 95.250239 | Z397: 574.77591 | AA397: 575.2992 | AB397: 574.77591 | AC397: 76.369227 | AD397: 78.010608 | AE397: 76.369227 | AF397: 8.6216216 | AH397: =IF(ISNUMBER(AG397),AG397,AF397) -> 8.6216216 | AI397: 54526.816
B398: 44865 | C398: 3.2273459 | D398: =VLOOKUP($B398,[1]OIS!$A$6:$B$43,2) -> #N/A | E398: =_xlfn.IFNA(D398,C398) -> 3.2273459 | F398: 125.92266 | G398: 125.51772 | H398: 125.92266 | I398: 120.63038 | J398: 123.46889 | K398: 116.11171 | L398: 198.35063 | M398: 127.49613 | N398: 122.01935 | O398: 1806126 | P398: 1.0472199 | Q398: 1.0364364 | R398: 1.0472199 | S398: 100.4901 | T398: 633433.2 | U398: 100.4901 | V398: 1044.5 | W398: 1048164.5 | X398: 1044.5 | Y398: 96.208808 | Z398: 579.48653 | AA398: 579.7491 | AB398: 579.48653 | AC398: 77.017338 | AD398: 78.095141 | AE398: 77.017338 | AF398: 8.6753247 | AH398: =IF(ISNUMBER(AG398),AG398,AF398) -> 8.6753247 | AI398: 54581.228
B399: 44895 | C399: 3.387491 | D399: =VLOOKUP($B399,[1]OIS!$A$6:$B$43,2) -> #N/A | E399: =_xlfn.IFNA(D399,C399) -> 3.387491 | F399: 126.54478 | G399: 126.7346 | H399: 126.54478 | I399: 121.30389 | J399: 124.17942 | K399: 116.76564 | L399: 198.67779 | M399: 127.96646 | N399: 123.3009 | O399: 1811787 | P399: 1.0466666 | Q399: 1.0458428 | R399: 1.0466666 | S399: 100.4582 | T399: 634190.64 | U399: 100.4582 | V399: 1050.7 | W399: 1050568.7 | X399: 1050.7 | Y399: 95.610736 | Z399: 584.27157 | AA399: 583.72905 | AB399: 584.27157 | AC399: 78.144836 | AD399: 78.134696 | AE399: 78.144836 | AF399: 7.2732558 | AH399: =IF(ISNUMBER(AG399),AG399,AF399) -> 7.2732558 | AI399: 54635.841
B400: 44926 | C400: 3.6502079 | D400: =VLOOKUP($B400,[1]OIS!$A$6:$B$43,2) -> #N/A | E400: =_xlfn.IFNA(D400,C400) -> 3.6502079 | F400: 127.15818 | G400: 127.38858 | H400: 127.15818 | I400: 121.89192 | J400: 125.12828 | K400: 117.07723 | L400: 195.01834 | M400: 127.53896 | N400: 124.83544 | O400: 1813974 | P400: 1.045407 | Q400: 1.0559447 | R400: 1.045407 | S400: 100.0564 | T400: 634512.89 | U400: 100.0564 | V400: 1053.2 | W400: 1053476.9 | X400: 1053.2 | Y400: 95.002279 | Z400: 586.61534 | AA400: 586.90405 | AB400: 586.61534 | AC400: 79.027264 | AD400: 78.009659 | AE400: 79.027264 | AF400: 5.6899642 | AH400: =IF(ISNUMBER(AG400),AG400,AF400) -> 5.6899642 | AI400: 54690.481
B401: 44957 | C401: 3.8769153 | D401: =VLOOKUP($B401,[1]OIS!$A$6:$B$43,2) -> #N/A | E401: =_xlfn.IFNA(D401,C401) -> 3.8769153 | F401: 127.28997 | G401: 127.74264 | H401: 127.28997 | I401: 122.08641 | J401: 124.85259 | K401: 117.70345 | L401: 192.97081 | M401: 129.07944 | N401: 125.80401 | O401: 1815752 | P401: 1.0635174 | Q401: 1.0648945 | R401: 1.0635174 | S401: 100.318 | T401: 634506.22 | U401: 100.318 | V401: 1055.1 | W401: 1056264.9 | X401: 1055.1 | Y401: 95.079139 | Z401: 588.60727 | AA401: 589.89312 | AB401: 588.60727 | AC401: 78.265059 | AD401: 77.884127 | AE401: 78.265059 | AF401: 5.351145 | AH401: =IF(ISNUMBER(AG401),AG401,AF401) -> 5.351145 | AI401: 54746.083
B402: 44985 | C402: 4.0745574 | D402: =VLOOKUP($B402,[1]OIS!$A$6:$B$43,2) -> #N/A | E402: =_xlfn.IFNA(D402,C402) -> 4.0745574 | F402: 128.58169 | G402: 128.19999 | H402: 128.58169 | I402: 123.21658 | J402: 126.07061 | K402: 118.61581 | L402: 192.00921 | M402: 130.16514 | N402: 128.29387 | O402: 1816527 | P402: 1.0716875 | Q402: 1.0698697 | R402: 1.0716875 | S402: 100.6724 | T402: 634401.9 | U402: 100.6724 | V402: 1057.5 | W402: 1058036.4 | X402: 1057.5 | Y402: 95.198487 | Z402: 594.58795 | AA402: 593.31353 | AB402: 594.58795 | AC402: 77.81528 | AD402: 78.005467 | AE402: 77.81528 | AF402: 5.6055363 | AH402: =IF(ISNUMBER(AG402),AG402,AF402) -> 5.6055363 | AI402: 54799.158
